Workbook
Name LST_LOC: Locations!$A$5:$A$34
Name LST_TRE: Treasuries!$A$5:$A$34
Name LST_PM: Payment_Methods!$A$5:$A$19
Name LST_CC: Cost_Centers!$A$5:$A$34
Name LST_SUP: Suppliers!$A$5:$A$154
Name LST_CUS: Customers!$A$5:$A$104
Name LST_EMP: Employees!$A$5:$A$104
Name LST_ACCT: COA!$A$5:$A$254
Name LST_USER: Users!$B$5:$B$44
Name LST_UNIT: Units!$A$5:$A$34
Name LST_ITEM: Items!$A$5:$A$304
Name ST_DRAFT: Lists!$A$5
Name ST_APPR: Lists!$A$6
Name ST_POST: Lists!$A$7
Name ST_REV: Lists!$A$8
Name ST_CANC: Lists!$A$9
Name LST_STATUS: Lists!$A$5:$A$9
Name LST_VTYPE: Lists!$E$5:$E$11
Name LST_ITYPE: Lists!$J$5:$J$7
Name LST_EMODE: Lists!$N$5:$N$6
Name LST_YN: Lists!$R$5:$R$6
Name LST_CATS: Lists!$T$5:$T$8
Name LST_JETYPE: Lists!$W$5:$W$14
Name LST_RSN: Lists!$Y$5:$Y$13
Name LST_RES: Lists!$AA$5:$AA$7
Name LST_CF: Lists!$AC$5:$AC$9
Name LST_TTYPE: Lists!$AF$5:$AF$7
Name LST_LTYPE: Lists!$AH$5:$AH$8
Name LST_ATYPE: Lists!$AJ$5:$AJ$10
Name LST_PMTYPE: Lists!$AM$5:$AM$8
Name LST_ROLE: Lists!$AO$5:$AO$14
Name S_FYStart: Settings!$C$8
Name S_From: Settings!$C$9
Name S_To: Settings!$C$10
Name S_Branch: Settings!$C$11
Name S_CC: Settings!$C$12
Name S_PeriodID: Settings!$C$13
Name S_PFrom: Settings!$C$14
Name S_PTo: Settings!$C$15
Name S_CogsMethod: Settings!$C$16
Name S_Tol: Settings!$C$17
Name S_PlatDays: Settings!$C$18
Name S_CashTol: Settings!$C$19
Name S_Mode: Settings!$C$20
Name S_VATOn: Tax_Settings!$C$5
Name S_VATRate: Tax_Settings!$C$6
Name S_VATF: Tax_Settings!$C$7
Name LG_Acct: GL_Ledger!$B$4
Name LG_Party: GL_Ledger!$B$5
Name LG_Loc: GL_Ledger!$B$6
Name LG_CC: GL_Ledger!$B$7
Name LG_From: GL_Ledger!$B$8
Name LG_To: GL_Ledger!$B$9
Name LG_Open: GL_Ledger!$E$5
Name TB_From: Trial_Balance!$C$4
Name TB_To: Trial_Balance!$C$5
Name TB_Branch: Trial_Balance!$C$6
Name TB_CC: Trial_Balance!$C$7
Name TB_LOCC: Trial_Balance!$E$4
Name TB_CCC: Trial_Balance!$E$5

Sheet Dashboard
B1: لوحة التحكم الرئيسية - مطاعم ستاموني
B2: ="الفترة: "&YEAR(S_From)&"-"&TEXT(MONTH(S_From),"00")&"-"&TEXT(DAY(S_From),"00")&" → "&YEAR(S_To)&"-"&TEXT(MONTH(S_To),"00")&"-"&TEXT(DAY(S_To),"00")&" | الفرع: "&S_Branch&" | وضع البيانات: "&S_Mode&" | العملة: EGP"
B3: =IS_Banner
B5: مبيعات آخر يوم مسجل | D5: إجمالي مبيعات الفترة | F5: صافي المبيعات | H5: عدد الطلبات | J5: متوسط قيمة الطلب | L5: ="مجمل الربح"&IF(CK_Critical>0," (أولي)","")
B6: =SUMIFS(Sales_Daily!$Z:$Z,Sales_Daily!$B:$B,_xlfn.MAXIFS(Sales_Daily!$B:$B,Sales_Daily!$B:$B,"<="&S_To,Sales_Daily!$AY:$AY,1),Sales_Daily!$AY:$AY,1) | D6: =IS_GrossSales | F6: =IS_NetSales | H6: =SUMIFS(Sales_Daily!$D:$D,Sales_Daily!$B:$B,">="&S_From,Sales_Daily!$B:$B,"<="&S_To,Sales_Daily!$AY:$AY,1) | J6: =IF(H6=0,"غير متوفر",SUMIFS(Sales_Daily!$AA:$AA,Sales_Daily!$B:$B,">="&S_From,Sales_Daily!$B:$B,"<="&S_To,Sales_Daily!$AY:$AY,1)/H6) | L6: =IS_GrossProfit
B7: =IF(_xlfn.MAXIFS(Sales_Daily!$B:$B,Sales_Daily!$B:$B,"<="&S_To,Sales_Daily!$AY:$AY,1)=0,"لا مبيعات مرحلة","بتاريخ "&YEAR(_xlfn.MAXIFS(Sales_Daily!$B:$B,Sales_Daily!$B:$B,"<="&S_To,Sales_Daily!$AY:$AY,1))&"-"&TEXT(MONTH(_xlfn.MAXIFS(Sales_Daily!$B:$B,Sales_Daily!$B:$B,"<="&S_To,Sales_Daily!$AY:$AY,1)),"00")&"-"&TEXT(DAY(_xlfn.MAXIFS(Sales_Daily!$B:$B,Sales_Daily!$B:$B,"<="&S_To,Sales_Daily!$AY:$AY,1)),"00")) | D7: قبل الخصومات والمرتجعات | F7: =IF(IS_NetSales_P=0,"المقارنة: لا توجد فترة سابقة","السابقة: "&TEXT(IS_NetSales_P,"#,##0")&" ("&TEXT((IS_NetSales-IS_NetSales_P)/ABS(IS_NetSales_P),"+0%;-0%")&")") | H7: من تقارير المبيعات المرحلة | J7: صافي المبيعات ÷ عدد الطلبات | L7: =IF(IS_GrossProfit_P=0,"المقارنة: لا توجد فترة سابقة","السابقة: "&TEXT(IS_GrossProfit_P,"#,##0")&" ("&TEXT((IS_GrossProfit-IS_GrossProfit_P)/ABS(IS_GrossProfit_P),"+0%;-0%")&")")
B9: ="صافي الربح"&IF(CK_Critical>0," (أولي - غير مؤكد)"," (مؤكد)") | D9: نسبة تكلفة المبيعات | F9: المصروفات التشغيلية | H9: قيمة المخزون | J9: مستحقات منصات التوصيل والبطاقات | L9: أرصدة الموردين
B10: =IS_NetProfit | D10: =IF(IS_NetSales=0,"-",IS_COGS/IS_NetSales) | F10: =IS_OpEx | H10: =(SUMIFS(GL_Journal!$S:$S,GL_Journal!$G:$G,">=1400",GL_Journal!$G:$G,"<=1499",GL_Journal!$D:$D,"<="&S_To)-SUMIFS(GL_Journal!$T:$T,GL_Journal!$G:$G,">=1400",GL_Journal!$G:$G,"<=1499",GL_Journal!$D:$D,"<="&S_To)) | J10: =(SUMIFS(GL_Journal!$S:$S,GL_Journal!$G:$G,">=1302",GL_Journal!$G:$G,"<=1304",GL_Journal!$D:$D,"<="&S_To)-SUMIFS(GL_Journal!$T:$T,GL_Journal!$G:$G,">=1302",GL_Journal!$G:$G,"<=1304",GL_Journal!$D:$D,"<="&S_To)) | L10: =SB_Total
B11: =IF(IS_NetProfit_P=0,"المقارنة: لا توجد فترة سابقة","السابقة: "&TEXT(IS_NetProfit_P,"#,##0")&" ("&TEXT((IS_NetProfit-IS_NetProfit_P)/ABS(IS_NetProfit_P),"+0%;-0%")&")") | D11: تكلفة المبيعات ÷ صافي المبيعات | F11: =IF(IS_OpEx_P=0,"المقارنة: لا توجد فترة سابقة","السابقة: "&TEXT(IS_OpEx_P,"#,##0")&" ("&TEXT((IS_OpEx-IS_OpEx_P)/ABS(IS_OpEx_P),"+0%;-0%")&")") | H11: حسابات 1400-1499 (دفتريًا) | J11: 1302-1304 غير محصلة | L11: إجمالي المستحق للموردين
B13: الهالك (طبيعي وغير طبيعي) | D13: فروق الجرد (مخزون) | F13: فروق الخزائن (عجز - زيادة) | H13: أرصدة البنوك | J13: النقدية بالخزائن | L13: مديونيات العملاء المستحقة
B14: =(SUMIFS(GL_Journal!$S:$S,GL_Journal!$G:$G,">=5200",GL_Journal!$G:$G,"<=5299",GL_Journal!$D:$D,">="&S_From,GL_Journal!$D:$D,"<="&S_To)-SUMIFS(GL_Journal!$T:$T,GL_Journal!$G:$G,">=5200",GL_Journal!$G:$G,"<=5299",GL_Journal!$D:$D,">="&S_From,GL_Journal!$D:$D,"<="&S_To)) | D14: =(SUMIFS(GL_Journal!$S:$S,GL_Journal!$G:$G,">=5400",GL_Journal!$G:$G,"<=5499",GL_Journal!$D:$D,">="&S_From,GL_Journal!$D:$D,"<="&S_To)-SUMIFS(GL_Journal!$T:$T,GL_Journal!$G:$G,">=5400",GL_Journal!$G:$G,"<=5499",GL_Journal!$D:$D,">="&S_From,GL_Journal!$D:$D,"<="&S_To)) | F14: =(SUMIFS(GL_Journal!$S:$S,GL_Journal!$G:$G,ACC_CASH_SHORT,GL_Journal!$D:$D,">="&S_From,GL_Journal!$D:$D,"<="&S_To)-SUMIFS(GL_Journal!$T:$T,GL_Journal!$G:$G,ACC_CASH_SHORT,GL_Journal!$D:$D,">="&S_From,GL_Journal!$D:$D,"<="&S_To))-(-(SUMIFS(GL_Journal!$S:$S,GL_Journal!$G:$G,ACC_CASH_OVER,GL_Journal!$D:$D,">="&S_From,GL_Journal!$D:$D,"<="&S_To)-SUMIFS(GL_Journal!$T:$T,GL_Journal!$G:$G,ACC_CASH_OVER,GL_Journal!$D:$D,">="&S_From,GL_Journal!$D:$D,"<="&S_To))) | H14: =(SUMIFS(GL_Journal!$S:$S,GL_Journal!$G:$G,">=1200",GL_Journal!$G:$G,"<=1299",GL_Journal!$D:$D,"<="&S_To)-SUMIFS(GL_Journal!$T:$T,GL_Journal!$G:$G,">=1200",GL_Journal!$G:$G,"<=1299",GL_Journal!$D:$D,"<="&S_To)) | J14: =(SUMIFS(GL_Journal!$S:$S,GL_Journal!$G:$G,">=1100",GL_Journal!$G:$G,"<=1199",GL_Journal!$D:$D,"<="&S_To)-SUMIFS(GL_Journal!$T:$T,GL_Journal!$G:$G,">=1100",GL_Journal!$G:$G,"<=1199",GL_Journal!$D:$D,"<="&S_To)) | L14: =(SUMIFS(GL_Journal!$S:$S,GL_Journal!$G:$G,ACC_CUSTOMERS,GL_Journal!$D:$D,"<="&S_To)-SUMIFS(GL_Journal!$T:$T,GL_Journal!$G:$G,ACC_CUSTOMERS,GL_Journal!$D:$D,"<="&S_To))
B15: المرحلة 2 للتفصيل | D15: موجب = عجز | F15: موجب = عجز صافٍ | L15: حساب 1301
A21: رصيد كل خزينة وبنك (Treasury_Balances)
B22: الكود | C22: الاسم | F22: الرصيد الختامي | H22: تنبيه
B23: =Treasury_Balances!$A$9 | C23: =Treasury_Balances!$B$9 | F23: =Treasury_Balances!$I$9 | H23: =Treasury_Balances!$L$9
B24: =Treasury_Balances!$A$10 | C24: =Treasury_Balances!$B$10 | F24: =Treasury_Balances!$I$10 | H24: =Treasury_Balances!$L$10
B25: =Treasury_Balances!$A$11 | C25: =Treasury_Balances!$B$11 | F25: =Treasury_Balances!$I$11 | H25: =Treasury_Balances!$L$11
B26: =Treasury_Balances!$A$12 | C26: =Treasury_Balances!$B$12 | F26: =Treasury_Balances!$I$12 | H26: =Treasury_Balances!$L$12
B27: =Treasury_Balances!$A$13 | C27: =Treasury_Balances!$B$13 | F27: =Treasury_Balances!$I$13 | H27: =Treasury_Balances!$L$13
B28: =Treasury_Balances!$A$14 | C28: =Treasury_Balances!$B$14 | F28: =Treasury_Balances!$I$14 | H28: =Treasury_Balances!$L$14
B29: =Treasury_Balances!$A$15 | C29: =Treasury_Balances!$B$15 | F29: =Treasury_Balances!$I$15 | H29: =Treasury_Balances!$L$15
B30: =Treasury_Balances!$A$16 | C30: =Treasury_Balances!$B$16 | F30: =Treasury_Balances!$I$16 | H30: =Treasury_Balances!$L$16
B31: =Treasury_Balances!$A$17 | C31: =Treasury_Balances!$B$17 | F31: =Treasury_Balances!$I$17 | H31: =Treasury_Balances!$L$17
B32: =Treasury_Balances!$A$18 | C32: =Treasury_Balances!$B$18 | F32: =Treasury_Balances!$I$18 | H32: =Treasury_Balances!$L$18
A35: مقارنة أداء الفروع (من قائمة الدخل - بدون توزيع تكاليف الإدارة)
B36: الفرع | C36: إجمالي المبيعات | D36: صافي المبيعات | E36: تكلفة المبيعات | F36: مجمل الربح | G36: % مجمل الربح | H36: مصروفات مباشرة | I36: الربح التشغيلي
B37: =Income_Statement!I$11 | C37: =IF(B37="","",Income_Statement!I17) | D37: =IF(B37="","",Income_Statement!I20) | E37: =IF(B37="","",Income_Statement!I26) | F37: =IF(B37="","",Income_Statement!I27) | G37: =IF(B37="","",IF(D37=0,0,F37/D37)) | H37: =IF(B37="","",Income_Statement!I38) | I37: =IF(B37="","",Income_Statement!I39)
B38: =Income_Statement!J$11 | C38: =IF(B38="","",Income_Statement!J17) | D38: =IF(B38="","",Income_Statement!J20) | E38: =IF(B38="","",Income_Statement!J26) | F38: =IF(B38="","",Income_Statement!J27) | G38: =IF(B38="","",IF(D38=0,0,F38/D38)) | H38: =IF(B38="","",Income_Statement!J38) | I38: =IF(B38="","",Income_Statement!J39)
B39: =Income_Statement!K$11 | C39: =IF(B39="","",Income_Statement!K17) | D39: =IF(B39="","",Income_Statement!K20) | E39: =IF(B39="","",Income_Statement!K26) | F39: =IF(B39="","",Income_Statement!K27) | G39: =IF(B39="","",IF(D39=0,0,F39/D39)) | H39: =IF(B39="","",Income_Statement!K38) | I39: =IF(B39="","",Income_Statement!K39)
B40: =Income_Statement!L$11 | C40: =IF(B40="","",Income_Statement!L17) | D40: =IF(B40="","",Income_Statement!L20) | E40: =IF(B40="","",Income_Statement!L26) | F40: =IF(B40="","",Income_Statement!L27) | G40: =IF(B40="","",IF(D40=0,0,F40/D40)) | H40: =IF(B40="","",Income_Statement!L38) | I40: =IF(B40="","",Income_Statement!L39)
B41: =Income_Statement!M$11 | C41: =IF(B41="","",Income_Statement!M17) | D41: =IF(B41="","",Income_Statement!M20) | E41: =IF(B41="","",Income_Statement!M26) | F41: =IF(B41="","",Income_Statement!M27) | G41: =IF(B41="","",IF(D41=0,0,F41/D41)) | H41: =IF(B41="","",Income_Statement!M38) | I41: =IF(B41="","",Income_Statement!M39)
B42: =Income_Statement!N$11 | C42: =IF(B42="","",Income_Statement!N17) | D42: =IF(B42="","",Income_Statement!N20) | E42: =IF(B42="","",Income_Statement!N26) | F42: =IF(B42="","",Income_Statement!N27) | G42: =IF(B42="","",IF(D42=0,0,F42/D42)) | H42: =IF(B42="","",Income_Statement!N38) | I42: =IF(B42="","",Income_Statement!N39)
A44: المصروفات التشغيلية حسب النوع | E44: الحالية | F44: السابقة
B45: =Income_Statement!$A$29 | E45: =Income_Statement!$E$29 | F45: =Income_Statement!$G$29
B46: =Income_Statement!$A$30 | E46: =Income_Statement!$E$30 | F46: =Income_Statement!$G$30
B47: =Income_Statement!$A$31 | E47: =Income_Statement!$E$31 | F47: =Income_Statement!$G$31
B48: =Income_Statement!$A$32 | E48: =Income_Statement!$E$32 | F48: =Income_Statement!$G$32
B49: =Income_Statement!$A$33 | E49: =Income_Statement!$E$33 | F49: =Income_Statement!$G$33
B50: =Income_Statement!$A$34 | E50: =Income_Statement!$E$34 | F50: =Income_Statement!$G$34
B51: =Income_Statement!$A$35 | E51: =Income_Statement!$E$35 | F51: =Income_Statement!$G$35
B52: =Income_Statement!$A$36 | E52: =Income_Statement!$E$36 | F52: =Income_Statement!$G$36
B53: =Income_Statement!$A$37 | E53: =Income_Statement!$E$37 | F53: =Income_Statement!$G$37
A58: التنبيهات (Alerts)
B59: =IF(CK_Critical>0,"✖ "&CK_Critical&" بند حرج مفتوح في قائمة الإقفال - النتائج أولية","✔ لا توجد بنود إقفال حرجة مفتوحة")
B60: =IF(CK_Drafts+CK_Approved>0,"⚠ "&CK_Drafts&" مستند مسودة و"&CK_Approved&" معتمد غير مرحّل في الفترة","✔ كل مستندات الفترة مرحّلة أو ملغاة")
B61: =IF(CK_DocDup+CK_InvDup>0,"✖ مستندات مكررة: أرقام "&CK_DocDup&" وفواتير موردين "&CK_InvDup,"✔ لا توجد مستندات مكررة")
B62: =IF(CK_Unbal>0,"✖ "&CK_Unbal&" قيد يدوي غير متوازن لم يُرحَّل","✔ كل القيود اليدوية متوازنة")
B63: =IF(CK_NoRecon>0,"⚠ "&CK_NoRecon&" يوم مبيعات بدون مطابقة يومية","✔ المطابقة اليومية للمبيعات مكتملة")
B64: =IF(CK_ReconOpen+CK_CashOpen>0,"⚠ فروق مفتوحة: مبيعات "&CK_ReconOpen&" وخزائن "&CK_CashOpen,"✔ لا فروق مفتوحة في المبيعات والخزائن")
B65: =IF(CK_Stale>0,"⚠ "&CK_Stale&" منصة/بطاقات بمستحقات متأخرة التسوية","✔ تسويات المنصات منتظمة")
B66: =IF(SB_Overdue>0,"⚠ مستحقات موردين متأخرة: "&TEXT(SB_Overdue,"#,##0"),"✔ لا مستحقات موردين متأخرة")
B67: =IF(CK_NoRef>0,"⚠ "&CK_NoRef&" مستند مرحل بدون مرجع/مرفق ورقي","✔ كل المستندات المرحلة لها مرجع ورقي")
B68: =IF(CK_CogsMissing>0,"✖ قيد تسوية تكلفة المبيعات غير مسجل: الربح مبالغ فيه","✔ تكلفة المبيعات مسجلة")
B69: =IF(ABS(TB_Diff)>S_Tol,"✖ ميزان المراجعة غير متوازن","✔ ميزان المراجعة متوازن")

Sheet Guide
A1: دليل الأوراق (Sheet Guide)
A2: ابدأ من هنا: ماذا تفعل كل ورقة وماذا تدخل فيها. التفاصيل الكاملة في ملفات docs
A4: الورقة | B4: المجموعة | C4: الوظيفة | D4: المدخلات | E4: المخرجات | F4: ملاحظات
A5: Dashboard | B5: A/K | C5: لوحة التحكم الرئيسية | D5: لا إدخال | E5: مؤشرات ورسوم وتنبيهات | F5: —
A6: Guide | B6: A | C6: هذا الدليل وخريطة الأوراق | D6: — | E6: — | F6: —
A7: System_Map | B7: A | C7: خريطة النظام: الوحدات والمستندات والقيود | D7: — | E7: — | F7: —
A8: Settings | B8: A | C8: فترة التقارير وطريقة التكلفة وحدود السماح | D8: الخلايا الصفراء | E8: تتحكم في كل التقارير | F8: —
A9: Lists | B9: A | C9: القوائم المنسدلة وحالات المستندات | D9: المسؤول فقط | E9: — | F9: —
A10: COA | B10: A/J | C10: دليل الحسابات الموحد | D10: حساب جديد في صف فارغ | E10: يغذي القوائم والتقارير | F10: —
A11: Locations | B11: A | C11: الفروع والمخازن والمطابخ والإدارة | D11: صف لكل موقع | E11: — | F11: —
A12: Treasuries | B12: A/C | C12: الخزائن والبنوك وحساب كل منها | D12: صف لكل خزينة | E12: — | F12: —
A13: Users / Permissions | B13: A | C13: المستخدمون ومصفوفة الصلاحيات | D13: — | E13: — | F13: —
A14: Suppliers / Customers / Employees | B14: A | C14: الموردون والعملاء والموظفون | D14: — | E14: — | F14: —
A15: Items / Units / Unit_Conversions / Unit_Converter | B15: A/E | C15: الأصناف والوحدات والتحويل المعتمد ومحوّل مضبوط | D15: — | E15: — | F15: —
... A37: PR, Quotations, PO, GRN, Inventory_Moves, Stock_Count, Recipes, Production, Payroll, Fixed_Assets, Advances_Custody | B37: المراحل 2-3 | C37: هياكل جاهزة للمراحل القادمة | D37: — | E37: — | F37: لا تؤثر على الدفاتر بعد

Sheet System_Map
A1: خريطة النظام (System Map)
A2: الوحدات المالية والتشغيلية وحركة البيانات بينها
A4: الوحدة | B4: المستند الذي يبدأ الحركة | C4: من يعدّه | D4: من يعتمده | E4: القيد المحاسبي الناتج | F4: الأثر (خزينة / مخزون / تكلفة / ربح) | G4: التقارير | H4: المرحلة
A5: مبيعات الفرع اليومية | B5: تقرير مبيعات يومي (15) | C5: الكاشير / أمين الصندوق | D5: مدير الفرع ← المحاسب يرحّل | E5: مدين: تحصيل كل وسيلة دفع (خزينة / بطاقات / منصات) + خصومات + مرتجعات | دائن: إيراد كل فئة (+ضريبة) | F5: نقدية↑ أو مستحقات↑ | ربح↑ | مخزون: لا (التكلفة في التسوية الدورية) | G5: Income_Statement, Dashboard, Daily_Recon | H5: 1
A6: مطابقة المبيعات اليومية | B6: كشف إقفال (14) + تقرير الجهاز/المنصة | C6: أمين الصندوق | D6: مدير الفرع | E6: لا قيد؛ الفرق يُسجل بسند عجز/زيادة | F6: يكشف الفروق قبل أن تدخل الأرباح | G6: Daily_Recon, Close_Checklist | H6: 1
A7: تسوية المنصات والبطاقات | B7: كشف تسوية (16) | C7: المحاسب | D7: المدير المالي | E7: مدين: بنك + عمولة + خصومات (+1309) | دائن: مستحقات المنصة | F7: نقدية↑ | مستحقات↓ | ربح↓ بقيمة العمولة فقط | G7: Platform_Settlements, Balance_Sheet | H7: 1
A8: الخزائن وسندات القبض والصرف | B8: سند قبض (11) / صرف (12) | C8: أمين الصندوق | D8: المعتمد ← المحاسب | E8: قبض: مدين خزينة / دائن الحساب المقابل | صرف: العكس | F8: حسب الحساب المقابل | G8: Treasury_Balances, GL_Ledger | H8: 1
A9: التحويل بين الخزائن والبنوك | B9: إذن تحويل (13) | C9: المسلِّم والمستلم | D9: المعتمد | E9: مدين: الخزينة المستلمة / دائن: المسلِّمة | F9: لا أثر على الإيراد أو المصروف | G9: Treasury_Balances, Cash_Flow (تحويلات داخلية = 0) | H9: 1
A10: عجز وزيادة الخزينة | B10: كشف إقفال (14) + تسوية (30) | C10: أمين الصندوق | D10: مدير الفرع + المدير المالي | E10: عجز: مدين 6910 / دائن خزينة | زيادة: مدين خزينة / دائن 4210 | F10: نقدية↓/↑ | ربح↓/↑ | G10: Cash_Close, Dashboard | H10: 1
A11: المصروفات والمستحقات | B11: نموذج مصروفات (17) | C11: مقدم الطلب | D11: مدير الفرع/الإدارة ← المحاسب | E11: فوري: مدين مصروف / دائن خزينة | آجل: دائن 2201 | F11: ربح↓ بتاريخ الاستحقاق | نقدية بتاريخ الدفع | G11: Expenses, Income_Statement | H11: 1
A12: المشتريات (طلب ← أمر ← استلام ← فاتورة ← سداد) | B12: نماذج 1 و2 و3 + فاتورة المورد | C12: مشرف المشتريات / أمين المخزن | D12: معتمد الشراء ← المدير المالي | E12: فاتورة: مدين مخزون/أصل/مصروف / دائن 2101 | الطلب والأمر لا قيد لهما | F12: مخزون↑ والتزام↑ | لا أثر على الربح | G12: Supplier_Invoices, Supplier_Balances | H12: 1 (الفاتورة) / 2 (الطلب والأمر والاستلام)
A13: الموردون ودفعاتهم | B13: سند صرف (12) | C13: مشرف المشتريات | D13: المدير المالي | E13: مدين 2101 / دائن خزينة أو بنك | F13: التزام↓ ونقدية↓ | G13: Supplier_Payments, Supplier_Balances | H13: 1
A14: المخزون والتحويلات | B14: إذن استلام (3) / صرف (4) / تحويل (5) / جرد (10) | C14: أمين المخزن | D14: معتمد الصرف | E14: التحويل: مدين مخزون المستلم / دائن المسلِّم (بالتكلفة الدفترية) | F14: لا إيراد ولا تكلفة مبيعات | G14: Inventory_Moves (المرحلة 2) | H14: 2
A15: السنتر كيتشن والإنتاج | B15: نماذج 6 و7 و8 و9 | C15: مدير الإنتاج | D15: المدير المالي (للهالك غير الطبيعي) | E15: خام ← تحت التشغيل ← تام ← مخزون الفرع، والهالك بحساب منفصل | F15: لا إيراد؛ التكلفة تنتقل مع المنتج | G15: Production, Recipes (المرحلة 2) | H15: 2
... A21: التقارير | B21: — | C21: المحاسب | D21: — | E21: تقرأ من دفتر اليومية فقط | F21: — | G21: Trial_Balance, Income_Statement, Balance_Sheet, Cash_Flow, Dashboard | H21: 1

Sheet User_Manual
A1: دليل التشغيل المبسط لغير المحاسبين
A2: 14 إجراء بالترتيب: من المسؤول، المستند، الخطوات، الخانات، النتيجة، التحقق، الأخطاء الشائعة، المعتمِد
A4: م | B4: الإجراء | C4: من المسؤول؟ | D4: المستند المطلوب | E4: الخطوات بالترتيب | F4: الخانات التي يملؤها | G4: النتيجة المتوقعة | H4: كيف يعرف أنها تمت صحيحة | I4: الأخطاء الشائعة | J4: من يعتمد
A5: 1 | B5: كيف يبدأ المستخدم يومه | C5: مدير الفرع + أمين الصندوق (+ المحاسب في الإدارة) | D5: لا مستند (فحص بداية اليوم) | E5: 1) افتح ملف Satamoni_Financial_Management_System من رابط Google Sheets الذي شاركه المدير المالي. 2) افتح ورقة Dashboard وانظر الشريط الأعلى: إذا ظهر (نتائج أولية) فهذا طبيعي أثناء الشهر. 3) اقرأ قسم التنبيهات (Alerts): الأحمر = مشكلة تحتاج إجراء، الأصفر = مراجعة، الأخضر = سليم. 4) افتح نموذج الورق الجديد لليوم (تقرير المبيعات اليومي - نموذج 15) وتأكد أن الرقم المطبوع عليه هو التالي بعد آخر رقم استُخدم. 5) أمين الصندوق يعدّ الفكّة ويسجلها في كشف إقفال الأمس ليتأكد من الرصيد الافتتاحي. | F5: لا خانات. | G5: تعرف حالة الفرع والتنبيهات المعلقة قبل بدء البيع. | H5: لا توجد تنبيهات حمراء تخص فرعك. | I5: • البدء دون قراءة التنبيهات • استخدام رقم نموذج مكرر (النظام يمنع ترحيله) | J5: —
A6: 2 | B6: كيف يسجل المبيعات | C6: أمين الصندوق/الكاشير يعد، مدير الفرع يعتمد، المحاسب يرحّل | D6: تقرير مبيعات يومي (نموذج 15) | E6: 1) في آخر اليوم: اطبع تقرير نقطة البيع (أو اجمع الأرقام) واملأ نموذج 15: المبيعات حسب الفئة، الخصومات، المرتجعات، ثم التحصيل حسب وسيلة الدفع. 2) تأكد على الورق أن (مجموع وسائل الدفع = صافي المبيعات). 3) يوقّع الكاشير ومدير الفرع. 4) في Google Sheets افتح ورقة Sales_Daily وأضف صفًا جديدًا في أول صف فارغ (الخلايا الصفراء فقط). 5) املأ: رقم التقرير، التاريخ، الفرع، عدد الطلبات، المبيعات لكل فئة، الخصومات، المرتجعات، ثم تحصيل كل وسيلة دفع. 6) اختر الحالة (مسودة) ثم أخبر مدير الفرع ليختار نفسه في خانة (المعتمد) ويغيّر الحالة إلى (معتمد). 7) المحاسب يراجع ويغيّر الحالة إلى (مرحل) ويكتب اسمه في خانة (المحاسب المرحِّل). | F6: رقم التقرير، التاريخ، الفرع، عدد الطلبات، أربع خانات للفئات، الخصومات، المرتجعات، خمس خانات لوسائل الدفع، الحالة، المُعِد، المعتمد، المرحِّل، مرجع الورق. | G6: عمود (فحص المستند) فارغ، وعمود (فرق صافي - وسائل الدفع) = 0.00، وتظهر أسطر القيد في GL_Journal. | H6: Dashboard: مبيعات اليوم تساوي ما في النموذج الورقي. | I6: • كتابة الصافي في خانة الإجمالي • نسيان خانة تحصيل المنصة فيظهر فرق • ترك الحالة (مسودة): لن يظهر في التقارير • اختيار فرع خطأ | J6: مدير الفرع (اعتماد) ثم المحاسب (ترحيل)
A7: 3 | B7: كيف يغلق الخزينة | C7: أمين الصندوق يعد، مدير الفرع يعتمد، المحاسب يراجع | D7: كشف إقفال خزينة يومي (نموذج 14)، وعند الفرق نموذج 30 | E7: 1) عدّ النقدية الفعلية بالفئات واملأ نموذج 14. 2) في ورقة Cash_Close أضف صفًا: التاريخ، الخزينة، المبلغ المعدود. 3) اقرأ الرصيد الدفتري ثم عمود (فرق الجرد). إن كان صفرًا انتهيت. 4) إن وُجد فرق: اكتب سبب الفرق والمسؤول وحالة المعالجة، واملأ نموذج 30. 5) المحاسب يسجل في Cash_Vouchers سند (عجز خزينة) أو (زيادة خزينة) ويربط رقمه في Cash_Close. 6) في ورقة Daily_Recon سجل المطابقة اليومية لنقدي وكل وسيلة دفع (المتوقع من المبيعات ← الفعلي). | F7: التاريخ، الخزينة، المبلغ المعدود، السبب، المسؤول، الحالة، رقم سند التسوية. | G7: عمود (فرق متبقٍ بعد التسوية) = 0 ولا ظهور لـ (فحص). | H7: Cash_Close: الصف أخضر بلا تنبيه. Treasury_Balances: رصيد الخزينة = ما عددته. | I7: • إخفاء العجز في تعديل المبيعات • عدم كتابة اسم المسؤول عن الفرق • نسيان ربط رقم سند التسوية | J7: مدير الفرع + المحاسب
A8: 4 | B8: كيف يطلب شراء بضاعة | C8: طالب الشراء (أمين المخزن/مدير الفرع)، معتمد الشراء | D8: طلب شراء (نموذج 1) ثم أمر شراء (نموذج 2) | E8: 1) املأ نموذج 1: الأصناف والكميات والجهة وتاريخ الاحتياج. 2) يوقّع مدير الجهة، ثم يعتمد مشرف المشتريات. 3) مشرف المشتريات يصدر أمر شراء (نموذج 2) للمورد المعتمد ويحتفظ بالصورة. 4) في المرحلة 1: الطلب والأمر ورقيان فقط، ولا يُسجلان محاسبيًا. في المرحلة 2 سيُسجلان في ورقتي PR وPO. | F8: الجهة، التاريخ، الأصناف، الكميات، سبب الطلب. | G8: أمر شراء موقع ومرقم يُسلَّم للمورد. | H8: رقم الأمر مسجل في دفتر الأوامر ويحمل نفس رقم الطلب. | I8: • الشراء بدون أمر شراء • أن يطلب ويعتمد نفس الشخص | J8: معتمد الشراء (مختلف عن الطالب)
A9: 5 | B9: كيف يستلم أمين المخزن البضاعة | C9: أمين المخزن يستلم، مشرف المشتريات يطابق، المحاسب يسجل الفاتورة | D9: إذن استلام مخزني (نموذج 3) + فاتورة المورد | E9: 1) قارن البضاعة الواردة بأمر الشراء: النوع والكمية والصلاحية والجودة. 2) املأ نموذج 3 بالكمية المستلمة والمرفوضة ووقّع مع مندوب المورد. 3) سلّم أصل الإذن للمحاسب مع الفاتورة في نفس اليوم. 4) المحاسب يسجل الفاتورة في Supplier_Invoices: المورد، رقم فاتورة المورد، التاريخ، الحساب المدين (مخزون)، الجهة، الصافي، مراجع الأمر والاستلام. 5) النظام يرفض فاتورة مكررة (نفس المورد ونفس الرقم). | F9: رقم التسجيل، رقم فاتورة المورد، المورد، التاريخ، النوع، الحساب المدين، الجهة، الصافي، الضريبة، الدفع الفوري (للنقدي)، الأمر، الاستلام. | G9: رصيد المورد يزيد بقيمة الفاتورة، ويظهر تاريخ الاستحقاق. | H9: Supplier_Balances: رصيد المورد وتاريخ الاستحقاق. عمود (فحص المستند) فارغ. | I9: • تسجيل الفاتورة قبل الاستلام الفعلي • اختيار حساب مصروف بدل مخزون • تسجيل فاتورة نفسها مرتين | J9: مشرف المشتريات (مطابقة) + المدير المالي
A10: 6 | B10: كيف يصرف المخزن للسنتر كيتشن أو الفروع | C10: أمين المخزن ينفذ، مدير الإنتاج/الفرع يستلم، المعتمد يوقع | D10: طلب صرف إنتاج (6) / إذن صرف (4) / إذن تحويل (5) | E10: 1) الجهة الطالبة تملأ الطلب بالكميات. 2) المعتمد يوقع. 3) أمين المخزن يصرف ويملأ إذن الصرف أو التحويل، ويوقع المستلم على الأصل. 4) تُسلَّم الأصول للمحاسب أسبوعيًا على الأقل لحفظ سجل الحركة. 5) المرحلة 1: ورقيًا فقط ولا يؤثر على الربح. المرحلة 2: تُسجل في Inventory_Moves، وتبقى تكلفة التحويل = التكلفة الدفترية. | F10: الصنف، الوحدة، الكمية، الجهة المصدر والمستلمة. | G10: الكمية تخرج من المخزن وتدخل جهة الاستلام بدون أي إيراد أو تكلفة مبيعات. | H10: لا يوجد في أي قيد حساب إيراد. الرصيد الإجمالي للمخزون لم يتغير. | I10: • الصرف بدون إذن موقع • ترك التحويل مفتوحًا بدون توقيع المستلم | J10: معتمد الصرف
A11: 7 | B11: كيف يتم تسجيل الإنتاج والهالك | C11: مدير الإنتاج يعد، أمين المخزن يتحقق، المدير المالي يعتمد الهالك غير الطبيعي | D11: تقرير إنتاج يومي (7) / تحويل إنتاج (8) / تقرير هالك (9) | E11: 1) يصرف المطبخ المواد حسب الوصفة القياسية. 2) في نهاية اليوم يسجل مدير الإنتاج الكمية المخططة والفعلية والهالك الطبيعي وغير الطبيعي في نموذج 7. 3) يحوّل الإنتاج للفروع بنموذج 8 ويوقع الفرع. 4) الهالك غير الطبيعي يحتاج تحقيقًا واعتمادًا كتابيًا من المدير المالي. 5) المرحلة 2: تسجيل في Production وInventory_Moves مع حساب تكلفة الدفعة وتكلفة الوحدة والفروق. | F11: الوصفة، الكمية المخططة والفعلية، الهالك بنوعيه، الجهة المحولة إليها. | G11: تكلفة المنتج المحوَّل = تكلفة الدفعة ÷ الناتج الصالح؛ الهالك غير الطبيعي يظهر بحساب منفصل. | H11: مقارنة الاستخدام الفعلي بالوصفة القياسية. | I11: • احتساب المنتج المحول مبيعات • إخفاء الهالك داخل الاستخدام | J11: مدير الإنتاج + المدير المالي (غير الطبيعي)
A12: 8 | B12: كيف يتم تسجيل المصروفات | C12: مقدم الطلب يعد، مدير الفرع/الإدارة يوافق، المحاسب يرحّل | D12: نموذج مصروفات (17) + فاتورة/إيصال | E12: 1) املأ نموذج 17 وارفق الفاتورة أو الإيصال. 2) اختر (فوري) إن دُفع الآن، أو (آجل) إن كان مستحقًا ويُسدد لاحقًا. 3) في ورقة Expenses أضف صفًا: رقم المصروف، تاريخ الاستحقاق، الفرع، مركز التكلفة، الحساب، المبلغ، النمط، الخزينة (للفوري)، المستفيد. 4) عند السداد لاحقًا للآجل: في Cash_Vouchers سجل (صرف) بالحساب المقابل 2201 واكتب في (المستند المرتبط) رقم المصروف. 5) لا تسجل هنا شراء أجهزة أو معدات: تُسجل في فواتير الموردين كأصل ثابت. | F12: الرقم، التاريخ، الفرع، مركز التكلفة، حساب المصروف، المبلغ، النمط، الخزينة، المستفيد، البيان. | G12: يظهر المصروف في قائمة الدخل في شهر الاستحقاق، وحالة السداد في عمود (حالة السداد). | H12: Expenses: حالة السداد صحيحة. Income_Statement: المصروف على الفرع المطلوب. | I12: • اختيار حساب غير صحيح • تسجيل الآجل كفوري • نسيان ربط سند السداد | J12: مدير الفرع/الإدارة + المدير المالي
A13: 9 | B13: كيف يتم تسجيل سداد الموردين | C13: مشرف المشتريات يعد، المدير المالي يعتمد، أمين الخزينة ينفذ، المحاسب يرحّل | D13: سند صرف (نموذج 12) أو طلب دفع | E13: 1) راجع Supplier_Balances: رصيد المورد وتاريخ الاستحقاق. 2) املأ نموذج 12 بالمبلغ والمورد والفواتير المسددة. 3) يعتمد المدير المالي، ثم يدفع أمين الخزينة أو يحوّل البنك. 4) في Supplier_Payments أضف صفًا: رقم الدفعة، التاريخ، المورد، الخزينة/البنك، المبلغ، طريقة الدفع، رقم تسجيل الفاتورة المسددة. | F13: رقم الدفعة، التاريخ، المورد، الخزينة/البنك، المبلغ، الطريقة، الفاتورة المسددة. | G13: رصيد المورد ينقص بقيمة الدفعة، ورصيد الخزينة/البنك ينقص. | H13: Supplier_Balances ثم Treasury_Balances. الفرق بين دفتر الموردين الفرعي وحساب 2101 = صفر. | I13: • دفعة تتجاوز الرصيد • السداد قبل الاعتماد • اختيار مورد خطأ | J13: المدير المالي
A14: 10 | B14: كيف يراجع المدير نتائج الفرع | C14: مدير الفرع / الإدارة | D14: لا مستند (مراجعة) | E14: 1) افتح Dashboard وانظر جدول (مقارنة أداء الفروع). 2) افتح Income_Statement واختر الفرع من Settings (S_Branch) لرؤية تفاصيل مصروفاته. 3) قارن الفترة الحالية بالسابقة في الأعمدة الجانبية. 4) انتبه: صافي الربح (أولي) حتى يكتمل الإقفال. | F14: لا. | G14: فهم المبيعات والتكلفة والمصروفات والربح التشغيلي للفرع. | H14: الأرقام تتطابق مع تقارير الفرع الورقية. | I14: • اعتبار الربح الأولي نهائيًا • مقارنة فرعين بدون النظر لتوزيع المصروفات المشتركة | J14: —
A15: 11 | B15: كيف يراجع المحاسب القيود | C15: المحاسب / مراجع الحسابات | D15: لا مستند (مراجعة) | E15: 1) افتح GL_Journal وفلتر عمود (أثر فعلي) على 0 لمعرفة الأسطر المحجوبة وأسبابها. 2) افتح Close_Checklist وعالج كل بند ✖ ثم ⚠. 3) افتح Trial_Balance وتأكد أن الحالة (متوازن). 4) راجع GL_Ledger لحسابات الصندوق والبنوك والموردين. 5) راجع عينة من المستندات الورقية مقابل ما سُجل. | F15: لا. | G15: لا أخطاء حرجة ولا قيود محجوبة بلا تفسير. | H15: Test_Cases كلها (نجح) في الاختبارات الحية. | I15: • ترحيل مستند به تنبيه • تجاهل بنود المراجعة | J15: المدير المالي
A16: 12 | B16: كيف يتم إقفال الشهر | C16: المحاسب يعد، المراجع يراجع، المدير المالي يقفل، الإدارة العليا تعتمد | D16: محضر إقفال شهر (26) | E16: 1) في Settings ضع (بداية الفترة) أول الشهر و(نهاية الفترة) آخر الشهر. 2) سجّل القيود الدورية: تسوية تكلفة المبيعات بعد الجرد، المصروفات المستحقة، إطفاء المقدم، الإهلاك، الرواتب، عمولة المنصات المقدرة. 3) افتح Close_Checklist وعالج كل البنود الحرجة الآلية. 4) للبنود اليدوية (M01-M14): نفّذ الإجراء ثم سجل التأكيد في Close_Confirm. 5) عندما تصبح (جاهزية الإقفال) خضراء: افتح Period_Close، أضف الشهر، انسخ القيم الحية والصقها كقيم في أعمدة (لقطة)، ثم اكتب اسمك والمعتمد الثاني وغيّر الحالة إلى (مقفلة). 6) وقّع محضر الإقفال (نموذج 26) وأرشفه، وأنشئ نسخة احتياطية من الملف (ملف ← إنشاء نسخة). | F16: رقم الفترة، الحالة، المقفِل، التاريخ، المعتمد الثاني، لقطات الإيرادات والربح والمدين والدائن. | G16: الفترة (مقفلة) وأي تغيير لاحق في أرقامها يظهر فورًا كبند حرج. | H16: Close_Checklist: لا بنود حرجة. Period_Close: عمود (تغيّر بعد الإقفال) فارغ. | I16: • الإقفال قبل الجرد • عدم حفظ نسخة احتياطية • تسجيل قيد بأثر رجعي في فترة مقفلة | J16: المدير المالي + الإدارة العليا
... A18: 14 | B18: العمليات التي يجب ألا يقوم بها المستخدم بنفسه | C18: الجميع | D18: — | E18: 1) لا تعدّل أو تحذف مستندًا (مرحل) أو (معكوس). 2) لا تغيّر الحالة إلى (مرحل) لمستند أعددته أو اعتمدته بنفسك. 3) لا تمسح الصيغ (الخلايا الرمادية) ولا تغيّر ترتيب الأعمدة أو تحذف أوراقًا. 4) لا تعدّل أرصدة المخزون يدويًا؛ التسوية بمستند معتمد فقط. 5) لا تغيّر دليل الحسابات أو الأكواد الأساسية؛ هذا للمدير المالي. 6) لا تدخل مبلغًا سالبًا لتصحيح خطأ؛ استخدم عكس المستند. 7) لا تشارك الملف أو تغيّر صلاحياته. 8) لا تغيّر فترة التقارير في Settings ثم تتجاهل أن الجميع يراها. | F18: — | G18: — | H18: — | I18: • — (هذه كلها أخطاء) | J18: —

Sheet Settings
A1: إعدادات النظام (System Settings)
A2: الخلايا الصفراء قابلة للتعديل. فترة التقارير تتحكم في لوحة التحكم وميزان المراجعة وقائمة الدخل وقائمة الإقفال.
B4: الإعداد | C4: القيمة | D4: ملاحظات
B5: اسم المنشأة | C5: مطاعم ستاموني (Satamoni) | D5: للعرض في التقارير
B6: العملة الأساسية | C6: EGP | D6: جنيه مصري
B7: المنطقة الزمنية | C7: Africa/Cairo | D7: اضبطها أيضًا من إعدادات ملف Google Sheets: ملف ← الإعدادات
B8: بداية السنة المالية | C8: 46023 | D8: تُستخدم في الإقفال السنوي
B9: بداية فترة التقارير | C9: 46296 | D9: غيّرها لعرض شهر آخر (يجب أن تكون أول الشهر عند الإقفال)
B10: نهاية فترة التقارير | C10: 46326 | D10: آخر يوم في الفترة؛ هي أيضًا تاريخ الأرصدة في الميزانية
B11: الفرع المختار للتقارير | C11: ALL | D11: ALL = كل المواقع، أو كود موقع مثل BR01
B12: مركز التكلفة المختار | C12: ALL | D12: ALL = كل المراكز، أو كود مثل CC10
B13: رقم الفترة (آلي) | C13: =YEAR(C10)*100+MONTH(C10) | D13: صيغة: سنة*100+شهر، تُستخدم في الإقفال
B14: بداية فترة المقارنة (آلي) | C14: =C9-(C10-C9+1) | D14: فترة سابقة بنفس عدد الأيام
B15: نهاية فترة المقارنة (آلي) | C15: =C9-1
B16: طريقة تسجيل تكلفة المبيعات | C16: PERIODIC | D16: PERIODIC = دوري مُعدّل (النسخة الأولى: قيد شهري بالجرد) | PERPETUAL = مستمر من حركات المخزون (المرحلة 2). لا تجمع بينهما في نفس الفترة.
B17: هامش السماح بالفروق (جنيه) | C17: 0.01 | D17: للمقارنات الحسابية (تقريب)
B18: أيام تنبيه تأخر تسوية المنصات | C18: 14 | D18: تنبيه إن مضى هذا العدد دون تسوية ومستحقات المنصة موجودة
B19: حد فرق الخزينة المسموح (جنيه) | C19: 0 | D19: أي فرق أكبر منه يجب أن يُسجل بسند عجز/زيادة
B20: وضع البيانات | C20: تشغيلي | D20: تجريبي = بيانات الاختبار؛ غيّرها إلى (تشغيلي) بعد تفريغ البيانات التجريبية

Sheet Lists
A1: القوائم المنسدلة وحالات المستندات (Lists & Document Statuses)
A2: هذه القوائم تغذي القوائم المنسدلة في كل الأوراق. لا تغيّر نصوص الحالات (مسودة/معتمد/مرحل/معكوس/ملغى) لأن المعادلات تعتمد عليها.
A4: حالة المستند | B4: Code | C4: المعنى | E4: نوع السند | F4: Code | G4: بادئة الرقم | H4: الوصف | J4: نوع فاتورة المورد | K4: Code | L4: الوصف | N4: نمط سداد المصروف | O4: Code | P4: الوصف | R4: نعم/لا | T4: فئة الإيراد | U4: حساب الإيراد | W4: نوع القيد اليدوي | Y4: سبب الفرق | AA4: حالة المعالجة | AC4: تصنيف التدفق | AD4: المعنى | AF4: نوع الخزينة | AH4: نوع الموقع | AJ4: رمز النوع | AK4: نوع الحساب | AM4: نوع وسيلة الدفع | AO4: الأدوار
A5: مسودة | B5: DRAFT | C5: مستند مُعد ولم يُعتمد بعد - لا يؤثر على الدفاتر | E5: قبض | F5: RCV | G5: RCV | H5: سند قبض نقدية/بنك من جهة (حساب مقابل دائن) | J5: فاتورة | K5: INV | L5: فاتورة مورد | N5: فوري | O5: IMM | P5: مدفوع وقت الإثبات | R5: نعم | T5: فطير | U5: 4101 | W5: افتتاحي | Y5: خطأ إدخال | AA5: تمت التسوية | AC5: OPERATING | AD5: تشغيلية | AF5: خزينة | AH5: فرع | AJ5: A | AK5: أصل | AM5: نقدي | AO5: الإدارة العليا
A6: معتمد | B6: APPROVED | C6: اعتمده المسؤول ولم يرحّله المحاسب بعد - لا يؤثر على الدفاتر | E6: صرف | F6: PAY | G6: PAY | H6: سند صرف نقدية/بنك لجهة (حساب مقابل مدين) | J6: إشعار خصم (مرتجع) | K6: CN | L6: تخفيض مديونية المورد | N6: آجل | O6: CRD | P6: مستحق ويُسدد لاحقًا بسند صرف مرتبط | R6: لا | T6: بيتزا | U6: 4102 | W6: تسوية | Y6: عجز نقدي | AA6: معلق | AC6: INVESTING | AD6: استثمارية | AF6: بنك | AH6: مخزن رئيسي | AJ6: L | AK6: التزام | AM6: بطاقة | AO6: المدير المالي
A7: مرحل | B7: POSTED | C7: رحّله المحاسب - يؤثر على دفتر اليومية والأستاذ | E7: تحويل بين خزائن | F7: TRF | G7: TRF | H7: نقل نقدية بين خزينتين - لا يؤثر على الإيراد/المصروف | J7: إشعار إضافة | K7: DN | L7: زيادة مديونية المورد (رسوم/فروق سعر) | T7: مكرونات | U7: 4103 | W7: تصحيح | Y7: زيادة نقدية | AA7: مقبول بموافقة الإدارة | AC7: FINANCING | AD7: تمويلية | AF7: عهدة نثرية | AH7: سنتر كيتشن | AJ7: E | AK7: حقوق ملكية | AM7: منصة | AO7: المحاسب
A8: معكوس | B8: REVERSED | C8: أُلغي أثره بمستند تصحيح موثق (مرجع التصحيح إلزامي) | E8: إيداع بنكي | F8: DEP | G8: TRF | H8: من خزينة إلى بنك | T8: أخرى | U8: 4104 | W8: عكس | Y8: تأخر تحصيل | AC8: INTERNAL | AD8: تحويل داخلي (يجب أن يصفّر) | AH8: إدارة | AJ8: R | AK8: إيراد | AM8: تحويل | AO8: مراجع الحسابات
A9: ملغى | B9: CANCELLED | C9: ألغي قبل الترحيل - يبقى في السجل ولا يؤثر | E9: سحب بنكي | F9: WDR | G9: TRF | H9: من بنك إلى خزينة | W9: إهلاك | Y9: خصم غير مسجل | AC9: OPENING | AD9: رصيد افتتاحي | AJ9: C | AK9: تكلفة مبيعات | AO9: مدير فرع
E10: عجز خزينة | F10: SHT | G10: ADJ | H10: فرق جرد خزينة بالنقص | W10: تسوية تكلفة المبيعات | Y10: إلغاء بعد الدفع | AJ10: X | AK10: مصروف | AO10: أمين صندوق
E11: زيادة خزينة | F11: OVR | G11: ADJ | H11: فرق جرد خزينة بالزيادة | W11: استحقاق/مقدم | Y11: فرق عمولة منصة | AO11: أمين مخزن
W12: رواتب (مؤقت) | Y12: مستند ناقص | AO12: مشرف مشتريات
W13: إقفال | Y13: أخرى | AO13: مدير إنتاج
W14: أخرى | AO14: مستخدم قراءة

Sheet COA
A1: دليل الحسابات الموحد (Chart of Accounts)
A2: ترقيم 4 خانات: الفئة (1-6) ثم المجموعة (100) ثم الحساب. أضف حسابًا جديدًا في أي صف فارغ بالنطاق المناسب ويظهر فورًا في ميزان المراجعة. الحسابات الرئيسية (لا) لا يُرحَّل عليها.
A3: خلايا الإدخال | B3: معادلات (لا تعدّل)
A4: كود الحساب Code | B4: اسم الحساب Name (AR) | C4: Account Name (EN) | D4: النوع | E4: المستوى | F4: قابل للترحيل | G4: الطبيعة | H4: نقدية/بنك (1/0) | I4: تصنيف التدفق | J4: مسموح في المصروفات | K4: مسموح في المشتريات | L4: نشط | M4: من نطاق (للرئيسي) | N4: إلى نطاق (للرئيسي) | O4: ملاحظات | P4: بداية النطاق | Q4: نهاية النطاق | R4: صالح للترحيل (1/0) | S4: نوع الحساب | T4: فحص
A5: 1000 | B5: الأصول | C5: Assets | D5: A | E5: 1 | F5: لا | G5: مدين | H5: 0 | I5: OPERATING | J5: لا | K5: لا | L5: نعم | M5: 1000 | N5: 1999 | P5: =IF($A5="","",IF($F5="نعم",$A5,$M5)) | Q5: =IF($A5="","",IF($F5="نعم",$A5,$N5)) | R5: =IF($A5="","",IF(AND($F5="نعم",$L5<>"لا"),1,0)) | S5: =IF($D5="","",IFERROR(INDEX(Lists!$AK$5:$AK$10,MATCH($D5,Lists!$AJ$5:$AJ$10,0)),"نوع غير معرف")) | T5: =IF($A5="","",IF(COUNTIF($A:$A,$A5)>1,"كود حساب مكرر",IF($B5="","اسم الحساب ناقص",IF(AND($F5="نعم",$G5=""),"الطبيعة ناقصة",IF(AND($F5<>"نعم",OR($M5="",$N5="")),"الحساب الرئيسي يحتاج نطاقًا (من/إلى)",IF(AND($H5=1,$F5<>"نعم"),"حساب نقدية يجب أن يكون قابلًا للترحيل",IF(AND($F5="نعم",$D5=""),"النوع ناقص","")))))))
A6: 1100 | B6: النقدية والخزائن | C6: Cash on Hand | D6: A | E6: 2 | F6: لا | G6: مدين | H6: 0 | I6: OPERATING | J6: لا | K6: لا | L6: نعم | M6: 1100 | N6: 1199 | P6: =IF($A6="","",IF($F6="نعم",$A6,$M6)) | Q6: =IF($A6="","",IF($F6="نعم",$A6,$N6)) | R6: =IF($A6="","",IF(AND($F6="نعم",$L6<>"لا"),1,0)) | S6: =IF($D6="","",IFERROR(INDEX(Lists!$AK$5:$AK$10,MATCH($D6,Lists!$AJ$5:$AJ$10,0)),"نوع غير معرف")) | T6: =IF($A6="","",IF(COUNTIF($A:$A,$A6)>1,"كود حساب مكرر",IF($B6="","اسم الحساب ناقص",IF(AND($F6="نعم",$G6=""),"الطبيعة ناقصة",IF(AND($F6<>"نعم",OR($M6="",$N6="")),"الحساب الرئيسي يحتاج نطاقًا (من/إلى)",IF(AND($H6=1,$F6<>"نعم"),"حساب نقدية يجب أن يكون قابلًا للترحيل",IF(AND($F6="نعم",$D6=""),"النوع ناقص","")))))))
A7: 1101 | B7: خزينة الفرع BR01 | C7: Cash - Branch BR01 | D7: A | E7: 3 | F7: نعم | G7: مدين | H7: 1 | I7: OPERATING | J7: لا | K7: لا | L7: نعم | P7: =IF($A7="","",IF($F7="نعم",$A7,$M7)) | Q7: =IF($A7="","",IF($F7="نعم",$A7,$N7)) | R7: =IF($A7="","",IF(AND($F7="نعم",$L7<>"لا"),1,0)) | S7: =IF($D7="","",IFERROR(INDEX(Lists!$AK$5:$AK$10,MATCH($D7,Lists!$AJ$5:$AJ$10,0)),"نوع غير معرف")) | T7: =IF($A7="","",IF(COUNTIF($A:$A,$A7)>1,"كود حساب مكرر",IF($B7="","اسم الحساب ناقص",IF(AND($F7="نعم",$G7=""),"الطبيعة ناقصة",IF(AND($F7<>"نعم",OR($M7="",$N7="")),"الحساب الرئيسي يحتاج نطاقًا (من/إلى)",IF(AND($H7=1,$F7<>"نعم"),"حساب نقدية يجب أن يكون قابلًا للترحيل",IF(AND($F7="نعم",$D7=""),"النوع ناقص","")))))))
A8: 1102 | B8: خزينة الفرع BR02 | C8: Cash - Branch BR02 | D8: A | E8: 3 | F8: نعم | G8: مدين | H8: 1 | I8: OPERATING | J8: لا | K8: لا | L8: نعم | P8: =IF($A8="","",IF($F8="نعم",$A8,$M8)) | Q8: =IF($A8="","",IF($F8="نعم",$A8,$N8)) | R8: =IF($A8="","",IF(AND($F8="نعم",$L8<>"لا"),1,0)) | S8: =IF($D8="","",IFERROR(INDEX(Lists!$AK$5:$AK$10,MATCH($D8,Lists!$AJ$5:$AJ$10,0)),"نوع غير معرف")) | T8: =IF($A8="","",IF(COUNTIF($A:$A,$A8)>1,"كود حساب مكرر",IF($B8="","اسم الحساب ناقص",IF(AND($F8="نعم",$G8=""),"الطبيعة ناقصة",IF(AND($F8<>"نعم",OR($M8="",$N8="")),"الحساب الرئيسي يحتاج نطاقًا (من/إلى)",IF(AND($H8=1,$F8<>"نعم"),"حساب نقدية يجب أن يكون قابلًا للترحيل",IF(AND($F8="نعم",$D8=""),"النوع ناقص","")))))))
A9: 1103 | B9: خزينة الفرع BR03 | C9: Cash - Branch BR03 | D9: A | E9: 3 | F9: نعم | G9: مدين | H9: 1 | I9: OPERATING | J9: لا | K9: لا | L9: نعم | P9: =IF($A9="","",IF($F9="نعم",$A9,$M9)) | Q9: =IF($A9="","",IF($F9="نعم",$A9,$N9)) | R9: =IF($A9="","",IF(AND($F9="نعم",$L9<>"لا"),1,0)) | S9: =IF($D9="","",IFERROR(INDEX(Lists!$AK$5:$AK$10,MATCH($D9,Lists!$AJ$5:$AJ$10,0)),"نوع غير معرف")) | T9: =IF($A9="","",IF(COUNTIF($A:$A,$A9)>1,"كود حساب مكرر",IF($B9="","اسم الحساب ناقص",IF(AND($F9="نعم",$G9=""),"الطبيعة ناقصة",IF(AND($F9<>"نعم",OR($M9="",$N9="")),"الحساب الرئيسي يحتاج نطاقًا (من/إلى)",IF(AND($H9=1,$F9<>"نعم"),"حساب نقدية يجب أن يكون قابلًا للترحيل",IF(AND($F9="نعم",$D9=""),"النوع ناقص","")))))))
A10: 1104 | B10: خزينة الإدارة الرئيسية HQ01 | C10: Cash - Head Office | D10: A | E10: 3 | F10: نعم | G10: مدين | H10: 1 | I10: OPERATING | J10: لا | K10: لا | L10: نعم | P10: =IF($A10="","",IF($F10="نعم",$A10,$M10)) | Q10: =IF($A10="","",IF($F10="نعم",$A10,$N10)) | R10: =IF($A10="","",IF(AND($F10="نعم",$L10<>"لا"),1,0)) | S10: =IF($D10="","",IFERROR(INDEX(Lists!$AK$5:$AK$10,MATCH($D10,Lists!$AJ$5:$AJ$10,0)),"نوع غير معرف")) | T10: =IF($A10="","",IF(COUNTIF($A:$A,$A10)>1,"كود حساب مكرر",IF($B10="","اسم الحساب ناقص",IF(AND($F10="نعم",$G10=""),"الطبيعة ناقصة",IF(AND($F10<>"نعم",OR($M10="",$N10="")),"الحساب الرئيسي يحتاج نطاقًا (من/إلى)",IF(AND($H10=1,$F10<>"نعم"),"حساب نقدية يجب أن يكون قابلًا للترحيل",IF(AND($F10="نعم",$D10=""),"النوع ناقص","")))))))
A11: 1105 | B11: عهدة المصروفات النثرية | C11: Petty Cash | D11: A | E11: 3 | F11: نعم | G11: مدين | H11: 1 | I11: OPERATING | J11: لا | K11: لا | L11: نعم | P11: =IF($A11="","",IF($F11="نعم",$A11,$M11)) | Q11: =IF($A11="","",IF($F11="نعم",$A11,$N11)) | R11: =IF($A11="","",IF(AND($F11="نعم",$L11<>"لا"),1,0)) | S11: =IF($D11="","",IFERROR(INDEX(Lists!$AK$5:$AK$10,MATCH($D11,Lists!$AJ$5:$AJ$10,0)),"نوع غير معرف")) | T11: =IF($A11="","",IF(COUNTIF($A:$A,$A11)>1,"كود حساب مكرر",IF($B11="","اسم الحساب ناقص",IF(AND($F11="نعم",$G11=""),"الطبيعة ناقصة",IF(AND($F11<>"نعم",OR($M11="",$N11="")),"الحساب الرئيسي يحتاج نطاقًا (من/إلى)",IF(AND($H11=1,$F11<>"نعم"),"حساب نقدية يجب أن يكون قابلًا للترحيل",IF(AND($F11="نعم",$D11=""),"النوع ناقص","")))))))
A12: 1106 | B12: نقدية بالطريق (تحويلات قيد التسوية) | C12: Cash in Transit | D12: A | E12: 3 | F12: نعم | G12: مدين | H12: 1 | I12: OPERATING | J12: لا | K12: لا | L12: نعم | O12: يجب أن يكون رصيده صفرًا عند الإقفال | P12: =IF($A12="","",IF($F12="نعم",$A12,$M12)) | Q12: =IF($A12="","",IF($F12="نعم",$A12,$N12)) | R12: =IF($A12="","",IF(AND($F12="نعم",$L12<>"لا"),1,0)) | S12: =IF($D12="","",IFERROR(INDEX(Lists!$AK$5:$AK$10,MATCH($D12,Lists!$AJ$5:$AJ$10,0)),"نوع غير معرف")) | T12: =IF($A12="","",IF(COUNTIF($A:$A,$A12)>1,"كود حساب مكرر",IF($B12="","اسم الحساب ناقص",IF(AND($F12="نعم",$G12=""),"الطبيعة ناقصة",IF(AND($F12<>"نعم",OR($M12="",$N12="")),"الحساب الرئيسي يحتاج نطاقًا (من/إلى)",IF(AND($H12=1,$F12<>"نعم"),"حساب نقدية يجب أن يكون قابلًا للترحيل",IF(AND($F12="نعم",$D12=""),"النوع ناقص","")))))))
A13: 1200 | B13: البنوك | C13: Banks | D13: A | E13: 2 | F13: لا | G13: مدين | H13: 0 | I13: OPERATING | J13: لا | K13: لا | L13: نعم | M13: 1200 | N13: 1299 | P13: =IF($A13="","",IF($F13="نعم",$A13,$M13)) | Q13: =IF($A13="","",IF($F13="نعم",$A13,$N13)) | R13: =IF($A13="","",IF(AND($F13="نعم",$L13<>"لا"),1,0)) | S13: =IF($D13="","",IFERROR(INDEX(Lists!$AK$5:$AK$10,MATCH($D13,Lists!$AJ$5:$AJ$10,0)),"نوع غير معرف")) | T13: =IF($A13="","",IF(COUNTIF($A:$A,$A13)>1,"كود حساب مكرر",IF($B13="","اسم الحساب ناقص",IF(AND($F13="نعم",$G13=""),"الطبيعة ناقصة",IF(AND($F13<>"نعم",OR($M13="",$N13="")),"الحساب الرئيسي يحتاج نطاقًا (من/إلى)",IF(AND($H13=1,$F13<>"نعم"),"حساب نقدية يجب أن يكون قابلًا للترحيل",IF(AND($F13="نعم",$D13=""),"النوع ناقص","")))))))
A14: 1201 | B14: البنك الأول - حساب جاري (تجريبي) | C14: Bank 1 - Current | D14: A | E14: 3 | F14: نعم | G14: مدين | H14: 1 | I14: OPERATING | J14: لا | K14: لا | L14: نعم | P14: =IF($A14="","",IF($F14="نعم",$A14,$M14)) | Q14: =IF($A14="","",IF($F14="نعم",$A14,$N14)) | R14: =IF($A14="","",IF(AND($F14="نعم",$L14<>"لا"),1,0)) | S14: =IF($D14="","",IFERROR(INDEX(Lists!$AK$5:$AK$10,MATCH($D14,Lists!$AJ$5:$AJ$10,0)),"نوع غير معرف")) | T14: =IF($A14="","",IF(COUNTIF($A:$A,$A14)>1,"كود حساب مكرر",IF($B14="","اسم الحساب ناقص",IF(AND($F14="نعم",$G14=""),"الطبيعة ناقصة",IF(AND($F14<>"نعم",OR($M14="",$N14="")),"الحساب الرئيسي يحتاج نطاقًا (من/إلى)",IF(AND($H14=1,$F14<>"نعم"),"حساب نقدية يجب أن يكون قابلًا للترحيل",IF(AND($F14="نعم",$D14=""),"النوع ناقص","")))))))
A15: 1202 | B15: البنك الثاني - حساب جاري (تجريبي) | C15: Bank 2 - Current | D15: A | E15: 3 | F15: نعم | G15: مدين | H15: 1 | I15: OPERATING | J15: لا | K15: لا | L15: نعم | P15: =IF($A15="","",IF($F15="نعم",$A15,$M15)) | Q15: =IF($A15="","",IF($F15="نعم",$A15,$N15)) | R15: =IF($A15="","",IF(AND($F15="نعم",$L15<>"لا"),1,0)) | S15: =IF($D15="","",IFERROR(INDEX(Lists!$AK$5:$AK$10,MATCH($D15,Lists!$AJ$5:$AJ$10,0)),"نوع غير معرف")) | T15: =IF($A15="","",IF(COUNTIF($A:$A,$A15)>1,"كود حساب مكرر",IF($B15="","اسم الحساب ناقص",IF(AND($F15="نعم",$G15=""),"الطبيعة ناقصة",IF(AND($F15<>"نعم",OR($M15="",$N15="")),"الحساب الرئيسي يحتاج نطاقًا (من/إلى)",IF(AND($H15=1,$F15<>"نعم"),"حساب نقدية يجب أن يكون قابلًا للترحيل",IF(AND($F15="نعم",$D15=""),"النوع ناقص","")))))))
A16: 1203 | B16: محافظ وتحويلات إلكترونية | C16: E-wallets / Instant transfers | D16: A | E16: 3 | F16: نعم | G16: مدين | H16: 1 | I16: OPERATING | J16: لا | K16: لا | L16: نعم | P16: =IF($A16="","",IF($F16="نعم",$A16,$M16)) | Q16: =IF($A16="","",IF($F16="نعم",$A16,$N16)) | R16: =IF($A16="","",IF(AND($F16="نعم",$L16<>"لا"),1,0)) | S16: =IF($D16="","",IFERROR(INDEX(Lists!$AK$5:$AK$10,MATCH($D16,Lists!$AJ$5:$AJ$10,0)),"نوع غير معرف")) | T16: =IF($A16="","",IF(COUNTIF($A:$A,$A16)>1,"كود حساب مكرر",IF($B16="","اسم الحساب ناقص",IF(AND($F16="نعم",$G16=""),"الطبيعة ناقصة",IF(AND($F16<>"نعم",OR($M16="",$N16="")),"الحساب الرئيسي يحتاج نطاقًا (من/إلى)",IF(AND($H16=1,$F16<>"نعم"),"حساب نقدية يجب أن يكون قابلًا للترحيل",IF(AND($F16="نعم",$D16=""),"النوع ناقص","")))))))
A17: 1300 | B17: العملاء ومنصات التوصيل والبطاقات | C17: Receivables & Platforms | D17: A | E17: 2 | F17: لا | G17: مدين | H17: 0 | I17: OPERATING | J17: لا | K17: لا | L17: نعم | M17: 1300 | N17: 1399 | P17: =IF($A17="","",IF($F17="نعم",$A17,$M17)) | Q17: =IF($A17="","",IF($F17="نعم",$A17,$N17)) | R17: =IF($A17="","",IF(AND($F17="نعم",$L17<>"لا"),1,0)) | S17: =IF($D17="","",IFERROR(INDEX(Lists!$AK$5:$AK$10,MATCH($D17,Lists!$AJ$5:$AJ$10,0)),"نوع غير معرف")) | T17: =IF($A17="","",IF(COUNTIF($A:$A,$A17)>1,"كود حساب مكرر",IF($B17="","اسم الحساب ناقص",IF(AND($F17="نعم",$G17=""),"الطبيعة ناقصة",IF(AND($F17<>"نعم",OR($M17="",$N17="")),"الحساب الرئيسي يحتاج نطاقًا (من/إلى)",IF(AND($H17=1,$F17<>"نعم"),"حساب نقدية يجب أن يكون قابلًا للترحيل",IF(AND($F17="نعم",$D17=""),"النوع ناقص","")))))))
A18: 1301 | B18: عملاء (مدينون تجاريون) | C18: Trade Receivables | D18: A | E18: 3 | F18: نعم | G18: مدين | H18: 0 | I18: OPERATING | J18: لا | K18: لا | L18: نعم | P18: =IF($A18="","",IF($F18="نعم",$A18,$M18)) | Q18: =IF($A18="","",IF($F18="نعم",$A18,$N18)) | R18: =IF($A18="","",IF(AND($F18="نعم",$L18<>"لا"),1,0)) | S18: =IF($D18="","",IFERROR(INDEX(Lists!$AK$5:$AK$10,MATCH($D18,Lists!$AJ$5:$AJ$10,0)),"نوع غير معرف")) | T18: =IF($A18="","",IF(COUNTIF($A:$A,$A18)>1,"كود حساب مكرر",IF($B18="","اسم الحساب ناقص",IF(AND($F18="نعم",$G18=""),"الطبيعة ناقصة",IF(AND($F18<>"نعم",OR($M18="",$N18="")),"الحساب الرئيسي يحتاج نطاقًا (من/إلى)",IF(AND($H18=1,$F18<>"نعم"),"حساب نقدية يجب أن يكون قابلًا للترحيل",IF(AND($F18="نعم",$D18=""),"النوع ناقص","")))))))
A19: 1302 | B19: مستحقات بطاقات الدفع (POS Clearing) | C19: Card Settlements Receivable | D19: A | E19: 3 | F19: نعم | G19: مدين | H19: 0 | I19: OPERATING | J19: لا | K19: لا | L19: نعم | P19: =IF($A19="","",IF($F19="نعم",$A19,$M19)) | Q19: =IF($A19="","",IF($F19="نعم",$A19,$N19)) | R19: =IF($A19="","",IF(AND($F19="نعم",$L19<>"لا"),1,0)) | S19: =IF($D19="","",IFERROR(INDEX(Lists!$AK$5:$AK$10,MATCH($D19,Lists!$AJ$5:$AJ$10,0)),"نوع غير معرف")) | T19: =IF($A19="","",IF(COUNTIF($A:$A,$A19)>1,"كود حساب مكرر",IF($B19="","اسم الحساب ناقص",IF(AND($F19="نعم",$G19=""),"الطبيعة ناقصة",IF(AND($F19<>"نعم",OR($M19="",$N19="")),"الحساب الرئيسي يحتاج نطاقًا (من/إلى)",IF(AND($H19=1,$F19<>"نعم"),"حساب نقدية يجب أن يكون قابلًا للترحيل",IF(AND($F19="نعم",$D19=""),"النوع ناقص","")))))))
A20: 1303 | B20: مستحقات منصة طلبات | C20: Receivable - Talabat | D20: A | E20: 3 | F20: نعم | G20: مدين | H20: 0 | I20: OPERATING | J20: لا | K20: لا | L20: نعم | P20: =IF($A20="","",IF($F20="نعم",$A20,$M20)) | Q20: =IF($A20="","",IF($F20="نعم",$A20,$N20)) | R20: =IF($A20="","",IF(AND($F20="نعم",$L20<>"لا"),1,0)) | S20: =IF($D20="","",IFERROR(INDEX(Lists!$AK$5:$AK$10,MATCH($D20,Lists!$AJ$5:$AJ$10,0)),"نوع غير معرف")) | T20: =IF($A20="","",IF(COUNTIF($A:$A,$A20)>1,"كود حساب مكرر",IF($B20="","اسم الحساب ناقص",IF(AND($F20="نعم",$G20=""),"الطبيعة ناقصة",IF(AND($F20<>"نعم",OR($M20="",$N20="")),"الحساب الرئيسي يحتاج نطاقًا (من/إلى)",IF(AND($H20=1,$F20<>"نعم"),"حساب نقدية يجب أن يكون قابلًا للترحيل",IF(AND($F20="نعم",$D20=""),"النوع ناقص","")))))))
A21: 1304 | B21: مستحقات منصة توصيل أخرى | C21: Receivable - Other Delivery Platform | D21: A | E21: 3 | F21: نعم | G21: مدين | H21: 0 | I21: OPERATING | J21: لا | K21: لا | L21: نعم | P21: =IF($A21="","",IF($F21="نعم",$A21,$M21)) | Q21: =IF($A21="","",IF($F21="نعم",$A21,$N21)) | R21: =IF($A21="","",IF(AND($F21="نعم",$L21<>"لا"),1,0)) | S21: =IF($D21="","",IFERROR(INDEX(Lists!$AK$5:$AK$10,MATCH($D21,Lists!$AJ$5:$AJ$10,0)),"نوع غير معرف")) | T21: =IF($A21="","",IF(COUNTIF($A:$A,$A21)>1,"كود حساب مكرر",IF($B21="","اسم الحساب ناقص",IF(AND($F21="نعم",$G21=""),"الطبيعة ناقصة",IF(AND($F21<>"نعم",OR($M21="",$N21="")),"الحساب الرئيسي يحتاج نطاقًا (من/إلى)",IF(AND($H21=1,$F21<>"نعم"),"حساب نقدية يجب أن يكون قابلًا للترحيل",IF(AND($F21="نعم",$D21=""),"النوع ناقص","")))))))
A22: 1309 | B22: فروق تسوية المنصات تحت المراجعة | C22: Platform Settlement Differences (pending) | D22: A | E22: 3 | F22: نعم | G22: مدين | H22: 0 | I22: OPERATING | J22: لا | K22: لا | L22: نعم | O22: حساب مراجعة؛ يُسوّى شهريًا | P22: =IF($A22="","",IF($F22="نعم",$A22,$M22)) | Q22: =IF($A22="","",IF($F22="نعم",$A22,$N22)) | R22: =IF($A22="","",IF(AND($F22="نعم",$L22<>"لا"),1,0)) | S22: =IF($D22="","",IFERROR(INDEX(Lists!$AK$5:$AK$10,MATCH($D22,Lists!$AJ$5:$AJ$10,0)),"نوع غير معرف")) | T22: =IF($A22="","",IF(COUNTIF($A:$A,$A22)>1,"كود حساب مكرر",IF($B22="","اسم الحساب ناقص",IF(AND($F22="نعم",$G22=""),"الطبيعة ناقصة",IF(AND($F22<>"نعم",OR($M22="",$N22="")),"الحساب الرئيسي يحتاج نطاقًا (من/إلى)",IF(AND($H22=1,$F22<>"نعم"),"حساب نقدية يجب أن يكون قابلًا للترحيل",IF(AND($F22="نعم",$D22=""),"النوع ناقص","")))))))
A23: 1400 | B23: المخزون | C23: Inventory | D23: A | E23: 2 | F23: لا | G23: مدين | H23: 0 | I23: OPERATING | J23: لا | K23: لا | L23: نعم | M23: 1400 | N23: 1499 | P23: =IF($A23="","",IF($F23="نعم",$A23,$M23)) | Q23: =IF($A23="","",IF($F23="نعم",$A23,$N23)) | R23: =IF($A23="","",IF(AND($F23="نعم",$L23<>"لا"),1,0)) | S23: =IF($D23="","",IFERROR(INDEX(Lists!$AK$5:$AK$10,MATCH($D23,Lists!$AJ$5:$AJ$10,0)),"نوع غير معرف")) | T23: =IF($A23="","",IF(COUNTIF($A:$A,$A23)>1,"كود حساب مكرر",IF($B23="","اسم الحساب ناقص",IF(AND($F23="نعم",$G23=""),"الطبيعة ناقصة",IF(AND($F23<>"نعم",OR($M23="",$N23="")),"الحساب الرئيسي يحتاج نطاقًا (من/إلى)",IF(AND($H23=1,$F23<>"نعم"),"حساب نقدية يجب أن يكون قابلًا للترحيل",IF(AND($F23="نعم",$D23=""),"النوع ناقص","")))))))
A24: 1401 | B24: مخزون المخزن الرئيسي - مواد خام | C24: Inventory - Main Warehouse (raw) | D24: A | E24: 3 | F24: نعم | G24: مدين | H24: 0 | I24: OPERATING | J24: لا | K24: نعم | L24: نعم | P24: =IF($A24="","",IF($F24="نعم",$A24,$M24)) | Q24: =IF($A24="","",IF($F24="نعم",$A24,$N24)) | R24: =IF($A24="","",IF(AND($F24="نعم",$L24<>"لا"),1,0)) | S24: =IF($D24="","",IFERROR(INDEX(Lists!$AK$5:$AK$10,MATCH($D24,Lists!$AJ$5:$AJ$10,0)),"نوع غير معرف")) | T24: =IF($A24="","",IF(COUNTIF($A:$A,$A24)>1,"كود حساب مكرر",IF($B24="","اسم الحساب ناقص",IF(AND($F24="نعم",$G24=""),"الطبيعة ناقصة",IF(AND($F24<>"نعم",OR($M24="",$N24="")),"الحساب الرئيسي يحتاج نطاقًا (من/إلى)",IF(AND($H24=1,$F24<>"نعم"),"حساب نقدية يجب أن يكون قابلًا للترحيل",IF(AND($F24="نعم",$D24=""),"النوع ناقص","")))))))
A25: 1402 | B25: مخزون السنتر كيتشن - مواد خام | C25: Inventory - Central Kitchen (raw) | D25: A | E25: 3 | F25: نعم | G25: مدين | H25: 0 | I25: OPERATING | J25: لا | K25: نعم | L25: نعم | P25: =IF($A25="","",IF($F25="نعم",$A25,$M25)) | Q25: =IF($A25="","",IF($F25="نعم",$A25,$N25)) | R25: =IF($A25="","",IF(AND($F25="نعم",$L25<>"لا"),1,0)) | S25: =IF($D25="","",IFERROR(INDEX(Lists!$AK$5:$AK$10,MATCH($D25,Lists!$AJ$5:$AJ$10,0)),"نوع غير معرف")) | T25: =IF($A25="","",IF(COUNTIF($A:$A,$A25)>1,"كود حساب مكرر",IF($B25="","اسم الحساب ناقص",IF(AND($F25="نعم",$G25=""),"الطبيعة ناقصة",IF(AND($F25<>"نعم",OR($M25="",$N25="")),"الحساب الرئيسي يحتاج نطاقًا (من/إلى)",IF(AND($H25=1,$F25<>"نعم"),"حساب نقدية يجب أن يكون قابلًا للترحيل",IF(AND($F25="نعم",$D25=""),"النوع ناقص","")))))))
A26: 1403 | B26: مخزون منتجات نصف مصنعة وتامة | C26: Inventory - WIP/Finished Goods | D26: A | E26: 3 | F26: نعم | G26: مدين | H26: 0 | I26: OPERATING | J26: لا | K26: نعم | L26: نعم | P26: =IF($A26="","",IF($F26="نعم",$A26,$M26)) | Q26: =IF($A26="","",IF($F26="نعم",$A26,$N26)) | R26: =IF($A26="","",IF(AND($F26="نعم",$L26<>"لا"),1,0)) | S26: =IF($D26="","",IFERROR(INDEX(Lists!$AK$5:$AK$10,MATCH($D26,Lists!$AJ$5:$AJ$10,0)),"نوع غير معرف")) | T26: =IF($A26="","",IF(COUNTIF($A:$A,$A26)>1,"كود حساب مكرر",IF($B26="","اسم الحساب ناقص",IF(AND($F26="نعم",$G26=""),"الطبيعة ناقصة",IF(AND($F26<>"نعم",OR($M26="",$N26="")),"الحساب الرئيسي يحتاج نطاقًا (من/إلى)",IF(AND($H26=1,$F26<>"نعم"),"حساب نقدية يجب أن يكون قابلًا للترحيل",IF(AND($F26="نعم",$D26=""),"النوع ناقص","")))))))
A27: 1404 | B27: مخزون الفروع | C27: Inventory - Branches | D27: A | E27: 3 | F27: نعم | G27: مدين | H27: 0 | I27: OPERATING | J27: لا | K27: نعم | L27: نعم | P27: =IF($A27="","",IF($F27="نعم",$A27,$M27)) | Q27: =IF($A27="","",IF($F27="نعم",$A27,$N27)) | R27: =IF($A27="","",IF(AND($F27="نعم",$L27<>"لا"),1,0)) | S27: =IF($D27="","",IFERROR(INDEX(Lists!$AK$5:$AK$10,MATCH($D27,Lists!$AJ$5:$AJ$10,0)),"نوع غير معرف")) | T27: =IF($A27="","",IF(COUNTIF($A:$A,$A27)>1,"كود حساب مكرر",IF($B27="","اسم الحساب ناقص",IF(AND($F27="نعم",$G27=""),"الطبيعة ناقصة",IF(AND($F27<>"نعم",OR($M27="",$N27="")),"الحساب الرئيسي يحتاج نطاقًا (من/إلى)",IF(AND($H27=1,$F27<>"نعم"),"حساب نقدية يجب أن يكون قابلًا للترحيل",IF(AND($F27="نعم",$D27=""),"النوع ناقص","")))))))
A28: 1405 | B28: مخزون عبوات وتغليف | C28: Inventory - Packaging | D28: A | E28: 3 | F28: نعم | G28: مدين | H28: 0 | I28: OPERATING | J28: لا | K28: نعم | L28: نعم | P28: =IF($A28="","",IF($F28="نعم",$A28,$M28)) | Q28: =IF($A28="","",IF($F28="نعم",$A28,$N28)) | R28: =IF($A28="","",IF(AND($F28="نعم",$L28<>"لا"),1,0)) | S28: =IF($D28="","",IFERROR(INDEX(Lists!$AK$5:$AK$10,MATCH($D28,Lists!$AJ$5:$AJ$10,0)),"نوع غير معرف")) | T28: =IF($A28="","",IF(COUNTIF($A:$A,$A28)>1,"كود حساب مكرر",IF($B28="","اسم الحساب ناقص",IF(AND($F28="نعم",$G28=""),"الطبيعة ناقصة",IF(AND($F28<>"نعم",OR($M28="",$N28="")),"الحساب الرئيسي يحتاج نطاقًا (من/إلى)",IF(AND($H28=1,$F28<>"نعم"),"حساب نقدية يجب أن يكون قابلًا للترحيل",IF(AND($F28="نعم",$D28=""),"النوع ناقص","")))))))
A29: 1406 | B29: إنتاج تحت التشغيل (WIP) | C29: Work in Process | D29: A | E29: 3 | F29: نعم | G29: مدين | H29: 0 | I29: OPERATING | J29: لا | K29: لا | L29: نعم | O29: المرحلة 2 | P29: =IF($A29="","",IF($F29="نعم",$A29,$M29)) | Q29: =IF($A29="","",IF($F29="نعم",$A29,$N29)) | R29: =IF($A29="","",IF(AND($F29="نعم",$L29<>"لا"),1,0)) | S29: =IF($D29="","",IFERROR(INDEX(Lists!$AK$5:$AK$10,MATCH($D29,Lists!$AJ$5:$AJ$10,0)),"نوع غير معرف")) | T29: =IF($A29="","",IF(COUNTIF($A:$A,$A29)>1,"كود حساب مكرر",IF($B29="","اسم الحساب ناقص",IF(AND($F29="نعم",$G29=""),"الطبيعة ناقصة",IF(AND($F29<>"نعم",OR($M29="",$N29="")),"الحساب الرئيسي يحتاج نطاقًا (من/إلى)",IF(AND($H29=1,$F29<>"نعم"),"حساب نقدية يجب أن يكون قابلًا للترحيل",IF(AND($F29="نعم",$D29=""),"النوع ناقص","")))))))
A30: 1407 | B30: بضاعة بالطريق (تحويلات مخزنية مفتوحة) | C30: Goods in Transit | D30: A | E30: 3 | F30: نعم | G30: مدين | H30: 0 | I30: OPERATING | J30: لا | K30: لا | L30: نعم | O30: المرحلة 2 | P30: =IF($A30="","",IF($F30="نعم",$A30,$M30)) | Q30: =IF($A30="","",IF($F30="نعم",$A30,$N30)) | R30: =IF($A30="","",IF(AND($F30="نعم",$L30<>"لا"),1,0)) | S30: =IF($D30="","",IFERROR(INDEX(Lists!$AK$5:$AK$10,MATCH($D30,Lists!$AJ$5:$AJ$10,0)),"نوع غير معرف")) | T30: =IF($A30="","",IF(COUNTIF($A:$A,$A30)>1,"كود حساب مكرر",IF($B30="","اسم الحساب ناقص",IF(AND($F30="نعم",$G30=""),"الطبيعة ناقصة",IF(AND($F30<>"نعم",OR($M30="",$N30="")),"الحساب الرئيسي يحتاج نطاقًا (من/إلى)",IF(AND($H30=1,$F30<>"نعم"),"حساب نقدية يجب أن يكون قابلًا للترحيل",IF(AND($F30="نعم",$D30=""),"النوع ناقص","")))))))
A31: 1500 | B31: السلف والعهد | C31: Advances & Custody | D31: A | E31: 2 | F31: لا | G31: مدين | H31: 0 | I31: OPERATING | J31: لا | K31: لا | L31: نعم | M31: 1500 | N31: 1599 | P31: =IF($A31="","",IF($F31="نعم",$A31,$M31)) | Q31: =IF($A31="","",IF($F31="نعم",$A31,$N31)) | R31: =IF($A31="","",IF(AND($F31="نعم",$L31<>"لا"),1,0)) | S31: =IF($D31="","",IFERROR(INDEX(Lists!$AK$5:$AK$10,MATCH($D31,Lists!$AJ$5:$AJ$10,0)),"نوع غير معرف")) | T31: =IF($A31="","",IF(COUNTIF($A:$A,$A31)>1,"كود حساب مكرر",IF($B31="","اسم الحساب ناقص",IF(AND($F31="نعم",$G31=""),"الطبيعة ناقصة",IF(AND($F31<>"نعم",OR($M31="",$N31="")),"الحساب الرئيسي يحتاج نطاقًا (من/إلى)",IF(AND($H31=1,$F31<>"نعم"),"حساب نقدية يجب أن يكون قابلًا للترحيل",IF(AND($F31="نعم",$D31=""),"النوع ناقص","")))))))
A32: 1501 | B32: سلف الموظفين | C32: Employee Advances | D32: A | E32: 3 | F32: نعم | G32: مدين | H32: 0 | I32: OPERATING | J32: لا | K32: لا | L32: نعم | P32: =IF($A32="","",IF($F32="نعم",$A32,$M32)) | Q32: =IF($A32="","",IF($F32="نعم",$A32,$N32)) | R32: =IF($A32="","",IF(AND($F32="نعم",$L32<>"لا"),1,0)) | S32: =IF($D32="","",IFERROR(INDEX(Lists!$AK$5:$AK$10,MATCH($D32,Lists!$AJ$5:$AJ$10,0)),"نوع غير معرف")) | T32: =IF($A32="","",IF(COUNTIF($A:$A,$A32)>1,"كود حساب مكرر",IF($B32="","اسم الحساب ناقص",IF(AND($F32="نعم",$G32=""),"الطبيعة ناقصة",IF(AND($F32<>"نعم",OR($M32="",$N32="")),"الحساب الرئيسي يحتاج نطاقًا (من/إلى)",IF(AND($H32=1,$F32<>"نعم"),"حساب نقدية يجب أن يكون قابلًا للترحيل",IF(AND($F32="نعم",$D32=""),"النوع ناقص","")))))))
A33: 1502 | B33: عهد الموظفين | C33: Employee Custody | D33: A | E33: 3 | F33: نعم | G33: مدين | H33: 0 | I33: OPERATING | J33: لا | K33: لا | L33: نعم | P33: =IF($A33="","",IF($F33="نعم",$A33,$M33)) | Q33: =IF($A33="","",IF($F33="نعم",$A33,$N33)) | R33: =IF($A33="","",IF(AND($F33="نعم",$L33<>"لا"),1,0)) | S33: =IF($D33="","",IFERROR(INDEX(Lists!$AK$5:$AK$10,MATCH($D33,Lists!$AJ$5:$AJ$10,0)),"نوع غير معرف")) | T33: =IF($A33="","",IF(COUNTIF($A:$A,$A33)>1,"كود حساب مكرر",IF($B33="","اسم الحساب ناقص",IF(AND($F33="نعم",$G33=""),"الطبيعة ناقصة",IF(AND($F33<>"نعم",OR($M33="",$N33="")),"الحساب الرئيسي يحتاج نطاقًا (من/إلى)",IF(AND($H33=1,$F33<>"نعم"),"حساب نقدية يجب أن يكون قابلًا للترحيل",IF(AND($F33="نعم",$D33=""),"النوع ناقص","")))))))
A34: 1600 | B34: المصروفات المقدمة والضرائب المدينة | C34: Prepaids & Tax Receivable | D34: A | E34: 2 | F34: لا | G34: مدين | H34: 0 | I34: OPERATING | J34: لا | K34: لا | L34: نعم | M34: 1600 | N34: 1699 | P34: =IF($A34="","",IF($F34="نعم",$A34,$M34)) | Q34: =IF($A34="","",IF($F34="نعم",$A34,$N34)) | R34: =IF($A34="","",IF(AND($F34="نعم",$L34<>"لا"),1,0)) | S34: =IF($D34="","",IFERROR(INDEX(Lists!$AK$5:$AK$10,MATCH($D34,Lists!$AJ$5:$AJ$10,0)),"نوع غير معرف")) | T34: =IF($A34="","",IF(COUNTIF($A:$A,$A34)>1,"كود حساب مكرر",IF($B34="","اسم الحساب ناقص",IF(AND($F34="نعم",$G34=""),"الطبيعة ناقصة",IF(AND($F34<>"نعم",OR($M34="",$N34="")),"الحساب الرئيسي يحتاج نطاقًا (من/إلى)",IF(AND($H34=1,$F34<>"نعم"),"حساب نقدية يجب أن يكون قابلًا للترحيل",IF(AND($F34="نعم",$D34=""),"النوع ناقص","")))))))
A35: 1601 | B35: إيجار مدفوع مقدمًا | C35: Prepaid Rent | D35: A | E35: 3 | F35: نعم | G35: مدين | H35: 0 | I35: OPERATING | J35: نعم | K35: نعم | L35: نعم | P35: =IF($A35="","",IF($F35="نعم",$A35,$M35)) | Q35: =IF($A35="","",IF($F35="نعم",$A35,$N35)) | R35: =IF($A35="","",IF(AND($F35="نعم",$L35<>"لا"),1,0)) | S35: =IF($D35="","",IFERROR(INDEX(Lists!$AK$5:$AK$10,MATCH($D35,Lists!$AJ$5:$AJ$10,0)),"نوع غير معرف")) | T35: =IF($A35="","",IF(COUNTIF($A:$A,$A35)>1,"كود حساب مكرر",IF($B35="","اسم الحساب ناقص",IF(AND($F35="نعم",$G35=""),"الطبيعة ناقصة",IF(AND($F35<>"نعم",OR($M35="",$N35="")),"الحساب الرئيسي يحتاج نطاقًا (من/إلى)",IF(AND($H35=1,$F35<>"نعم"),"حساب نقدية يجب أن يكون قابلًا للترحيل",IF(AND($F35="نعم",$D35=""),"النوع ناقص","")))))))
A36: 1602 | B36: تأمينات وتراخيص مدفوعة مقدمًا | C36: Prepaid Insurance & Licences | D36: A | E36: 3 | F36: نعم | G36: مدين | H36: 0 | I36: OPERATING | J36: نعم | K36: نعم | L36: نعم | P36: =IF($A36="","",IF($F36="نعم",$A36,$M36)) | Q36: =IF($A36="","",IF($F36="نعم",$A36,$N36)) | R36: =IF($A36="","",IF(AND($F36="نعم",$L36<>"لا"),1,0)) | S36: =IF($D36="","",IFERROR(INDEX(Lists!$AK$5:$AK$10,MATCH($D36,Lists!$AJ$5:$AJ$10,0)),"نوع غير معرف")) | T36: =IF($A36="","",IF(COUNTIF($A:$A,$A36)>1,"كود حساب مكرر",IF($B36="","اسم الحساب ناقص",IF(AND($F36="نعم",$G36=""),"الطبيعة ناقصة",IF(AND($F36<>"نعم",OR($M36="",$N36="")),"الحساب الرئيسي يحتاج نطاقًا (من/إلى)",IF(AND($H36=1,$F36<>"نعم"),"حساب نقدية يجب أن يكون قابلًا للترحيل",IF(AND($F36="نعم",$D36=""),"النوع ناقص","")))))))
A37: 1603 | B37: مصروفات مدفوعة مقدمًا أخرى | C37: Other Prepaids | D37: A | E37: 3 | F37: نعم | G37: مدين | H37: 0 | I37: OPERATING | J37: نعم | K37: نعم | L37: نعم | P37: =IF($A37="","",IF($F37="نعم",$A37,$M37)) | Q37: =IF($A37="","",IF($F37="نعم",$A37,$N37)) | R37: =IF($A37="","",IF(AND($F37="نعم",$L37<>"لا"),1,0)) | S37: =IF($D37="","",IFERROR(INDEX(Lists!$AK$5:$AK$10,MATCH($D37,Lists!$AJ$5:$AJ$10,0)),"نوع غير معرف")) | T37: =IF($A37="","",IF(COUNTIF($A:$A,$A37)>1,"كود حساب مكرر",IF($B37="","اسم الحساب ناقص",IF(AND($F37="نعم",$G37=""),"الطبيعة ناقصة",IF(AND($F37<>"نعم",OR($M37="",$N37="")),"الحساب الرئيسي يحتاج نطاقًا (من/إلى)",IF(AND($H37=1,$F37<>"نعم"),"حساب نقدية يجب أن يكون قابلًا للترحيل",IF(AND($F37="نعم",$D37=""),"النوع ناقص","")))))))
A38: 1610 | B38: ضريبة قيمة مضافة - مدخلات | C38: VAT Input | D38: A | E38: 3 | F38: نعم | G38: مدين | H38: 0 | I38: OPERATING | J38: لا | K38: لا | L38: نعم | O38: تُستخدم فقط عند تفعيل الضريبة | P38: =IF($A38="","",IF($F38="نعم",$A38,$M38)) | Q38: =IF($A38="","",IF($F38="نعم",$A38,$N38)) | R38: =IF($A38="","",IF(AND($F38="نعم",$L38<>"لا"),1,0)) | S38: =IF($D38="","",IFERROR(INDEX(Lists!$AK$5:$AK$10,MATCH($D38,Lists!$AJ$5:$AJ$10,0)),"نوع غير معرف")) | T38: =IF($A38="","",IF(COUNTIF($A:$A,$A38)>1,"كود حساب مكرر",IF($B38="","اسم الحساب ناقص",IF(AND($F38="نعم",$G38=""),"الطبيعة ناقصة",IF(AND($F38<>"نعم",OR($M38="",$N38="")),"الحساب الرئيسي يحتاج نطاقًا (من/إلى)",IF(AND($H38=1,$F38<>"نعم"),"حساب نقدية يجب أن يكون قابلًا للترحيل",IF(AND($F38="نعم",$D38=""),"النوع ناقص","")))))))
A39: 1700 | B39: الأصول الثابتة | C39: Fixed Assets | D39: A | E39: 2 | F39: لا | G39: مدين | H39: 0 | I39: OPERATING | J39: لا | K39: لا | L39: نعم | M39: 1700 | N39: 1799 | P39: =IF($A39="","",IF($F39="نعم",$A39,$M39)) | Q39: =IF($A39="","",IF($F39="نعم",$A39,$N39)) | R39: =IF($A39="","",IF(AND($F39="نعم",$L39<>"لا"),1,0)) | S39: =IF($D39="","",IFERROR(INDEX(Lists!$AK$5:$AK$10,MATCH($D39,Lists!$AJ$5:$AJ$10,0)),"نوع غير معرف")) | T39: =IF($A39="","",IF(COUNTIF($A:$A,$A39)>1,"كود حساب مكرر",IF($B39="","اسم الحساب ناقص",IF(AND($F39="نعم",$G39=""),"الطبيعة ناقصة",IF(AND($F39<>"نعم",OR($M39="",$N39="")),"الحساب الرئيسي يحتاج نطاقًا (من/إلى)",IF(AND($H39=1,$F39<>"نعم"),"حساب نقدية يجب أن يكون قابلًا للترحيل",IF(AND($F39="نعم",$D39=""),"النوع ناقص","")))))))
A40: 1701 | B40: معدات المطابخ والأفران | C40: Kitchen Equipment & Ovens | D40: A | E40: 3 | F40: نعم | G40: مدين | H40: 0 | I40: INVESTING | J40: لا | K40: نعم | L40: نعم | P40: =IF($A40="","",IF($F40="نعم",$A40,$M40)) | Q40: =IF($A40="","",IF($F40="نعم",$A40,$N40)) | R40: =IF($A40="","",IF(AND($F40="نعم",$L40<>"لا"),1,0)) | S40: =IF($D40="","",IFERROR(INDEX(Lists!$AK$5:$AK$10,MATCH($D40,Lists!$AJ$5:$AJ$10,0)),"نوع غير معرف")) | T40: =IF($A40="","",IF(COUNTIF($A:$A,$A40)>1,"كود حساب مكرر",IF($B40="","اسم الحساب ناقص",IF(AND($F40="نعم",$G40=""),"الطبيعة ناقصة",IF(AND($F40<>"نعم",OR($M40="",$N40="")),"الحساب الرئيسي يحتاج نطاقًا (من/إلى)",IF(AND($H40=1,$F40<>"نعم"),"حساب نقدية يجب أن يكون قابلًا للترحيل",IF(AND($F40="نعم",$D40=""),"النوع ناقص","")))))))
A41: 1702 | B41: أثاث وتجهيزات | C41: Furniture & Fixtures | D41: A | E41: 3 | F41: نعم | G41: مدين | H41: 0 | I41: INVESTING | J41: لا | K41: نعم | L41: نعم | P41: =IF($A41="","",IF($F41="نعم",$A41,$M41)) | Q41: =IF($A41="","",IF($F41="نعم",$A41,$N41)) | R41: =IF($A41="","",IF(AND($F41="نعم",$L41<>"لا"),1,0)) | S41: =IF($D41="","",IFERROR(INDEX(Lists!$AK$5:$AK$10,MATCH($D41,Lists!$AJ$5:$AJ$10,0)),"نوع غير معرف")) | T41: =IF($A41="","",IF(COUNTIF($A:$A,$A41)>1,"كود حساب مكرر",IF($B41="","اسم الحساب ناقص",IF(AND($F41="نعم",$G41=""),"الطبيعة ناقصة",IF(AND($F41<>"نعم",OR($M41="",$N41="")),"الحساب الرئيسي يحتاج نطاقًا (من/إلى)",IF(AND($H41=1,$F41<>"نعم"),"حساب نقدية يجب أن يكون قابلًا للترحيل",IF(AND($F41="نعم",$D41=""),"النوع ناقص","")))))))
A42: 1703 | B42: أجهزة وحاسبات ونظم نقاط البيع | C42: IT & POS Equipment | D42: A | E42: 3 | F42: نعم | G42: مدين | H42: 0 | I42: INVESTING | J42: لا | K42: نعم | L42: نعم | P42: =IF($A42="","",IF($F42="نعم",$A42,$M42)) | Q42: =IF($A42="","",IF($F42="نعم",$A42,$N42)) | R42: =IF($A42="","",IF(AND($F42="نعم",$L42<>"لا"),1,0)) | S42: =IF($D42="","",IFERROR(INDEX(Lists!$AK$5:$AK$10,MATCH($D42,Lists!$AJ$5:$AJ$10,0)),"نوع غير معرف")) | T42: =IF($A42="","",IF(COUNTIF($A:$A,$A42)>1,"كود حساب مكرر",IF($B42="","اسم الحساب ناقص",IF(AND($F42="نعم",$G42=""),"الطبيعة ناقصة",IF(AND($F42<>"نعم",OR($M42="",$N42="")),"الحساب الرئيسي يحتاج نطاقًا (من/إلى)",IF(AND($H42=1,$F42<>"نعم"),"حساب نقدية يجب أن يكون قابلًا للترحيل",IF(AND($F42="نعم",$D42=""),"النوع ناقص","")))))))
A43: 1704 | B43: ديكورات وتجهيزات الفروع | C43: Leasehold Improvements | D43: A | E43: 3 | F43: نعم | G43: مدين | H43: 0 | I43: INVESTING | J43: لا | K43: نعم | L43: نعم | P43: =IF($A43="","",IF($F43="نعم",$A43,$M43)) | Q43: =IF($A43="","",IF($F43="نعم",$A43,$N43)) | R43: =IF($A43="","",IF(AND($F43="نعم",$L43<>"لا"),1,0)) | S43: =IF($D43="","",IFERROR(INDEX(Lists!$AK$5:$AK$10,MATCH($D43,Lists!$AJ$5:$AJ$10,0)),"نوع غير معرف")) | T43: =IF($A43="","",IF(COUNTIF($A:$A,$A43)>1,"كود حساب مكرر",IF($B43="","اسم الحساب ناقص",IF(AND($F43="نعم",$G43=""),"الطبيعة ناقصة",IF(AND($F43<>"نعم",OR($M43="",$N43="")),"الحساب الرئيسي يحتاج نطاقًا (من/إلى)",IF(AND($H43=1,$F43<>"نعم"),"حساب نقدية يجب أن يكون قابلًا للترحيل",IF(AND($F43="نعم",$D43=""),"النوع ناقص","")))))))
A44: 1790 | B44: مجمع الإهلاك | C44: Accumulated Depreciation | D44: A | E44: 2 | F44: لا | G44: دائن | H44: 0 | I44: OPERATING | J44: لا | K44: لا | L44: نعم | M44: 1790 | N44: 1799 | P44: =IF($A44="","",IF($F44="نعم",$A44,$M44)) | Q44: =IF($A44="","",IF($F44="نعم",$A44,$N44)) | R44: =IF($A44="","",IF(AND($F44="نعم",$L44<>"لا"),1,0)) | S44: =IF($D44="","",IFERROR(INDEX(Lists!$AK$5:$AK$10,MATCH($D44,Lists!$AJ$5:$AJ$10,0)),"نوع غير معرف")) | T44: =IF($A44="","",IF(COUNTIF($A:$A,$A44)>1,"كود حساب مكرر",IF($B44="","اسم الحساب ناقص",IF(AND($F44="نعم",$G44=""),"الطبيعة ناقصة",IF(AND($F44<>"نعم",OR($M44="",$N44="")),"الحساب الرئيسي يحتاج نطاقًا (من/إلى)",IF(AND($H44=1,$F44<>"نعم"),"حساب نقدية يجب أن يكون قابلًا للترحيل",IF(AND($F44="نعم",$D44=""),"النوع ناقص","")))))))
A45: 1791 | B45: مجمع إهلاك معدات المطابخ | C45: Acc. Dep. - Kitchen Equipment | D45: A | E45: 3 | F45: نعم | G45: دائن | H45: 0 | I45: OPERATING | J45: لا | K45: لا | L45: نعم | P45: =IF($A45="","",IF($F45="نعم",$A45,$M45)) | Q45: =IF($A45="","",IF($F45="نعم",$A45,$N45)) | R45: =IF($A45="","",IF(AND($F45="نعم",$L45<>"لا"),1,0)) | S45: =IF($D45="","",IFERROR(INDEX(Lists!$AK$5:$AK$10,MATCH($D45,Lists!$AJ$5:$AJ$10,0)),"نوع غير معرف")) | T45: =IF($A45="","",IF(COUNTIF($A:$A,$A45)>1,"كود حساب مكرر",IF($B45="","اسم الحساب ناقص",IF(AND($F45="نعم",$G45=""),"الطبيعة ناقصة",IF(AND($F45<>"نعم",OR($M45="",$N45="")),"الحساب الرئيسي يحتاج نطاقًا (من/إلى)",IF(AND($H45=1,$F45<>"نعم"),"حساب نقدية يجب أن يكون قابلًا للترحيل",IF(AND($F45="نعم",$D45=""),"النوع ناقص","")))))))
A46: 1792 | B46: مجمع إهلاك الأثاث والتجهيزات | C46: Acc. Dep. - Furniture | D46: A | E46: 3 | F46: نعم | G46: دائن | H46: 0 | I46: OPERATING | J46: لا | K46: لا | L46: نعم | P46: =IF($A46="","",IF($F46="نعم",$A46,$M46)) | Q46: =IF($A46="","",IF($F46="نعم",$A46,$N46)) | R46: =IF($A46="","",IF(AND($F46="نعم",$L46<>"لا"),1,0)) | S46: =IF($D46="","",IFERROR(INDEX(Lists!$AK$5:$AK$10,MATCH($D46,Lists!$AJ$5:$AJ$10,0)),"نوع غير معرف")) | T46: =IF($A46="","",IF(COUNTIF($A:$A,$A46)>1,"كود حساب مكرر",IF($B46="","اسم الحساب ناقص",IF(AND($F46="نعم",$G46=""),"الطبيعة ناقصة",IF(AND($F46<>"نعم",OR($M46="",$N46="")),"الحساب الرئيسي يحتاج نطاقًا (من/إلى)",IF(AND($H46=1,$F46<>"نعم"),"حساب نقدية يجب أن يكون قابلًا للترحيل",IF(AND($F46="نعم",$D46=""),"النوع ناقص","")))))))
A47: 1793 | B47: مجمع إهلاك الأجهزة والحاسبات | C47: Acc. Dep. - IT | D47: A | E47: 3 | F47: نعم | G47: دائن | H47: 0 | I47: OPERATING | J47: لا | K47: لا | L47: نعم | P47: =IF($A47="","",IF($F47="نعم",$A47,$M47)) | Q47: =IF($A47="","",IF($F47="نعم",$A47,$N47)) | R47: =IF($A47="","",IF(AND($F47="نعم",$L47<>"لا"),1,0)) | S47: =IF($D47="","",IFERROR(INDEX(Lists!$AK$5:$AK$10,MATCH($D47,Lists!$AJ$5:$AJ$10,0)),"نوع غير معرف")) | T47: =IF($A47="","",IF(COUNTIF($A:$A,$A47)>1,"كود حساب مكرر",IF($B47="","اسم الحساب ناقص",IF(AND($F47="نعم",$G47=""),"الطبيعة ناقصة",IF(AND($F47<>"نعم",OR($M47="",$N47="")),"الحساب الرئيسي يحتاج نطاقًا (من/إلى)",IF(AND($H47=1,$F47<>"نعم"),"حساب نقدية يجب أن يكون قابلًا للترحيل",IF(AND($F47="نعم",$D47=""),"النوع ناقص","")))))))
A48: 1794 | B48: مجمع إهلاك الديكورات | C48: Acc. Dep. - Leasehold | D48: A | E48: 3 | F48: نعم | G48: دائن | H48: 0 | I48: OPERATING | J48: لا | K48: لا | L48: نعم | P48: =IF($A48="","",IF($F48="نعم",$A48,$M48)) | Q48: =IF($A48="","",IF($F48="نعم",$A48,$N48)) | R48: =IF($A48="","",IF(AND($F48="نعم",$L48<>"لا"),1,0)) | S48: =IF($D48="","",IFERROR(INDEX(Lists!$AK$5:$AK$10,MATCH($D48,Lists!$AJ$5:$AJ$10,0)),"نوع غير معرف")) | T48: =IF($A48="","",IF(COUNTIF($A:$A,$A48)>1,"كود حساب مكرر",IF($B48="","اسم الحساب ناقص",IF(AND($F48="نعم",$G48=""),"الطبيعة ناقصة",IF(AND($F48<>"نعم",OR($M48="",$N48="")),"الحساب الرئيسي يحتاج نطاقًا (من/إلى)",IF(AND($H48=1,$F48<>"نعم"),"حساب نقدية يجب أن يكون قابلًا للترحيل",IF(AND($F48="نعم",$D48=""),"النوع ناقص","")))))))
A49: 2000 | B49: الالتزامات | C49: Liabilities | D49: L | E49: 1 | F49: لا | G49: دائن | H49: 0 | I49: OPERATING | J49: لا | K49: لا | L49: نعم | M49: 2000 | N49: 2999 | P49: =IF($A49="","",IF($F49="نعم",$A49,$M49)) | Q49: =IF($A49="","",IF($F49="نعم",$A49,$N49)) | R49: =IF($A49="","",IF(AND($F49="نعم",$L49<>"لا"),1,0)) | S49: =IF($D49="","",IFERROR(INDEX(Lists!$AK$5:$AK$10,MATCH($D49,Lists!$AJ$5:$AJ$10,0)),"نوع غير معرف")) | T49: =IF($A49="","",IF(COUNTIF($A:$A,$A49)>1,"كود حساب مكرر",IF($B49="","اسم الحساب ناقص",IF(AND($F49="نعم",$G49=""),"الطبيعة ناقصة",IF(AND($F49<>"نعم",OR($M49="",$N49="")),"الحساب الرئيسي يحتاج نطاقًا (من/إلى)",IF(AND($H49=1,$F49<>"نعم"),"حساب نقدية يجب أن يكون قابلًا للترحيل",IF(AND($F49="نعم",$D49=""),"النوع ناقص","")))))))
A50: 2100 | B50: الموردون | C50: Suppliers | D50: L | E50: 2 | F50: لا | G50: دائن | H50: 0 | I50: OPERATING | J50: لا | K50: لا | L50: نعم | M50: 2100 | N50: 2199 | P50: =IF($A50="","",IF($F50="نعم",$A50,$M50)) | Q50: =IF($A50="","",IF($F50="نعم",$A50,$N50)) | R50: =IF($A50="","",IF(AND($F50="نعم",$L50<>"لا"),1,0)) | S50: =IF($D50="","",IFERROR(INDEX(Lists!$AK$5:$AK$10,MATCH($D50,Lists!$AJ$5:$AJ$10,0)),"نوع غير معرف")) | T50: =IF($A50="","",IF(COUNTIF($A:$A,$A50)>1,"كود حساب مكرر",IF($B50="","اسم الحساب ناقص",IF(AND($F50="نعم",$G50=""),"الطبيعة ناقصة",IF(AND($F50<>"نعم",OR($M50="",$N50="")),"الحساب الرئيسي يحتاج نطاقًا (من/إلى)",IF(AND($H50=1,$F50<>"نعم"),"حساب نقدية يجب أن يكون قابلًا للترحيل",IF(AND($F50="نعم",$D50=""),"النوع ناقص","")))))))
A51: 2101 | B51: موردون (ذمم دائنة) | C51: Trade Payables | D51: L | E51: 3 | F51: نعم | G51: دائن | H51: 0 | I51: OPERATING | J51: لا | K51: لا | L51: نعم | P51: =IF($A51="","",IF($F51="نعم",$A51,$M51)) | Q51: =IF($A51="","",IF($F51="نعم",$A51,$N51)) | R51: =IF($A51="","",IF(AND($F51="نعم",$L51<>"لا"),1,0)) | S51: =IF($D51="","",IFERROR(INDEX(Lists!$AK$5:$AK$10,MATCH($D51,Lists!$AJ$5:$AJ$10,0)),"نوع غير معرف")) | T51: =IF($A51="","",IF(COUNTIF($A:$A,$A51)>1,"كود حساب مكرر",IF($B51="","اسم الحساب ناقص",IF(AND($F51="نعم",$G51=""),"الطبيعة ناقصة",IF(AND($F51<>"نعم",OR($M51="",$N51="")),"الحساب الرئيسي يحتاج نطاقًا (من/إلى)",IF(AND($H51=1,$F51<>"نعم"),"حساب نقدية يجب أن يكون قابلًا للترحيل",IF(AND($F51="نعم",$D51=""),"النوع ناقص","")))))))
A52: 2110 | B52: بضاعة مستلمة غير مفوترة (GRNI) | C52: Goods Received Not Invoiced | D52: L | E52: 3 | F52: نعم | G52: دائن | H52: 0 | I52: OPERATING | J52: لا | K52: لا | L52: نعم | O52: المرحلة 2 | P52: =IF($A52="","",IF($F52="نعم",$A52,$M52)) | Q52: =IF($A52="","",IF($F52="نعم",$A52,$N52)) | R52: =IF($A52="","",IF(AND($F52="نعم",$L52<>"لا"),1,0)) | S52: =IF($D52="","",IFERROR(INDEX(Lists!$AK$5:$AK$10,MATCH($D52,Lists!$AJ$5:$AJ$10,0)),"نوع غير معرف")) | T52: =IF($A52="","",IF(COUNTIF($A:$A,$A52)>1,"كود حساب مكرر",IF($B52="","اسم الحساب ناقص",IF(AND($F52="نعم",$G52=""),"الطبيعة ناقصة",IF(AND($F52<>"نعم",OR($M52="",$N52="")),"الحساب الرئيسي يحتاج نطاقًا (من/إلى)",IF(AND($H52=1,$F52<>"نعم"),"حساب نقدية يجب أن يكون قابلًا للترحيل",IF(AND($F52="نعم",$D52=""),"النوع ناقص","")))))))
A53: 2200 | B53: المصروفات والرواتب المستحقة | C53: Accruals | D53: L | E53: 2 | F53: لا | G53: دائن | H53: 0 | I53: OPERATING | J53: لا | K53: لا | L53: نعم | M53: 2200 | N53: 2299 | P53: =IF($A53="","",IF($F53="نعم",$A53,$M53)) | Q53: =IF($A53="","",IF($F53="نعم",$A53,$N53)) | R53: =IF($A53="","",IF(AND($F53="نعم",$L53<>"لا"),1,0)) | S53: =IF($D53="","",IFERROR(INDEX(Lists!$AK$5:$AK$10,MATCH($D53,Lists!$AJ$5:$AJ$10,0)),"نوع غير معرف")) | T53: =IF($A53="","",IF(COUNTIF($A:$A,$A53)>1,"كود حساب مكرر",IF($B53="","اسم الحساب ناقص",IF(AND($F53="نعم",$G53=""),"الطبيعة ناقصة",IF(AND($F53<>"نعم",OR($M53="",$N53="")),"الحساب الرئيسي يحتاج نطاقًا (من/إلى)",IF(AND($H53=1,$F53<>"نعم"),"حساب نقدية يجب أن يكون قابلًا للترحيل",IF(AND($F53="نعم",$D53=""),"النوع ناقص","")))))))
A54: 2201 | B54: مصروفات مستحقة | C54: Accrued Expenses | D54: L | E54: 3 | F54: نعم | G54: دائن | H54: 0 | I54: OPERATING | J54: لا | K54: لا | L54: نعم | P54: =IF($A54="","",IF($F54="نعم",$A54,$M54)) | Q54: =IF($A54="","",IF($F54="نعم",$A54,$N54)) | R54: =IF($A54="","",IF(AND($F54="نعم",$L54<>"لا"),1,0)) | S54: =IF($D54="","",IFERROR(INDEX(Lists!$AK$5:$AK$10,MATCH($D54,Lists!$AJ$5:$AJ$10,0)),"نوع غير معرف")) | T54: =IF($A54="","",IF(COUNTIF($A:$A,$A54)>1,"كود حساب مكرر",IF($B54="","اسم الحساب ناقص",IF(AND($F54="نعم",$G54=""),"الطبيعة ناقصة",IF(AND($F54<>"نعم",OR($M54="",$N54="")),"الحساب الرئيسي يحتاج نطاقًا (من/إلى)",IF(AND($H54=1,$F54<>"نعم"),"حساب نقدية يجب أن يكون قابلًا للترحيل",IF(AND($F54="نعم",$D54=""),"النوع ناقص","")))))))
A55: 2202 | B55: رواتب وأجور مستحقة | C55: Accrued Salaries | D55: L | E55: 3 | F55: نعم | G55: دائن | H55: 0 | I55: OPERATING | J55: لا | K55: لا | L55: نعم | P55: =IF($A55="","",IF($F55="نعم",$A55,$M55)) | Q55: =IF($A55="","",IF($F55="نعم",$A55,$N55)) | R55: =IF($A55="","",IF(AND($F55="نعم",$L55<>"لا"),1,0)) | S55: =IF($D55="","",IFERROR(INDEX(Lists!$AK$5:$AK$10,MATCH($D55,Lists!$AJ$5:$AJ$10,0)),"نوع غير معرف")) | T55: =IF($A55="","",IF(COUNTIF($A:$A,$A55)>1,"كود حساب مكرر",IF($B55="","اسم الحساب ناقص",IF(AND($F55="نعم",$G55=""),"الطبيعة ناقصة",IF(AND($F55<>"نعم",OR($M55="",$N55="")),"الحساب الرئيسي يحتاج نطاقًا (من/إلى)",IF(AND($H55=1,$F55<>"نعم"),"حساب نقدية يجب أن يكون قابلًا للترحيل",IF(AND($F55="نعم",$D55=""),"النوع ناقص","")))))))
A56: 2203 | B56: تأمينات اجتماعية مستحقة | C56: Social Insurance Payable | D56: L | E56: 3 | F56: نعم | G56: دائن | H56: 0 | I56: OPERATING | J56: لا | K56: لا | L56: نعم | P56: =IF($A56="","",IF($F56="نعم",$A56,$M56)) | Q56: =IF($A56="","",IF($F56="نعم",$A56,$N56)) | R56: =IF($A56="","",IF(AND($F56="نعم",$L56<>"لا"),1,0)) | S56: =IF($D56="","",IFERROR(INDEX(Lists!$AK$5:$AK$10,MATCH($D56,Lists!$AJ$5:$AJ$10,0)),"نوع غير معرف")) | T56: =IF($A56="","",IF(COUNTIF($A:$A,$A56)>1,"كود حساب مكرر",IF($B56="","اسم الحساب ناقص",IF(AND($F56="نعم",$G56=""),"الطبيعة ناقصة",IF(AND($F56<>"نعم",OR($M56="",$N56="")),"الحساب الرئيسي يحتاج نطاقًا (من/إلى)",IF(AND($H56=1,$F56<>"نعم"),"حساب نقدية يجب أن يكون قابلًا للترحيل",IF(AND($F56="نعم",$D56=""),"النوع ناقص","")))))))
A57: 2300 | B57: الضرائب المستحقة | C57: Taxes Payable | D57: L | E57: 2 | F57: لا | G57: دائن | H57: 0 | I57: OPERATING | J57: لا | K57: لا | L57: نعم | M57: 2300 | N57: 2399 | P57: =IF($A57="","",IF($F57="نعم",$A57,$M57)) | Q57: =IF($A57="","",IF($F57="نعم",$A57,$N57)) | R57: =IF($A57="","",IF(AND($F57="نعم",$L57<>"لا"),1,0)) | S57: =IF($D57="","",IFERROR(INDEX(Lists!$AK$5:$AK$10,MATCH($D57,Lists!$AJ$5:$AJ$10,0)),"نوع غير معرف")) | T57: =IF($A57="","",IF(COUNTIF($A:$A,$A57)>1,"كود حساب مكرر",IF($B57="","اسم الحساب ناقص",IF(AND($F57="نعم",$G57=""),"الطبيعة ناقصة",IF(AND($F57<>"نعم",OR($M57="",$N57="")),"الحساب الرئيسي يحتاج نطاقًا (من/إلى)",IF(AND($H57=1,$F57<>"نعم"),"حساب نقدية يجب أن يكون قابلًا للترحيل",IF(AND($F57="نعم",$D57=""),"النوع ناقص","")))))))
A58: 2301 | B58: ضريبة قيمة مضافة - مخرجات | C58: VAT Output | D58: L | E58: 3 | F58: نعم | G58: دائن | H58: 0 | I58: OPERATING | J58: لا | K58: لا | L58: نعم | O58: تُستخدم فقط عند تفعيل الضريبة | P58: =IF($A58="","",IF($F58="نعم",$A58,$M58)) | Q58: =IF($A58="","",IF($F58="نعم",$A58,$N58)) | R58: =IF($A58="","",IF(AND($F58="نعم",$L58<>"لا"),1,0)) | S58: =IF($D58="","",IFERROR(INDEX(Lists!$AK$5:$AK$10,MATCH($D58,Lists!$AJ$5:$AJ$10,0)),"نوع غير معرف")) | T58: =IF($A58="","",IF(COUNTIF($A:$A,$A58)>1,"كود حساب مكرر",IF($B58="","اسم الحساب ناقص",IF(AND($F58="نعم",$G58=""),"الطبيعة ناقصة",IF(AND($F58<>"نعم",OR($M58="",$N58="")),"الحساب الرئيسي يحتاج نطاقًا (من/إلى)",IF(AND($H58=1,$F58<>"نعم"),"حساب نقدية يجب أن يكون قابلًا للترحيل",IF(AND($F58="نعم",$D58=""),"النوع ناقص","")))))))
A59: 2302 | B59: ضرائب ورسوم أخرى مستحقة | C59: Other Taxes Payable | D59: L | E59: 3 | F59: نعم | G59: دائن | H59: 0 | I59: OPERATING | J59: لا | K59: لا | L59: نعم | P59: =IF($A59="","",IF($F59="نعم",$A59,$M59)) | Q59: =IF($A59="","",IF($F59="نعم",$A59,$N59)) | R59: =IF($A59="","",IF(AND($F59="نعم",$L59<>"لا"),1,0)) | S59: =IF($D59="","",IFERROR(INDEX(Lists!$AK$5:$AK$10,MATCH($D59,Lists!$AJ$5:$AJ$10,0)),"نوع غير معرف")) | T59: =IF($A59="","",IF(COUNTIF($A:$A,$A59)>1,"كود حساب مكرر",IF($B59="","اسم الحساب ناقص",IF(AND($F59="نعم",$G59=""),"الطبيعة ناقصة",IF(AND($F59<>"نعم",OR($M59="",$N59="")),"الحساب الرئيسي يحتاج نطاقًا (من/إلى)",IF(AND($H59=1,$F59<>"نعم"),"حساب نقدية يجب أن يكون قابلًا للترحيل",IF(AND($F59="نعم",$D59=""),"النوع ناقص","")))))))
A60: 2400 | B60: التزامات أخرى | C60: Other Liabilities | D60: L | E60: 2 | F60: لا | G60: دائن | H60: 0 | I60: OPERATING | J60: لا | K60: لا | L60: نعم | M60: 2400 | N60: 2499 | P60: =IF($A60="","",IF($F60="نعم",$A60,$M60)) | Q60: =IF($A60="","",IF($F60="نعم",$A60,$N60)) | R60: =IF($A60="","",IF(AND($F60="نعم",$L60<>"لا"),1,0)) | S60: =IF($D60="","",IFERROR(INDEX(Lists!$AK$5:$AK$10,MATCH($D60,Lists!$AJ$5:$AJ$10,0)),"نوع غير معرف")) | T60: =IF($A60="","",IF(COUNTIF($A:$A,$A60)>1,"كود حساب مكرر",IF($B60="","اسم الحساب ناقص",IF(AND($F60="نعم",$G60=""),"الطبيعة ناقصة",IF(AND($F60<>"نعم",OR($M60="",$N60="")),"الحساب الرئيسي يحتاج نطاقًا (من/إلى)",IF(AND($H60=1,$F60<>"نعم"),"حساب نقدية يجب أن يكون قابلًا للترحيل",IF(AND($F60="نعم",$D60=""),"النوع ناقص","")))))))
A61: 2401 | B61: أمانات وتأمينات من الغير | C61: Deposits Held | D61: L | E61: 3 | F61: نعم | G61: دائن | H61: 0 | I61: FINANCING | J61: لا | K61: لا | L61: نعم | P61: =IF($A61="","",IF($F61="نعم",$A61,$M61)) | Q61: =IF($A61="","",IF($F61="نعم",$A61,$N61)) | R61: =IF($A61="","",IF(AND($F61="نعم",$L61<>"لا"),1,0)) | S61: =IF($D61="","",IFERROR(INDEX(Lists!$AK$5:$AK$10,MATCH($D61,Lists!$AJ$5:$AJ$10,0)),"نوع غير معرف")) | T61: =IF($A61="","",IF(COUNTIF($A:$A,$A61)>1,"كود حساب مكرر",IF($B61="","اسم الحساب ناقص",IF(AND($F61="نعم",$G61=""),"الطبيعة ناقصة",IF(AND($F61<>"نعم",OR($M61="",$N61="")),"الحساب الرئيسي يحتاج نطاقًا (من/إلى)",IF(AND($H61=1,$F61<>"نعم"),"حساب نقدية يجب أن يكون قابلًا للترحيل",IF(AND($F61="نعم",$D61=""),"النوع ناقص","")))))))
A62: 2402 | B62: قروض وتمويل | C62: Loans | D62: L | E62: 3 | F62: نعم | G62: دائن | H62: 0 | I62: FINANCING | J62: لا | K62: لا | L62: نعم | P62: =IF($A62="","",IF($F62="نعم",$A62,$M62)) | Q62: =IF($A62="","",IF($F62="نعم",$A62,$N62)) | R62: =IF($A62="","",IF(AND($F62="نعم",$L62<>"لا"),1,0)) | S62: =IF($D62="","",IFERROR(INDEX(Lists!$AK$5:$AK$10,MATCH($D62,Lists!$AJ$5:$AJ$10,0)),"نوع غير معرف")) | T62: =IF($A62="","",IF(COUNTIF($A:$A,$A62)>1,"كود حساب مكرر",IF($B62="","اسم الحساب ناقص",IF(AND($F62="نعم",$G62=""),"الطبيعة ناقصة",IF(AND($F62<>"نعم",OR($M62="",$N62="")),"الحساب الرئيسي يحتاج نطاقًا (من/إلى)",IF(AND($H62=1,$F62<>"نعم"),"حساب نقدية يجب أن يكون قابلًا للترحيل",IF(AND($F62="نعم",$D62=""),"النوع ناقص","")))))))
A63: 2403 | B63: التزامات أخرى | C63: Other Payables | D63: L | E63: 3 | F63: نعم | G63: دائن | H63: 0 | I63: OPERATING | J63: لا | K63: لا | L63: نعم | P63: =IF($A63="","",IF($F63="نعم",$A63,$M63)) | Q63: =IF($A63="","",IF($F63="نعم",$A63,$N63)) | R63: =IF($A63="","",IF(AND($F63="نعم",$L63<>"لا"),1,0)) | S63: =IF($D63="","",IFERROR(INDEX(Lists!$AK$5:$AK$10,MATCH($D63,Lists!$AJ$5:$AJ$10,0)),"نوع غير معرف")) | T63: =IF($A63="","",IF(COUNTIF($A:$A,$A63)>1,"كود حساب مكرر",IF($B63="","اسم الحساب ناقص",IF(AND($F63="نعم",$G63=""),"الطبيعة ناقصة",IF(AND($F63<>"نعم",OR($M63="",$N63="")),"الحساب الرئيسي يحتاج نطاقًا (من/إلى)",IF(AND($H63=1,$F63<>"نعم"),"حساب نقدية يجب أن يكون قابلًا للترحيل",IF(AND($F63="نعم",$D63=""),"النوع ناقص","")))))))
A64: 2900 | B64: حسابات معلقة | C64: Suspense | D64: L | E64: 2 | F64: لا | G64: دائن | H64: 0 | I64: OPERATING | J64: لا | K64: لا | L64: نعم | M64: 2900 | N64: 2999 | P64: =IF($A64="","",IF($F64="نعم",$A64,$M64)) | Q64: =IF($A64="","",IF($F64="نعم",$A64,$N64)) | R64: =IF($A64="","",IF(AND($F64="نعم",$L64<>"لا"),1,0)) | S64: =IF($D64="","",IFERROR(INDEX(Lists!$AK$5:$AK$10,MATCH($D64,Lists!$AJ$5:$AJ$10,0)),"نوع غير معرف")) | T64: =IF($A64="","",IF(COUNTIF($A:$A,$A64)>1,"كود حساب مكرر",IF($B64="","اسم الحساب ناقص",IF(AND($F64="نعم",$G64=""),"الطبيعة ناقصة",IF(AND($F64<>"نعم",OR($M64="",$N64="")),"الحساب الرئيسي يحتاج نطاقًا (من/إلى)",IF(AND($H64=1,$F64<>"نعم"),"حساب نقدية يجب أن يكون قابلًا للترحيل",IF(AND($F64="نعم",$D64=""),"النوع ناقص","")))))))
A65: 2901 | B65: حساب معلق (يجب تصفيره قبل الإقفال) | C65: Suspense Account | D65: L | E65: 3 | F65: نعم | G65: دائن | H65: 0 | I65: OPERATING | J65: لا | K65: لا | L65: نعم | P65: =IF($A65="","",IF($F65="نعم",$A65,$M65)) | Q65: =IF($A65="","",IF($F65="نعم",$A65,$N65)) | R65: =IF($A65="","",IF(AND($F65="نعم",$L65<>"لا"),1,0)) | S65: =IF($D65="","",IFERROR(INDEX(Lists!$AK$5:$AK$10,MATCH($D65,Lists!$AJ$5:$AJ$10,0)),"نوع غير معرف")) | T65: =IF($A65="","",IF(COUNTIF($A:$A,$A65)>1,"كود حساب مكرر",IF($B65="","اسم الحساب ناقص",IF(AND($F65="نعم",$G65=""),"الطبيعة ناقصة",IF(AND($F65<>"نعم",OR($M65="",$N65="")),"الحساب الرئيسي يحتاج نطاقًا (من/إلى)",IF(AND($H65=1,$F65<>"نعم"),"حساب نقدية يجب أن يكون قابلًا للترحيل",IF(AND($F65="نعم",$D65=""),"النوع ناقص","")))))))
A66: 3000 | B66: حقوق الملكية | C66: Equity | D66: E | E66: 1 | F66: لا | G66: دائن | H66: 0 | I66: OPERATING | J66: لا | K66: لا | L66: نعم | M66: 3000 | N66: 3999 | P66: =IF($A66="","",IF($F66="نعم",$A66,$M66)) | Q66: =IF($A66="","",IF($F66="نعم",$A66,$N66)) | R66: =IF($A66="","",IF(AND($F66="نعم",$L66<>"لا"),1,0)) | S66: =IF($D66="","",IFERROR(INDEX(Lists!$AK$5:$AK$10,MATCH($D66,Lists!$AJ$5:$AJ$10,0)),"نوع غير معرف")) | T66: =IF($A66="","",IF(COUNTIF($A:$A,$A66)>1,"كود حساب مكرر",IF($B66="","اسم الحساب ناقص",IF(AND($F66="نعم",$G66=""),"الطبيعة ناقصة",IF(AND($F66<>"نعم",OR($M66="",$N66="")),"الحساب الرئيسي يحتاج نطاقًا (من/إلى)",IF(AND($H66=1,$F66<>"نعم"),"حساب نقدية يجب أن يكون قابلًا للترحيل",IF(AND($F66="نعم",$D66=""),"النوع ناقص","")))))))
A67: 3100 | B67: رأس المال | C67: Capital | D67: E | E67: 2 | F67: لا | G67: دائن | H67: 0 | I67: OPERATING | J67: لا | K67: لا | L67: نعم | M67: 3100 | N67: 3199 | P67: =IF($A67="","",IF($F67="نعم",$A67,$M67)) | Q67: =IF($A67="","",IF($F67="نعم",$A67,$N67)) | R67: =IF($A67="","",IF(AND($F67="نعم",$L67<>"لا"),1,0)) | S67: =IF($D67="","",IFERROR(INDEX(Lists!$AK$5:$AK$10,MATCH($D67,Lists!$AJ$5:$AJ$10,0)),"نوع غير معرف")) | T67: =IF($A67="","",IF(COUNTIF($A:$A,$A67)>1,"كود حساب مكرر",IF($B67="","اسم الحساب ناقص",IF(AND($F67="نعم",$G67=""),"الطبيعة ناقصة",IF(AND($F67<>"نعم",OR($M67="",$N67="")),"الحساب الرئيسي يحتاج نطاقًا (من/إلى)",IF(AND($H67=1,$F67<>"نعم"),"حساب نقدية يجب أن يكون قابلًا للترحيل",IF(AND($F67="نعم",$D67=""),"النوع ناقص","")))))))
A68: 3101 | B68: رأس المال | C68: Owner's Capital | D68: E | E68: 3 | F68: نعم | G68: دائن | H68: 0 | I68: FINANCING | J68: لا | K68: لا | L68: نعم | P68: =IF($A68="","",IF($F68="نعم",$A68,$M68)) | Q68: =IF($A68="","",IF($F68="نعم",$A68,$N68)) | R68: =IF($A68="","",IF(AND($F68="نعم",$L68<>"لا"),1,0)) | S68: =IF($D68="","",IFERROR(INDEX(Lists!$AK$5:$AK$10,MATCH($D68,Lists!$AJ$5:$AJ$10,0)),"نوع غير معرف")) | T68: =IF($A68="","",IF(COUNTIF($A:$A,$A68)>1,"كود حساب مكرر",IF($B68="","اسم الحساب ناقص",IF(AND($F68="نعم",$G68=""),"الطبيعة ناقصة",IF(AND($F68<>"نعم",OR($M68="",$N68="")),"الحساب الرئيسي يحتاج نطاقًا (من/إلى)",IF(AND($H68=1,$F68<>"نعم"),"حساب نقدية يجب أن يكون قابلًا للترحيل",IF(AND($F68="نعم",$D68=""),"النوع ناقص","")))))))
A69: 3200 | B69: جاري المالك | C69: Owner Current Account | D69: E | E69: 2 | F69: لا | G69: دائن | H69: 0 | I69: OPERATING | J69: لا | K69: لا | L69: نعم | M69: 3200 | N69: 3299 | P69: =IF($A69="","",IF($F69="نعم",$A69,$M69)) | Q69: =IF($A69="","",IF($F69="نعم",$A69,$N69)) | R69: =IF($A69="","",IF(AND($F69="نعم",$L69<>"لا"),1,0)) | S69: =IF($D69="","",IFERROR(INDEX(Lists!$AK$5:$AK$10,MATCH($D69,Lists!$AJ$5:$AJ$10,0)),"نوع غير معرف")) | T69: =IF($A69="","",IF(COUNTIF($A:$A,$A69)>1,"كود حساب مكرر",IF($B69="","اسم الحساب ناقص",IF(AND($F69="نعم",$G69=""),"الطبيعة ناقصة",IF(AND($F69<>"نعم",OR($M69="",$N69="")),"الحساب الرئيسي يحتاج نطاقًا (من/إلى)",IF(AND($H69=1,$F69<>"نعم"),"حساب نقدية يجب أن يكون قابلًا للترحيل",IF(AND($F69="نعم",$D69=""),"النوع ناقص","")))))))
A70: 3201 | B70: جاري المالك | C70: Owner Current Account | D70: E | E70: 3 | F70: نعم | G70: دائن | H70: 0 | I70: FINANCING | J70: لا | K70: لا | L70: نعم | P70: =IF($A70="","",IF($F70="نعم",$A70,$M70)) | Q70: =IF($A70="","",IF($F70="نعم",$A70,$N70)) | R70: =IF($A70="","",IF(AND($F70="نعم",$L70<>"لا"),1,0)) | S70: =IF($D70="","",IFERROR(INDEX(Lists!$AK$5:$AK$10,MATCH($D70,Lists!$AJ$5:$AJ$10,0)),"نوع غير معرف")) | T70: =IF($A70="","",IF(COUNTIF($A:$A,$A70)>1,"كود حساب مكرر",IF($B70="","اسم الحساب ناقص",IF(AND($F70="نعم",$G70=""),"الطبيعة ناقصة",IF(AND($F70<>"نعم",OR($M70="",$N70="")),"الحساب الرئيسي يحتاج نطاقًا (من/إلى)",IF(AND($H70=1,$F70<>"نعم"),"حساب نقدية يجب أن يكون قابلًا للترحيل",IF(AND($F70="نعم",$D70=""),"النوع ناقص","")))))))
A71: 3300 | B71: الأرباح المحتجزة | C71: Retained Earnings | D71: E | E71: 2 | F71: لا | G71: دائن | H71: 0 | I71: OPERATING | J71: لا | K71: لا | L71: نعم | M71: 3300 | N71: 3399 | P71: =IF($A71="","",IF($F71="نعم",$A71,$M71)) | Q71: =IF($A71="","",IF($F71="نعم",$A71,$N71)) | R71: =IF($A71="","",IF(AND($F71="نعم",$L71<>"لا"),1,0)) | S71: =IF($D71="","",IFERROR(INDEX(Lists!$AK$5:$AK$10,MATCH($D71,Lists!$AJ$5:$AJ$10,0)),"نوع غير معرف")) | T71: =IF($A71="","",IF(COUNTIF($A:$A,$A71)>1,"كود حساب مكرر",IF($B71="","اسم الحساب ناقص",IF(AND($F71="نعم",$G71=""),"الطبيعة ناقصة",IF(AND($F71<>"نعم",OR($M71="",$N71="")),"الحساب الرئيسي يحتاج نطاقًا (من/إلى)",IF(AND($H71=1,$F71<>"نعم"),"حساب نقدية يجب أن يكون قابلًا للترحيل",IF(AND($F71="نعم",$D71=""),"النوع ناقص","")))))))
A72: 3301 | B72: أرباح محتجزة (مرحّلة) | C72: Retained Earnings | D72: E | E72: 3 | F72: نعم | G72: دائن | H72: 0 | I72: OPERATING | J72: لا | K72: لا | L72: نعم | P72: =IF($A72="","",IF($F72="نعم",$A72,$M72)) | Q72: =IF($A72="","",IF($F72="نعم",$A72,$N72)) | R72: =IF($A72="","",IF(AND($F72="نعم",$L72<>"لا"),1,0)) | S72: =IF($D72="","",IFERROR(INDEX(Lists!$AK$5:$AK$10,MATCH($D72,Lists!$AJ$5:$AJ$10,0)),"نوع غير معرف")) | T72: =IF($A72="","",IF(COUNTIF($A:$A,$A72)>1,"كود حساب مكرر",IF($B72="","اسم الحساب ناقص",IF(AND($F72="نعم",$G72=""),"الطبيعة ناقصة",IF(AND($F72<>"نعم",OR($M72="",$N72="")),"الحساب الرئيسي يحتاج نطاقًا (من/إلى)",IF(AND($H72=1,$F72<>"نعم"),"حساب نقدية يجب أن يكون قابلًا للترحيل",IF(AND($F72="نعم",$D72=""),"النوع ناقص","")))))))
A73: 3400 | B73: المسحوبات والتوزيعات | C73: Drawings & Distributions | D73: E | E73: 2 | F73: لا | G73: مدين | H73: 0 | I73: OPERATING | J73: لا | K73: لا | L73: نعم | M73: 3400 | N73: 3499 | P73: =IF($A73="","",IF($F73="نعم",$A73,$M73)) | Q73: =IF($A73="","",IF($F73="نعم",$A73,$N73)) | R73: =IF($A73="","",IF(AND($F73="نعم",$L73<>"لا"),1,0)) | S73: =IF($D73="","",IFERROR(INDEX(Lists!$AK$5:$AK$10,MATCH($D73,Lists!$AJ$5:$AJ$10,0)),"نوع غير معرف")) | T73: =IF($A73="","",IF(COUNTIF($A:$A,$A73)>1,"كود حساب مكرر",IF($B73="","اسم الحساب ناقص",IF(AND($F73="نعم",$G73=""),"الطبيعة ناقصة",IF(AND($F73<>"نعم",OR($M73="",$N73="")),"الحساب الرئيسي يحتاج نطاقًا (من/إلى)",IF(AND($H73=1,$F73<>"نعم"),"حساب نقدية يجب أن يكون قابلًا للترحيل",IF(AND($F73="نعم",$D73=""),"النوع ناقص","")))))))
A74: 3401 | B74: مسحوبات المالك | C74: Owner Drawings | D74: E | E74: 3 | F74: نعم | G74: مدين | H74: 0 | I74: FINANCING | J74: لا | K74: لا | L74: نعم | P74: =IF($A74="","",IF($F74="نعم",$A74,$M74)) | Q74: =IF($A74="","",IF($F74="نعم",$A74,$N74)) | R74: =IF($A74="","",IF(AND($F74="نعم",$L74<>"لا"),1,0)) | S74: =IF($D74="","",IFERROR(INDEX(Lists!$AK$5:$AK$10,MATCH($D74,Lists!$AJ$5:$AJ$10,0)),"نوع غير معرف")) | T74: =IF($A74="","",IF(COUNTIF($A:$A,$A74)>1,"كود حساب مكرر",IF($B74="","اسم الحساب ناقص",IF(AND($F74="نعم",$G74=""),"الطبيعة ناقصة",IF(AND($F74<>"نعم",OR($M74="",$N74="")),"الحساب الرئيسي يحتاج نطاقًا (من/إلى)",IF(AND($H74=1,$F74<>"نعم"),"حساب نقدية يجب أن يكون قابلًا للترحيل",IF(AND($F74="نعم",$D74=""),"النوع ناقص","")))))))
A75: 3402 | B75: توزيعات أرباح | C75: Dividends | D75: E | E75: 3 | F75: نعم | G75: مدين | H75: 0 | I75: FINANCING | J75: لا | K75: لا | L75: نعم | P75: =IF($A75="","",IF($F75="نعم",$A75,$M75)) | Q75: =IF($A75="","",IF($F75="نعم",$A75,$N75)) | R75: =IF($A75="","",IF(AND($F75="نعم",$L75<>"لا"),1,0)) | S75: =IF($D75="","",IFERROR(INDEX(Lists!$AK$5:$AK$10,MATCH($D75,Lists!$AJ$5:$AJ$10,0)),"نوع غير معرف")) | T75: =IF($A75="","",IF(COUNTIF($A:$A,$A75)>1,"كود حساب مكرر",IF($B75="","اسم الحساب ناقص",IF(AND($F75="نعم",$G75=""),"الطبيعة ناقصة",IF(AND($F75<>"نعم",OR($M75="",$N75="")),"الحساب الرئيسي يحتاج نطاقًا (من/إلى)",IF(AND($H75=1,$F75<>"نعم"),"حساب نقدية يجب أن يكون قابلًا للترحيل",IF(AND($F75="نعم",$D75=""),"النوع ناقص","")))))))
A76: 3500 | B76: ملخص الدخل (حساب الإقفال) | C76: Income Summary | D76: E | E76: 2 | F76: لا | G76: دائن | H76: 0 | I76: OPERATING | J76: لا | K76: لا | L76: نعم | M76: 3500 | N76: 3599 | P76: =IF($A76="","",IF($F76="نعم",$A76,$M76)) | Q76: =IF($A76="","",IF($F76="نعم",$A76,$N76)) | R76: =IF($A76="","",IF(AND($F76="نعم",$L76<>"لا"),1,0)) | S76: =IF($D76="","",IFERROR(INDEX(Lists!$AK$5:$AK$10,MATCH($D76,Lists!$AJ$5:$AJ$10,0)),"نوع غير معرف")) | T76: =IF($A76="","",IF(COUNTIF($A:$A,$A76)>1,"كود حساب مكرر",IF($B76="","اسم الحساب ناقص",IF(AND($F76="نعم",$G76=""),"الطبيعة ناقصة",IF(AND($F76<>"نعم",OR($M76="",$N76="")),"الحساب الرئيسي يحتاج نطاقًا (من/إلى)",IF(AND($H76=1,$F76<>"نعم"),"حساب نقدية يجب أن يكون قابلًا للترحيل",IF(AND($F76="نعم",$D76=""),"النوع ناقص","")))))))
A77: 3501 | B77: ملخص الدخل | C77: Income Summary | D77: E | E77: 3 | F77: نعم | G77: دائن | H77: 0 | I77: OPERATING | J77: لا | K77: لا | L77: نعم | O77: يُستخدم فقط في قيد إقفال نهاية السنة | P77: =IF($A77="","",IF($F77="نعم",$A77,$M77)) | Q77: =IF($A77="","",IF($F77="نعم",$A77,$N77)) | R77: =IF($A77="","",IF(AND($F77="نعم",$L77<>"لا"),1,0)) | S77: =IF($D77="","",IFERROR(INDEX(Lists!$AK$5:$AK$10,MATCH($D77,Lists!$AJ$5:$AJ$10,0)),"نوع غير معرف")) | T77: =IF($A77="","",IF(COUNTIF($A:$A,$A77)>1,"كود حساب مكرر",IF($B77="","اسم الحساب ناقص",IF(AND($F77="نعم",$G77=""),"الطبيعة ناقصة",IF(AND($F77<>"نعم",OR($M77="",$N77="")),"الحساب الرئيسي يحتاج نطاقًا (من/إلى)",IF(AND($H77=1,$F77<>"نعم"),"حساب نقدية يجب أن يكون قابلًا للترحيل",IF(AND($F77="نعم",$D77=""),"النوع ناقص","")))))))
A78: 4000 | B78: الإيرادات | C78: Revenue | D78: R | E78: 1 | F78: لا | G78: دائن | H78: 0 | I78: OPERATING | J78: لا | K78: لا | L78: نعم | M78: 4000 | N78: 4999 | P78: =IF($A78="","",IF($F78="نعم",$A78,$M78)) | Q78: =IF($A78="","",IF($F78="نعم",$A78,$N78)) | R78: =IF($A78="","",IF(AND($F78="نعم",$L78<>"لا"),1,0)) | S78: =IF($D78="","",IFERROR(INDEX(Lists!$AK$5:$AK$10,MATCH($D78,Lists!$AJ$5:$AJ$10,0)),"نوع غير معرف")) | T78: =IF($A78="","",IF(COUNTIF($A:$A,$A78)>1,"كود حساب مكرر",IF($B78="","اسم الحساب ناقص",IF(AND($F78="نعم",$G78=""),"الطبيعة ناقصة",IF(AND($F78<>"نعم",OR($M78="",$N78="")),"الحساب الرئيسي يحتاج نطاقًا (من/إلى)",IF(AND($H78=1,$F78<>"نعم"),"حساب نقدية يجب أن يكون قابلًا للترحيل",IF(AND($F78="نعم",$D78=""),"النوع ناقص","")))))))
A79: 4100 | B79: المبيعات | C79: Sales | D79: R | E79: 2 | F79: لا | G79: دائن | H79: 0 | I79: OPERATING | J79: لا | K79: لا | L79: نعم | M79: 4100 | N79: 4199 | P79: =IF($A79="","",IF($F79="نعم",$A79,$M79)) | Q79: =IF($A79="","",IF($F79="نعم",$A79,$N79)) | R79: =IF($A79="","",IF(AND($F79="نعم",$L79<>"لا"),1,0)) | S79: =IF($D79="","",IFERROR(INDEX(Lists!$AK$5:$AK$10,MATCH($D79,Lists!$AJ$5:$AJ$10,0)),"نوع غير معرف")) | T79: =IF($A79="","",IF(COUNTIF($A:$A,$A79)>1,"كود حساب مكرر",IF($B79="","اسم الحساب ناقص",IF(AND($F79="نعم",$G79=""),"الطبيعة ناقصة",IF(AND($F79<>"نعم",OR($M79="",$N79="")),"الحساب الرئيسي يحتاج نطاقًا (من/إلى)",IF(AND($H79=1,$F79<>"نعم"),"حساب نقدية يجب أن يكون قابلًا للترحيل",IF(AND($F79="نعم",$D79=""),"النوع ناقص","")))))))
A80: 4101 | B80: مبيعات الفطير | C80: Sales - Fateer | D80: R | E80: 3 | F80: نعم | G80: دائن | H80: 0 | I80: OPERATING | J80: لا | K80: لا | L80: نعم | P80: =IF($A80="","",IF($F80="نعم",$A80,$M80)) | Q80: =IF($A80="","",IF($F80="نعم",$A80,$N80)) | R80: =IF($A80="","",IF(AND($F80="نعم",$L80<>"لا"),1,0)) | S80: =IF($D80="","",IFERROR(INDEX(Lists!$AK$5:$AK$10,MATCH($D80,Lists!$AJ$5:$AJ$10,0)),"نوع غير معرف")) | T80: =IF($A80="","",IF(COUNTIF($A:$A,$A80)>1,"كود حساب مكرر",IF($B80="","اسم الحساب ناقص",IF(AND($F80="نعم",$G80=""),"الطبيعة ناقصة",IF(AND($F80<>"نعم",OR($M80="",$N80="")),"الحساب الرئيسي يحتاج نطاقًا (من/إلى)",IF(AND($H80=1,$F80<>"نعم"),"حساب نقدية يجب أن يكون قابلًا للترحيل",IF(AND($F80="نعم",$D80=""),"النوع ناقص","")))))))
A81: 4102 | B81: مبيعات البيتزا | C81: Sales - Pizza | D81: R | E81: 3 | F81: نعم | G81: دائن | H81: 0 | I81: OPERATING | J81: لا | K81: لا | L81: نعم | P81: =IF($A81="","",IF($F81="نعم",$A81,$M81)) | Q81: =IF($A81="","",IF($F81="نعم",$A81,$N81)) | R81: =IF($A81="","",IF(AND($F81="نعم",$L81<>"لا"),1,0)) | S81: =IF($D81="","",IFERROR(INDEX(Lists!$AK$5:$AK$10,MATCH($D81,Lists!$AJ$5:$AJ$10,0)),"نوع غير معرف")) | T81: =IF($A81="","",IF(COUNTIF($A:$A,$A81)>1,"كود حساب مكرر",IF($B81="","اسم الحساب ناقص",IF(AND($F81="نعم",$G81=""),"الطبيعة ناقصة",IF(AND($F81<>"نعم",OR($M81="",$N81="")),"الحساب الرئيسي يحتاج نطاقًا (من/إلى)",IF(AND($H81=1,$F81<>"نعم"),"حساب نقدية يجب أن يكون قابلًا للترحيل",IF(AND($F81="نعم",$D81=""),"النوع ناقص","")))))))
A82: 4103 | B82: مبيعات المكرونات | C82: Sales - Pasta | D82: R | E82: 3 | F82: نعم | G82: دائن | H82: 0 | I82: OPERATING | J82: لا | K82: لا | L82: نعم | P82: =IF($A82="","",IF($F82="نعم",$A82,$M82)) | Q82: =IF($A82="","",IF($F82="نعم",$A82,$N82)) | R82: =IF($A82="","",IF(AND($F82="نعم",$L82<>"لا"),1,0)) | S82: =IF($D82="","",IFERROR(INDEX(Lists!$AK$5:$AK$10,MATCH($D82,Lists!$AJ$5:$AJ$10,0)),"نوع غير معرف")) | T82: =IF($A82="","",IF(COUNTIF($A:$A,$A82)>1,"كود حساب مكرر",IF($B82="","اسم الحساب ناقص",IF(AND($F82="نعم",$G82=""),"الطبيعة ناقصة",IF(AND($F82<>"نعم",OR($M82="",$N82="")),"الحساب الرئيسي يحتاج نطاقًا (من/إلى)",IF(AND($H82=1,$F82<>"نعم"),"حساب نقدية يجب أن يكون قابلًا للترحيل",IF(AND($F82="نعم",$D82=""),"النوع ناقص","")))))))
A83: 4104 | B83: مبيعات أخرى (مشروبات وإضافات) | C83: Sales - Other | D83: R | E83: 3 | F83: نعم | G83: دائن | H83: 0 | I83: OPERATING | J83: لا | K83: لا | L83: نعم | P83: =IF($A83="","",IF($F83="نعم",$A83,$M83)) | Q83: =IF($A83="","",IF($F83="نعم",$A83,$N83)) | R83: =IF($A83="","",IF(AND($F83="نعم",$L83<>"لا"),1,0)) | S83: =IF($D83="","",IFERROR(INDEX(Lists!$AK$5:$AK$10,MATCH($D83,Lists!$AJ$5:$AJ$10,0)),"نوع غير معرف")) | T83: =IF($A83="","",IF(COUNTIF($A:$A,$A83)>1,"كود حساب مكرر",IF($B83="","اسم الحساب ناقص",IF(AND($F83="نعم",$G83=""),"الطبيعة ناقصة",IF(AND($F83<>"نعم",OR($M83="",$N83="")),"الحساب الرئيسي يحتاج نطاقًا (من/إلى)",IF(AND($H83=1,$F83<>"نعم"),"حساب نقدية يجب أن يكون قابلًا للترحيل",IF(AND($F83="نعم",$D83=""),"النوع ناقص","")))))))
A84: 4200 | B84: إيرادات أخرى | C84: Other Income | D84: R | E84: 2 | F84: لا | G84: دائن | H84: 0 | I84: OPERATING | J84: لا | K84: لا | L84: نعم | M84: 4200 | N84: 4299 | P84: =IF($A84="","",IF($F84="نعم",$A84,$M84)) | Q84: =IF($A84="","",IF($F84="نعم",$A84,$N84)) | R84: =IF($A84="","",IF(AND($F84="نعم",$L84<>"لا"),1,0)) | S84: =IF($D84="","",IFERROR(INDEX(Lists!$AK$5:$AK$10,MATCH($D84,Lists!$AJ$5:$AJ$10,0)),"نوع غير معرف")) | T84: =IF($A84="","",IF(COUNTIF($A:$A,$A84)>1,"كود حساب مكرر",IF($B84="","اسم الحساب ناقص",IF(AND($F84="نعم",$G84=""),"الطبيعة ناقصة",IF(AND($F84<>"نعم",OR($M84="",$N84="")),"الحساب الرئيسي يحتاج نطاقًا (من/إلى)",IF(AND($H84=1,$F84<>"نعم"),"حساب نقدية يجب أن يكون قابلًا للترحيل",IF(AND($F84="نعم",$D84=""),"النوع ناقص","")))))))
A85: 4201 | B85: إيرادات متنوعة | C85: Miscellaneous Income | D85: R | E85: 3 | F85: نعم | G85: دائن | H85: 0 | I85: OPERATING | J85: لا | K85: لا | L85: نعم | P85: =IF($A85="","",IF($F85="نعم",$A85,$M85)) | Q85: =IF($A85="","",IF($F85="نعم",$A85,$N85)) | R85: =IF($A85="","",IF(AND($F85="نعم",$L85<>"لا"),1,0)) | S85: =IF($D85="","",IFERROR(INDEX(Lists!$AK$5:$AK$10,MATCH($D85,Lists!$AJ$5:$AJ$10,0)),"نوع غير معرف")) | T85: =IF($A85="","",IF(COUNTIF($A:$A,$A85)>1,"كود حساب مكرر",IF($B85="","اسم الحساب ناقص",IF(AND($F85="نعم",$G85=""),"الطبيعة ناقصة",IF(AND($F85<>"نعم",OR($M85="",$N85="")),"الحساب الرئيسي يحتاج نطاقًا (من/إلى)",IF(AND($H85=1,$F85<>"نعم"),"حساب نقدية يجب أن يكون قابلًا للترحيل",IF(AND($F85="نعم",$D85=""),"النوع ناقص","")))))))
A86: 4210 | B86: زيادة خزينة | C86: Cash Overage | D86: R | E86: 3 | F86: نعم | G86: دائن | H86: 0 | I86: OPERATING | J86: لا | K86: لا | L86: نعم | P86: =IF($A86="","",IF($F86="نعم",$A86,$M86)) | Q86: =IF($A86="","",IF($F86="نعم",$A86,$N86)) | R86: =IF($A86="","",IF(AND($F86="نعم",$L86<>"لا"),1,0)) | S86: =IF($D86="","",IFERROR(INDEX(Lists!$AK$5:$AK$10,MATCH($D86,Lists!$AJ$5:$AJ$10,0)),"نوع غير معرف")) | T86: =IF($A86="","",IF(COUNTIF($A:$A,$A86)>1,"كود حساب مكرر",IF($B86="","اسم الحساب ناقص",IF(AND($F86="نعم",$G86=""),"الطبيعة ناقصة",IF(AND($F86<>"نعم",OR($M86="",$N86="")),"الحساب الرئيسي يحتاج نطاقًا (من/إلى)",IF(AND($H86=1,$F86<>"نعم"),"حساب نقدية يجب أن يكون قابلًا للترحيل",IF(AND($F86="نعم",$D86=""),"النوع ناقص","")))))))
A87: 4900 | B87: خصومات ومرتجعات المبيعات (حسابات مقابلة) | C87: Sales Contra Accounts | D87: R | E87: 2 | F87: لا | G87: مدين | H87: 0 | I87: OPERATING | J87: لا | K87: لا | L87: نعم | M87: 4900 | N87: 4999 | P87: =IF($A87="","",IF($F87="نعم",$A87,$M87)) | Q87: =IF($A87="","",IF($F87="نعم",$A87,$N87)) | R87: =IF($A87="","",IF(AND($F87="نعم",$L87<>"لا"),1,0)) | S87: =IF($D87="","",IFERROR(INDEX(Lists!$AK$5:$AK$10,MATCH($D87,Lists!$AJ$5:$AJ$10,0)),"نوع غير معرف")) | T87: =IF($A87="","",IF(COUNTIF($A:$A,$A87)>1,"كود حساب مكرر",IF($B87="","اسم الحساب ناقص",IF(AND($F87="نعم",$G87=""),"الطبيعة ناقصة",IF(AND($F87<>"نعم",OR($M87="",$N87="")),"الحساب الرئيسي يحتاج نطاقًا (من/إلى)",IF(AND($H87=1,$F87<>"نعم"),"حساب نقدية يجب أن يكون قابلًا للترحيل",IF(AND($F87="نعم",$D87=""),"النوع ناقص","")))))))
A88: 4901 | B88: خصومات المبيعات والعروض | C88: Sales Discounts | D88: R | E88: 3 | F88: نعم | G88: مدين | H88: 0 | I88: OPERATING | J88: لا | K88: لا | L88: نعم | P88: =IF($A88="","",IF($F88="نعم",$A88,$M88)) | Q88: =IF($A88="","",IF($F88="نعم",$A88,$N88)) | R88: =IF($A88="","",IF(AND($F88="نعم",$L88<>"لا"),1,0)) | S88: =IF($D88="","",IFERROR(INDEX(Lists!$AK$5:$AK$10,MATCH($D88,Lists!$AJ$5:$AJ$10,0)),"نوع غير معرف")) | T88: =IF($A88="","",IF(COUNTIF($A:$A,$A88)>1,"كود حساب مكرر",IF($B88="","اسم الحساب ناقص",IF(AND($F88="نعم",$G88=""),"الطبيعة ناقصة",IF(AND($F88<>"نعم",OR($M88="",$N88="")),"الحساب الرئيسي يحتاج نطاقًا (من/إلى)",IF(AND($H88=1,$F88<>"نعم"),"حساب نقدية يجب أن يكون قابلًا للترحيل",IF(AND($F88="نعم",$D88=""),"النوع ناقص","")))))))
A89: 4902 | B89: مرتجعات وإلغاءات المبيعات | C89: Sales Returns & Cancellations | D89: R | E89: 3 | F89: نعم | G89: مدين | H89: 0 | I89: OPERATING | J89: لا | K89: لا | L89: نعم | P89: =IF($A89="","",IF($F89="نعم",$A89,$M89)) | Q89: =IF($A89="","",IF($F89="نعم",$A89,$N89)) | R89: =IF($A89="","",IF(AND($F89="نعم",$L89<>"لا"),1,0)) | S89: =IF($D89="","",IFERROR(INDEX(Lists!$AK$5:$AK$10,MATCH($D89,Lists!$AJ$5:$AJ$10,0)),"نوع غير معرف")) | T89: =IF($A89="","",IF(COUNTIF($A:$A,$A89)>1,"كود حساب مكرر",IF($B89="","اسم الحساب ناقص",IF(AND($F89="نعم",$G89=""),"الطبيعة ناقصة",IF(AND($F89<>"نعم",OR($M89="",$N89="")),"الحساب الرئيسي يحتاج نطاقًا (من/إلى)",IF(AND($H89=1,$F89<>"نعم"),"حساب نقدية يجب أن يكون قابلًا للترحيل",IF(AND($F89="نعم",$D89=""),"النوع ناقص","")))))))
A90: 5000 | B90: تكلفة المبيعات | C90: Cost of Sales | D90: C | E90: 1 | F90: لا | G90: مدين | H90: 0 | I90: OPERATING | J90: لا | K90: لا | L90: نعم | M90: 5000 | N90: 5999 | P90: =IF($A90="","",IF($F90="نعم",$A90,$M90)) | Q90: =IF($A90="","",IF($F90="نعم",$A90,$N90)) | R90: =IF($A90="","",IF(AND($F90="نعم",$L90<>"لا"),1,0)) | S90: =IF($D90="","",IFERROR(INDEX(Lists!$AK$5:$AK$10,MATCH($D90,Lists!$AJ$5:$AJ$10,0)),"نوع غير معرف")) | T90: =IF($A90="","",IF(COUNTIF($A:$A,$A90)>1,"كود حساب مكرر",IF($B90="","اسم الحساب ناقص",IF(AND($F90="نعم",$G90=""),"الطبيعة ناقصة",IF(AND($F90<>"نعم",OR($M90="",$N90="")),"الحساب الرئيسي يحتاج نطاقًا (من/إلى)",IF(AND($H90=1,$F90<>"نعم"),"حساب نقدية يجب أن يكون قابلًا للترحيل",IF(AND($F90="نعم",$D90=""),"النوع ناقص","")))))))
A91: 5100 | B91: تكلفة المواد | C91: Material Cost | D91: C | E91: 2 | F91: لا | G91: مدين | H91: 0 | I91: OPERATING | J91: لا | K91: لا | L91: نعم | M91: 5100 | N91: 5199 | P91: =IF($A91="","",IF($F91="نعم",$A91,$M91)) | Q91: =IF($A91="","",IF($F91="نعم",$A91,$N91)) | R91: =IF($A91="","",IF(AND($F91="نعم",$L91<>"لا"),1,0)) | S91: =IF($D91="","",IFERROR(INDEX(Lists!$AK$5:$AK$10,MATCH($D91,Lists!$AJ$5:$AJ$10,0)),"نوع غير معرف")) | T91: =IF($A91="","",IF(COUNTIF($A:$A,$A91)>1,"كود حساب مكرر",IF($B91="","اسم الحساب ناقص",IF(AND($F91="نعم",$G91=""),"الطبيعة ناقصة",IF(AND($F91<>"نعم",OR($M91="",$N91="")),"الحساب الرئيسي يحتاج نطاقًا (من/إلى)",IF(AND($H91=1,$F91<>"نعم"),"حساب نقدية يجب أن يكون قابلًا للترحيل",IF(AND($F91="نعم",$D91=""),"النوع ناقص","")))))))
A92: 5101 | B92: تكلفة المواد المباشرة المستهلكة | C92: Direct Materials Consumed | D92: C | E92: 3 | F92: نعم | G92: مدين | H92: 0 | I92: OPERATING | J92: لا | K92: لا | L92: نعم | P92: =IF($A92="","",IF($F92="نعم",$A92,$M92)) | Q92: =IF($A92="","",IF($F92="نعم",$A92,$N92)) | R92: =IF($A92="","",IF(AND($F92="نعم",$L92<>"لا"),1,0)) | S92: =IF($D92="","",IFERROR(INDEX(Lists!$AK$5:$AK$10,MATCH($D92,Lists!$AJ$5:$AJ$10,0)),"نوع غير معرف")) | T92: =IF($A92="","",IF(COUNTIF($A:$A,$A92)>1,"كود حساب مكرر",IF($B92="","اسم الحساب ناقص",IF(AND($F92="نعم",$G92=""),"الطبيعة ناقصة",IF(AND($F92<>"نعم",OR($M92="",$N92="")),"الحساب الرئيسي يحتاج نطاقًا (من/إلى)",IF(AND($H92=1,$F92<>"نعم"),"حساب نقدية يجب أن يكون قابلًا للترحيل",IF(AND($F92="نعم",$D92=""),"النوع ناقص","")))))))
A93: 5102 | B93: تكلفة المنتجات المحولة والمباعة | C93: Transferred Products Sold | D93: C | E93: 3 | F93: نعم | G93: مدين | H93: 0 | I93: OPERATING | J93: لا | K93: لا | L93: نعم | P93: =IF($A93="","",IF($F93="نعم",$A93,$M93)) | Q93: =IF($A93="","",IF($F93="نعم",$A93,$N93)) | R93: =IF($A93="","",IF(AND($F93="نعم",$L93<>"لا"),1,0)) | S93: =IF($D93="","",IFERROR(INDEX(Lists!$AK$5:$AK$10,MATCH($D93,Lists!$AJ$5:$AJ$10,0)),"نوع غير معرف")) | T93: =IF($A93="","",IF(COUNTIF($A:$A,$A93)>1,"كود حساب مكرر",IF($B93="","اسم الحساب ناقص",IF(AND($F93="نعم",$G93=""),"الطبيعة ناقصة",IF(AND($F93<>"نعم",OR($M93="",$N93="")),"الحساب الرئيسي يحتاج نطاقًا (من/إلى)",IF(AND($H93=1,$F93<>"نعم"),"حساب نقدية يجب أن يكون قابلًا للترحيل",IF(AND($F93="نعم",$D93=""),"النوع ناقص","")))))))
A94: 5103 | B94: تكلفة العبوات والتغليف | C94: Packaging Cost | D94: C | E94: 3 | F94: نعم | G94: مدين | H94: 0 | I94: OPERATING | J94: لا | K94: لا | L94: نعم | P94: =IF($A94="","",IF($F94="نعم",$A94,$M94)) | Q94: =IF($A94="","",IF($F94="نعم",$A94,$N94)) | R94: =IF($A94="","",IF(AND($F94="نعم",$L94<>"لا"),1,0)) | S94: =IF($D94="","",IFERROR(INDEX(Lists!$AK$5:$AK$10,MATCH($D94,Lists!$AJ$5:$AJ$10,0)),"نوع غير معرف")) | T94: =IF($A94="","",IF(COUNTIF($A:$A,$A94)>1,"كود حساب مكرر",IF($B94="","اسم الحساب ناقص",IF(AND($F94="نعم",$G94=""),"الطبيعة ناقصة",IF(AND($F94<>"نعم",OR($M94="",$N94="")),"الحساب الرئيسي يحتاج نطاقًا (من/إلى)",IF(AND($H94=1,$F94<>"نعم"),"حساب نقدية يجب أن يكون قابلًا للترحيل",IF(AND($F94="نعم",$D94=""),"النوع ناقص","")))))))
A95: 5200 | B95: الهالك | C95: Waste | D95: C | E95: 2 | F95: لا | G95: مدين | H95: 0 | I95: OPERATING | J95: لا | K95: لا | L95: نعم | M95: 5200 | N95: 5299 | P95: =IF($A95="","",IF($F95="نعم",$A95,$M95)) | Q95: =IF($A95="","",IF($F95="نعم",$A95,$N95)) | R95: =IF($A95="","",IF(AND($F95="نعم",$L95<>"لا"),1,0)) | S95: =IF($D95="","",IFERROR(INDEX(Lists!$AK$5:$AK$10,MATCH($D95,Lists!$AJ$5:$AJ$10,0)),"نوع غير معرف")) | T95: =IF($A95="","",IF(COUNTIF($A:$A,$A95)>1,"كود حساب مكرر",IF($B95="","اسم الحساب ناقص",IF(AND($F95="نعم",$G95=""),"الطبيعة ناقصة",IF(AND($F95<>"نعم",OR($M95="",$N95="")),"الحساب الرئيسي يحتاج نطاقًا (من/إلى)",IF(AND($H95=1,$F95<>"نعم"),"حساب نقدية يجب أن يكون قابلًا للترحيل",IF(AND($F95="نعم",$D95=""),"النوع ناقص","")))))))
A96: 5201 | B96: هالك طبيعي معتمد | C96: Normal Waste (approved) | D96: C | E96: 3 | F96: نعم | G96: مدين | H96: 0 | I96: OPERATING | J96: لا | K96: لا | L96: نعم | P96: =IF($A96="","",IF($F96="نعم",$A96,$M96)) | Q96: =IF($A96="","",IF($F96="نعم",$A96,$N96)) | R96: =IF($A96="","",IF(AND($F96="نعم",$L96<>"لا"),1,0)) | S96: =IF($D96="","",IFERROR(INDEX(Lists!$AK$5:$AK$10,MATCH($D96,Lists!$AJ$5:$AJ$10,0)),"نوع غير معرف")) | T96: =IF($A96="","",IF(COUNTIF($A:$A,$A96)>1,"كود حساب مكرر",IF($B96="","اسم الحساب ناقص",IF(AND($F96="نعم",$G96=""),"الطبيعة ناقصة",IF(AND($F96<>"نعم",OR($M96="",$N96="")),"الحساب الرئيسي يحتاج نطاقًا (من/إلى)",IF(AND($H96=1,$F96<>"نعم"),"حساب نقدية يجب أن يكون قابلًا للترحيل",IF(AND($F96="نعم",$D96=""),"النوع ناقص","")))))))
A97: 5202 | B97: هالك غير طبيعي | C97: Abnormal Waste | D97: C | E97: 3 | F97: نعم | G97: مدين | H97: 0 | I97: OPERATING | J97: لا | K97: لا | L97: نعم | P97: =IF($A97="","",IF($F97="نعم",$A97,$M97)) | Q97: =IF($A97="","",IF($F97="نعم",$A97,$N97)) | R97: =IF($A97="","",IF(AND($F97="نعم",$L97<>"لا"),1,0)) | S97: =IF($D97="","",IFERROR(INDEX(Lists!$AK$5:$AK$10,MATCH($D97,Lists!$AJ$5:$AJ$10,0)),"نوع غير معرف")) | T97: =IF($A97="","",IF(COUNTIF($A:$A,$A97)>1,"كود حساب مكرر",IF($B97="","اسم الحساب ناقص",IF(AND($F97="نعم",$G97=""),"الطبيعة ناقصة",IF(AND($F97<>"نعم",OR($M97="",$N97="")),"الحساب الرئيسي يحتاج نطاقًا (من/إلى)",IF(AND($H97=1,$F97<>"نعم"),"حساب نقدية يجب أن يكون قابلًا للترحيل",IF(AND($F97="نعم",$D97=""),"النوع ناقص","")))))))
A98: 5300 | B98: الضيافة والمجانيات | C98: Complimentary | D98: C | E98: 2 | F98: لا | G98: مدين | H98: 0 | I98: OPERATING | J98: لا | K98: لا | L98: نعم | M98: 5300 | N98: 5399 | P98: =IF($A98="","",IF($F98="نعم",$A98,$M98)) | Q98: =IF($A98="","",IF($F98="نعم",$A98,$N98)) | R98: =IF($A98="","",IF(AND($F98="نعم",$L98<>"لا"),1,0)) | S98: =IF($D98="","",IFERROR(INDEX(Lists!$AK$5:$AK$10,MATCH($D98,Lists!$AJ$5:$AJ$10,0)),"نوع غير معرف")) | T98: =IF($A98="","",IF(COUNTIF($A:$A,$A98)>1,"كود حساب مكرر",IF($B98="","اسم الحساب ناقص",IF(AND($F98="نعم",$G98=""),"الطبيعة ناقصة",IF(AND($F98<>"نعم",OR($M98="",$N98="")),"الحساب الرئيسي يحتاج نطاقًا (من/إلى)",IF(AND($H98=1,$F98<>"نعم"),"حساب نقدية يجب أن يكون قابلًا للترحيل",IF(AND($F98="نعم",$D98=""),"النوع ناقص","")))))))
A99: 5301 | B99: تكلفة الضيافة والطلبات المجانية | C99: Complimentary Cost | D99: C | E99: 3 | F99: نعم | G99: مدين | H99: 0 | I99: OPERATING | J99: لا | K99: لا | L99: نعم | P99: =IF($A99="","",IF($F99="نعم",$A99,$M99)) | Q99: =IF($A99="","",IF($F99="نعم",$A99,$N99)) | R99: =IF($A99="","",IF(AND($F99="نعم",$L99<>"لا"),1,0)) | S99: =IF($D99="","",IFERROR(INDEX(Lists!$AK$5:$AK$10,MATCH($D99,Lists!$AJ$5:$AJ$10,0)),"نوع غير معرف")) | T99: =IF($A99="","",IF(COUNTIF($A:$A,$A99)>1,"كود حساب مكرر",IF($B99="","اسم الحساب ناقص",IF(AND($F99="نعم",$G99=""),"الطبيعة ناقصة",IF(AND($F99<>"نعم",OR($M99="",$N99="")),"الحساب الرئيسي يحتاج نطاقًا (من/إلى)",IF(AND($H99=1,$F99<>"نعم"),"حساب نقدية يجب أن يكون قابلًا للترحيل",IF(AND($F99="نعم",$D99=""),"النوع ناقص","")))))))
A100: 5400 | B100: فروق المخزون والتكلفة | C100: Inventory & Cost Variances | D100: C | E100: 2 | F100: لا | G100: مدين | H100: 0 | I100: OPERATING | J100: لا | K100: لا | L100: نعم | M100: 5400 | N100: 5499 | P100: =IF($A100="","",IF($F100="نعم",$A100,$M100)) | Q100: =IF($A100="","",IF($F100="نعم",$A100,$N100)) | R100: =IF($A100="","",IF(AND($F100="نعم",$L100<>"لا"),1,0)) | S100: =IF($D100="","",IFERROR(INDEX(Lists!$AK$5:$AK$10,MATCH($D100,Lists!$AJ$5:$AJ$10,0)),"نوع غير معرف")) | T100: =IF($A100="","",IF(COUNTIF($A:$A,$A100)>1,"كود حساب مكرر",IF($B100="","اسم الحساب ناقص",IF(AND($F100="نعم",$G100=""),"الطبيعة ناقصة",IF(AND($F100<>"نعم",OR($M100="",$N100="")),"الحساب الرئيسي يحتاج نطاقًا (من/إلى)",IF(AND($H100=1,$F100<>"نعم"),"حساب نقدية يجب أن يكون قابلًا للترحيل",IF(AND($F100="نعم",$D100=""),"النوع ناقص","")))))))
...

Sheet Locations
A1: الفروع والمواقع (Branches & Locations)
A2: كل فرع/مخزن/مطبخ له كود ثابت. لإضافة فرع جديد: أضف صفًا هنا، ثم خزينة له في Treasuries وحسابًا في COA - وتظهر بياناته آليًا في التقارير.
A3: خلايا الإدخال | B3: معادلات (لا تعدّل)
A4: كود الموقع Code | B4: اسم الموقع | C4: النوع | D4: Name (EN) | E4: المسؤول | F4: نشط | G4: خزينة النقدية الافتراضية | H4: تاريخ الافتتاح | I4: ملاحظات | J4: ترتيب فرع البيع | K4: فحص
A5: BR01 | B5: فرع ستاموني 1 (تجريبي) | C5: فرع | D5: Branch 1 | E5: مدير الفرع 1 | F5: نعم | G5: CSH-BR01 | H5: 46023 | J5: =IF(AND($C5="فرع",$F5<>"لا",$A5<>""),MAX($J$4:$J4)+1,"") | K5: =IF($A5="","",IF(COUNTIF($A:$A,$A5)>1,"كود موقع مكرر",IF($B5="","اسم الموقع ناقص",IF($C5="","نوع الموقع ناقص",IF(AND($G5<>"",COUNTIF(Treasuries!$A:$A,$G5)=0),"الخزينة الافتراضية غير معرفة",IF(AND($C5="فرع",$G5=""),"الفرع يحتاج خزينة افتراضية",""))))))
A6: BR02 | B6: فرع ستاموني 2 (تجريبي) | C6: فرع | D6: Branch 2 | E6: مدير الفرع 2 | F6: نعم | G6: CSH-BR02 | H6: 46023 | J6: =IF(AND($C6="فرع",$F6<>"لا",$A6<>""),MAX($J$4:$J5)+1,"") | K6: =IF($A6="","",IF(COUNTIF($A:$A,$A6)>1,"كود موقع مكرر",IF($B6="","اسم الموقع ناقص",IF($C6="","نوع الموقع ناقص",IF(AND($G6<>"",COUNTIF(Treasuries!$A:$A,$G6)=0),"الخزينة الافتراضية غير معرفة",IF(AND($C6="فرع",$G6=""),"الفرع يحتاج خزينة افتراضية",""))))))
A7: BR03 | B7: فرع ستاموني 3 (تجريبي) | C7: فرع | D7: Branch 3 | E7: مدير الفرع 3 | F7: نعم | G7: CSH-BR03 | H7: 46023 | J7: =IF(AND($C7="فرع",$F7<>"لا",$A7<>""),MAX($J$4:$J6)+1,"") | K7: =IF($A7="","",IF(COUNTIF($A:$A,$A7)>1,"كود موقع مكرر",IF($B7="","اسم الموقع ناقص",IF($C7="","نوع الموقع ناقص",IF(AND($G7<>"",COUNTIF(Treasuries!$A:$A,$G7)=0),"الخزينة الافتراضية غير معرفة",IF(AND($C7="فرع",$G7=""),"الفرع يحتاج خزينة افتراضية",""))))))
A8: WH01 | B8: المخزن الرئيسي | C8: مخزن رئيسي | D8: Main Warehouse | E8: أمين المخزن | F8: نعم | H8: 46023 | J8: =IF(AND($C8="فرع",$F8<>"لا",$A8<>""),MAX($J$4:$J7)+1,"") | K8: =IF($A8="","",IF(COUNTIF($A:$A,$A8)>1,"كود موقع مكرر",IF($B8="","اسم الموقع ناقص",IF($C8="","نوع الموقع ناقص",IF(AND($G8<>"",COUNTIF(Treasuries!$A:$A,$G8)=0),"الخزينة الافتراضية غير معرفة",IF(AND($C8="فرع",$G8=""),"الفرع يحتاج خزينة افتراضية",""))))))
A9: CK01 | B9: السنتر كيتشن (المطبخ المركزي) | C9: سنتر كيتشن | D9: Central Kitchen | E9: مدير الإنتاج | F9: نعم | H9: 46023 | J9: =IF(AND($C9="فرع",$F9<>"لا",$A9<>""),MAX($J$4:$J8)+1,"") | K9: =IF($A9="","",IF(COUNTIF($A:$A,$A9)>1,"كود موقع مكرر",IF($B9="","اسم الموقع ناقص",IF($C9="","نوع الموقع ناقص",IF(AND($G9<>"",COUNTIF(Treasuries!$A:$A,$G9)=0),"الخزينة الافتراضية غير معرفة",IF(AND($C9="فرع",$G9=""),"الفرع يحتاج خزينة افتراضية",""))))))
A10: HQ01 | B10: الإدارة الرئيسية | C10: إدارة | D10: Head Office | E10: المدير المالي | F10: نعم | G10: CSH-HQ01 | H10: 46023 | J10: =IF(AND($C10="فرع",$F10<>"لا",$A10<>""),MAX($J$4:$J9)+1,"") | K10: =IF($A10="","",IF(COUNTIF($A:$A,$A10)>1,"كود موقع مكرر",IF($B10="","اسم الموقع ناقص",IF($C10="","نوع الموقع ناقص",IF(AND($G10<>"",COUNTIF(Treasuries!$A:$A,$G10)=0),"الخزينة الافتراضية غير معرفة",IF(AND($C10="فرع",$G10=""),"الفرع يحتاج خزينة افتراضية",""))))))
J11: =IF(AND($C11="فرع",$F11<>"لا",$A11<>""),MAX($J$4:$J10)+1,"") | K11: =IF($A11="","",IF(COUNTIF($A:$A,$A11)>1,"كود موقع مكرر",IF($B11="","اسم الموقع ناقص",IF($C11="","نوع الموقع ناقص",IF(AND($G11<>"",COUNTIF(Treasuries!$A:$A,$G11)=0),"الخزينة الافتراضية غير معرفة",IF(AND($C11="فرع",$G11=""),"الفرع يحتاج خزينة افتراضية",""))))))
J12: =IF(AND($C12="فرع",$F12<>"لا",$A12<>""),MAX($J$4:$J11)+1,"") | K12: =IF($A12="","",IF(COUNTIF($A:$A,$A12)>1,"كود موقع مكرر",IF($B12="","اسم الموقع ناقص",IF($C12="","نوع الموقع ناقص",IF(AND($G12<>"",COUNTIF(Treasuries!$A:$A,$G12)=0),"الخزينة الافتراضية غير معرفة",IF(AND($C12="فرع",$G12=""),"الفرع يحتاج خزينة افتراضية",""))))))
J13: =IF(AND($C13="فرع",$F13<>"لا",$A13<>""),MAX($J$4:$J12)+1,"") | K13: =IF($A13="","",IF(COUNTIF($A:$A,$A13)>1,"كود موقع مكرر",IF($B13="","اسم الموقع ناقص",IF($C13="","نوع الموقع ناقص",IF(AND($G13<>"",COUNTIF(Treasuries!$A:$A,$G13)=0),"الخزينة الافتراضية غير معرفة",IF(AND($C13="فرع",$G13=""),"الفرع يحتاج خزينة افتراضية",""))))))
J14: =IF(AND($C14="فرع",$F14<>"لا",$A14<>""),MAX($J$4:$J13)+1,"") | K14: =IF($A14="","",IF(COUNTIF($A:$A,$A14)>1,"كود موقع مكرر",IF($B14="","اسم الموقع ناقص",IF($C14="","نوع الموقع ناقص",IF(AND($G14<>"",COUNTIF(Treasuries!$A:$A,$G14)=0),"الخزينة الافتراضية غير معرفة",IF(AND($C14="فرع",$G14=""),"الفرع يحتاج خزينة افتراضية",""))))))
J15: =IF(AND($C15="فرع",$F15<>"لا",$A15<>""),MAX($J$4:$J14)+1,"") | K15: =IF($A15="","",IF(COUNTIF($A:$A,$A15)>1,"كود موقع مكرر",IF($B15="","اسم الموقع ناقص",IF($C15="","نوع الموقع ناقص",IF(AND($G15<>"",COUNTIF(Treasuries!$A:$A,$G15)=0),"الخزينة الافتراضية غير معرفة",IF(AND($C15="فرع",$G15=""),"الفرع يحتاج خزينة افتراضية",""))))))
J16: =IF(AND($C16="فرع",$F16<>"لا",$A16<>""),MAX($J$4:$J15)+1,"") | K16: =IF($A16="","",IF(COUNTIF($A:$A,$A16)>1,"كود موقع مكرر",IF($B16="","اسم الموقع ناقص",IF($C16="","نوع الموقع ناقص",IF(AND($G16<>"",COUNTIF(Treasuries!$A:$A,$G16)=0),"الخزينة الافتراضية غير معرفة",IF(AND($C16="فرع",$G16=""),"الفرع يحتاج خزينة افتراضية",""))))))
J17: =IF(AND($C17="فرع",$F17<>"لا",$A17<>""),MAX($J$4:$J16)+1,"") | K17: =IF($A17="","",IF(COUNTIF($A:$A,$A17)>1,"كود موقع مكرر",IF($B17="","اسم الموقع ناقص",IF($C17="","نوع الموقع ناقص",IF(AND($G17<>"",COUNTIF(Treasuries!$A:$A,$G17)=0),"الخزينة الافتراضية غير معرفة",IF(AND($C17="فرع",$G17=""),"الفرع يحتاج خزينة افتراضية",""))))))
J18: =IF(AND($C18="فرع",$F18<>"لا",$A18<>""),MAX($J$4:$J17)+1,"") | K18: =IF($A18="","",IF(COUNTIF($A:$A,$A18)>1,"كود موقع مكرر",IF($B18="","اسم الموقع ناقص",IF($C18="","نوع الموقع ناقص",IF(AND($G18<>"",COUNTIF(Treasuries!$A:$A,$G18)=0),"الخزينة الافتراضية غير معرفة",IF(AND($C18="فرع",$G18=""),"الفرع يحتاج خزينة افتراضية",""))))))
J19: =IF(AND($C19="فرع",$F19<>"لا",$A19<>""),MAX($J$4:$J18)+1,"") | K19: =IF($A19="","",IF(COUNTIF($A:$A,$A19)>1,"كود موقع مكرر",IF($B19="","اسم الموقع ناقص",IF($C19="","نوع الموقع ناقص",IF(AND($G19<>"",COUNTIF(Treasuries!$A:$A,$G19)=0),"الخزينة الافتراضية غير معرفة",IF(AND($C19="فرع",$G19=""),"الفرع يحتاج خزينة افتراضية",""))))))
J20: =IF(AND($C20="فرع",$F20<>"لا",$A20<>""),MAX($J$4:$J19)+1,"") | K20: =IF($A20="","",IF(COUNTIF($A:$A,$A20)>1,"كود موقع مكرر",IF($B20="","اسم الموقع ناقص",IF($C20="","نوع الموقع ناقص",IF(AND($G20<>"",COUNTIF(Treasuries!$A:$A,$G20)=0),"الخزينة الافتراضية غير معرفة",IF(AND($C20="فرع",$G20=""),"الفرع يحتاج خزينة افتراضية",""))))))
J21: =IF(AND($C21="فرع",$F21<>"لا",$A21<>""),MAX($J$4:$J20)+1,"") | K21: =IF($A21="","",IF(COUNTIF($A:$A,$A21)>1,"كود موقع مكرر",IF($B21="","اسم الموقع ناقص",IF($C21="","نوع الموقع ناقص",IF(AND($G21<>"",COUNTIF(Treasuries!$A:$A,$G21)=0),"الخزينة الافتراضية غير معرفة",IF(AND($C21="فرع",$G21=""),"الفرع يحتاج خزينة افتراضية",""))))))
J22: =IF(AND($C22="فرع",$F22<>"لا",$A22<>""),MAX($J$4:$J21)+1,"") | K22: =IF($A22="","",IF(COUNTIF($A:$A,$A22)>1,"كود موقع مكرر",IF($B22="","اسم الموقع ناقص",IF($C22="","نوع الموقع ناقص",IF(AND($G22<>"",COUNTIF(Treasuries!$A:$A,$G22)=0),"الخزينة الافتراضية غير معرفة",IF(AND($C22="فرع",$G22=""),"الفرع يحتاج خزينة افتراضية",""))))))
... J34: =IF(AND($C34="فرع",$F34<>"لا",$A34<>""),MAX($J$4:$J33)+1,"") | K34: =IF($A34="","",IF(COUNTIF($A:$A,$A34)>1,"كود موقع مكرر",IF($B34="","اسم الموقع ناقص",IF($C34="","نوع الموقع ناقص",IF(AND($G34<>"",COUNTIF(Treasuries!$A:$A,$G34)=0),"الخزينة الافتراضية غير معرفة",IF(AND($C34="فرع",$G34=""),"الفرع يحتاج خزينة افتراضية",""))))))

Sheet Treasuries
A1: الخزائن والبنوك (Treasuries & Banks)
A2: كل خزينة/بنك مرتبط بحساب مستقل في دليل الحسابات (حساب واحد لكل خزينة). الأرصدة الافتتاحية تُسجَّل بقيد افتتاحي في Manual_JE وليس هنا.
A3: خلايا الإدخال | B3: معادلات (لا تعدّل)
A4: كود الخزينة/البنك | B4: الاسم | C4: النوع | D4: الموقع | E4: حساب الأستاذ | F4: أمين الخزينة/المسؤول | G4: نشط | H4: ملاحظات | I4: اسم الحساب | J4: فحص
A5: CSH-BR01 | B5: خزينة الفرع BR01 | C5: خزينة | D5: BR01 | E5: 1101 | F5: أمين صندوق الفرع 1 | G5: نعم | I5: =IF($E5="","",IFERROR(INDEX(COA!$B:$B,MATCH($E5,COA!$A:$A,0)),"حساب غير موجود")) | J5: =IF($A5="","",IF(COUNTIF($A:$A,$A5)>1,"كود مكرر",IF(COUNTIF($E:$E,$E5)>1,"حساب الأستاذ مستخدم لخزينة أخرى",IF(COUNTIFS(COA!$A:$A,$E5,COA!$R:$R,1,COA!$H:$H,1)<>1,"الحساب غير موجود أو غير نقدي أو غير قابل للترحيل",IF(COUNTIF(Locations!$A:$A,$D5)=0,"الموقع غير معرف","")))))
A6: CSH-BR02 | B6: خزينة الفرع BR02 | C6: خزينة | D6: BR02 | E6: 1102 | F6: أمين صندوق الفرع 2 | G6: نعم | I6: =IF($E6="","",IFERROR(INDEX(COA!$B:$B,MATCH($E6,COA!$A:$A,0)),"حساب غير موجود")) | J6: =IF($A6="","",IF(COUNTIF($A:$A,$A6)>1,"كود مكرر",IF(COUNTIF($E:$E,$E6)>1,"حساب الأستاذ مستخدم لخزينة أخرى",IF(COUNTIFS(COA!$A:$A,$E6,COA!$R:$R,1,COA!$H:$H,1)<>1,"الحساب غير موجود أو غير نقدي أو غير قابل للترحيل",IF(COUNTIF(Locations!$A:$A,$D6)=0,"الموقع غير معرف","")))))
A7: CSH-BR03 | B7: خزينة الفرع BR03 | C7: خزينة | D7: BR03 | E7: 1103 | F7: أمين صندوق الفرع 3 | G7: نعم | I7: =IF($E7="","",IFERROR(INDEX(COA!$B:$B,MATCH($E7,COA!$A:$A,0)),"حساب غير موجود")) | J7: =IF($A7="","",IF(COUNTIF($A:$A,$A7)>1,"كود مكرر",IF(COUNTIF($E:$E,$E7)>1,"حساب الأستاذ مستخدم لخزينة أخرى",IF(COUNTIFS(COA!$A:$A,$E7,COA!$R:$R,1,COA!$H:$H,1)<>1,"الحساب غير موجود أو غير نقدي أو غير قابل للترحيل",IF(COUNTIF(Locations!$A:$A,$D7)=0,"الموقع غير معرف","")))))
A8: CSH-HQ01 | B8: خزينة الإدارة الرئيسية | C8: خزينة | D8: HQ01 | E8: 1104 | F8: أمين خزينة الإدارة | G8: نعم | I8: =IF($E8="","",IFERROR(INDEX(COA!$B:$B,MATCH($E8,COA!$A:$A,0)),"حساب غير موجود")) | J8: =IF($A8="","",IF(COUNTIF($A:$A,$A8)>1,"كود مكرر",IF(COUNTIF($E:$E,$E8)>1,"حساب الأستاذ مستخدم لخزينة أخرى",IF(COUNTIFS(COA!$A:$A,$E8,COA!$R:$R,1,COA!$H:$H,1)<>1,"الحساب غير موجود أو غير نقدي أو غير قابل للترحيل",IF(COUNTIF(Locations!$A:$A,$D8)=0,"الموقع غير معرف","")))))
A9: PTY-HQ01 | B9: عهدة المصروفات النثرية | C9: عهدة نثرية | D9: HQ01 | E9: 1105 | F9: أمين العهدة | G9: نعم | I9: =IF($E9="","",IFERROR(INDEX(COA!$B:$B,MATCH($E9,COA!$A:$A,0)),"حساب غير موجود")) | J9: =IF($A9="","",IF(COUNTIF($A:$A,$A9)>1,"كود مكرر",IF(COUNTIF($E:$E,$E9)>1,"حساب الأستاذ مستخدم لخزينة أخرى",IF(COUNTIFS(COA!$A:$A,$E9,COA!$R:$R,1,COA!$H:$H,1)<>1,"الحساب غير موجود أو غير نقدي أو غير قابل للترحيل",IF(COUNTIF(Locations!$A:$A,$D9)=0,"الموقع غير معرف","")))))
A10: BNK-01 | B10: البنك الأول - جاري (تجريبي) | C10: بنك | D10: HQ01 | E10: 1201 | F10: المدير المالي | G10: نعم | I10: =IF($E10="","",IFERROR(INDEX(COA!$B:$B,MATCH($E10,COA!$A:$A,0)),"حساب غير موجود")) | J10: =IF($A10="","",IF(COUNTIF($A:$A,$A10)>1,"كود مكرر",IF(COUNTIF($E:$E,$E10)>1,"حساب الأستاذ مستخدم لخزينة أخرى",IF(COUNTIFS(COA!$A:$A,$E10,COA!$R:$R,1,COA!$H:$H,1)<>1,"الحساب غير موجود أو غير نقدي أو غير قابل للترحيل",IF(COUNTIF(Locations!$A:$A,$D10)=0,"الموقع غير معرف","")))))
A11: BNK-02 | B11: البنك الثاني - جاري (تجريبي) | C11: بنك | D11: HQ01 | E11: 1202 | F11: المدير المالي | G11: نعم | I11: =IF($E11="","",IFERROR(INDEX(COA!$B:$B,MATCH($E11,COA!$A:$A,0)),"حساب غير موجود")) | J11: =IF($A11="","",IF(COUNTIF($A:$A,$A11)>1,"كود مكرر",IF(COUNTIF($E:$E,$E11)>1,"حساب الأستاذ مستخدم لخزينة أخرى",IF(COUNTIFS(COA!$A:$A,$E11,COA!$R:$R,1,COA!$H:$H,1)<>1,"الحساب غير موجود أو غير نقدي أو غير قابل للترحيل",IF(COUNTIF(Locations!$A:$A,$D11)=0,"الموقع غير معرف","")))))
A12: WLT-01 | B12: محفظة / تحويلات إلكترونية | C12: بنك | D12: HQ01 | E12: 1203 | F12: المدير المالي | G12: نعم | I12: =IF($E12="","",IFERROR(INDEX(COA!$B:$B,MATCH($E12,COA!$A:$A,0)),"حساب غير موجود")) | J12: =IF($A12="","",IF(COUNTIF($A:$A,$A12)>1,"كود مكرر",IF(COUNTIF($E:$E,$E12)>1,"حساب الأستاذ مستخدم لخزينة أخرى",IF(COUNTIFS(COA!$A:$A,$E12,COA!$R:$R,1,COA!$H:$H,1)<>1,"الحساب غير موجود أو غير نقدي أو غير قابل للترحيل",IF(COUNTIF(Locations!$A:$A,$D12)=0,"الموقع غير معرف","")))))
I13: =IF($E13="","",IFERROR(INDEX(COA!$B:$B,MATCH($E13,COA!$A:$A,0)),"حساب غير موجود")) | J13: =IF($A13="","",IF(COUNTIF($A:$A,$A13)>1,"كود مكرر",IF(COUNTIF($E:$E,$E13)>1,"حساب الأستاذ مستخدم لخزينة أخرى",IF(COUNTIFS(COA!$A:$A,$E13,COA!$R:$R,1,COA!$H:$H,1)<>1,"الحساب غير موجود أو غير نقدي أو غير قابل للترحيل",IF(COUNTIF(Locations!$A:$A,$D13)=0,"الموقع غير معرف","")))))
I14: =IF($E14="","",IFERROR(INDEX(COA!$B:$B,MATCH($E14,COA!$A:$A,0)),"حساب غير موجود")) | J14: =IF($A14="","",IF(COUNTIF($A:$A,$A14)>1,"كود مكرر",IF(COUNTIF($E:$E,$E14)>1,"حساب الأستاذ مستخدم لخزينة أخرى",IF(COUNTIFS(COA!$A:$A,$E14,COA!$R:$R,1,COA!$H:$H,1)<>1,"الحساب غير موجود أو غير نقدي أو غير قابل للترحيل",IF(COUNTIF(Locations!$A:$A,$D14)=0,"الموقع غير معرف","")))))
I15: =IF($E15="","",IFERROR(INDEX(COA!$B:$B,MATCH($E15,COA!$A:$A,0)),"حساب غير موجود")) | J15: =IF($A15="","",IF(COUNTIF($A:$A,$A15)>1,"كود مكرر",IF(COUNTIF($E:$E,$E15)>1,"حساب الأستاذ مستخدم لخزينة أخرى",IF(COUNTIFS(COA!$A:$A,$E15,COA!$R:$R,1,COA!$H:$H,1)<>1,"الحساب غير موجود أو غير نقدي أو غير قابل للترحيل",IF(COUNTIF(Locations!$A:$A,$D15)=0,"الموقع غير معرف","")))))
I16: =IF($E16="","",IFERROR(INDEX(COA!$B:$B,MATCH($E16,COA!$A:$A,0)),"حساب غير موجود")) | J16: =IF($A16="","",IF(COUNTIF($A:$A,$A16)>1,"كود مكرر",IF(COUNTIF($E:$E,$E16)>1,"حساب الأستاذ مستخدم لخزينة أخرى",IF(COUNTIFS(COA!$A:$A,$E16,COA!$R:$R,1,COA!$H:$H,1)<>1,"الحساب غير موجود أو غير نقدي أو غير قابل للترحيل",IF(COUNTIF(Locations!$A:$A,$D16)=0,"الموقع غير معرف","")))))
I17: =IF($E17="","",IFERROR(INDEX(COA!$B:$B,MATCH($E17,COA!$A:$A,0)),"حساب غير موجود")) | J17: =IF($A17="","",IF(COUNTIF($A:$A,$A17)>1,"كود مكرر",IF(COUNTIF($E:$E,$E17)>1,"حساب الأستاذ مستخدم لخزينة أخرى",IF(COUNTIFS(COA!$A:$A,$E17,COA!$R:$R,1,COA!$H:$H,1)<>1,"الحساب غير موجود أو غير نقدي أو غير قابل للترحيل",IF(COUNTIF(Locations!$A:$A,$D17)=0,"الموقع غير معرف","")))))
I18: =IF($E18="","",IFERROR(INDEX(COA!$B:$B,MATCH($E18,COA!$A:$A,0)),"حساب غير موجود")) | J18: =IF($A18="","",IF(COUNTIF($A:$A,$A18)>1,"كود مكرر",IF(COUNTIF($E:$E,$E18)>1,"حساب الأستاذ مستخدم لخزينة أخرى",IF(COUNTIFS(COA!$A:$A,$E18,COA!$R:$R,1,COA!$H:$H,1)<>1,"الحساب غير موجود أو غير نقدي أو غير قابل للترحيل",IF(COUNTIF(Locations!$A:$A,$D18)=0,"الموقع غير معرف","")))))
I19: =IF($E19="","",IFERROR(INDEX(COA!$B:$B,MATCH($E19,COA!$A:$A,0)),"حساب غير موجود")) | J19: =IF($A19="","",IF(COUNTIF($A:$A,$A19)>1,"كود مكرر",IF(COUNTIF($E:$E,$E19)>1,"حساب الأستاذ مستخدم لخزينة أخرى",IF(COUNTIFS(COA!$A:$A,$E19,COA!$R:$R,1,COA!$H:$H,1)<>1,"الحساب غير موجود أو غير نقدي أو غير قابل للترحيل",IF(COUNTIF(Locations!$A:$A,$D19)=0,"الموقع غير معرف","")))))
I20: =IF($E20="","",IFERROR(INDEX(COA!$B:$B,MATCH($E20,COA!$A:$A,0)),"حساب غير موجود")) | J20: =IF($A20="","",IF(COUNTIF($A:$A,$A20)>1,"كود مكرر",IF(COUNTIF($E:$E,$E20)>1,"حساب الأستاذ مستخدم لخزينة أخرى",IF(COUNTIFS(COA!$A:$A,$E20,COA!$R:$R,1,COA!$H:$H,1)<>1,"الحساب غير موجود أو غير نقدي أو غير قابل للترحيل",IF(COUNTIF(Locations!$A:$A,$D20)=0,"الموقع غير معرف","")))))
I21: =IF($E21="","",IFERROR(INDEX(COA!$B:$B,MATCH($E21,COA!$A:$A,0)),"حساب غير موجود")) | J21: =IF($A21="","",IF(COUNTIF($A:$A,$A21)>1,"كود مكرر",IF(COUNTIF($E:$E,$E21)>1,"حساب الأستاذ مستخدم لخزينة أخرى",IF(COUNTIFS(COA!$A:$A,$E21,COA!$R:$R,1,COA!$H:$H,1)<>1,"الحساب غير موجود أو غير نقدي أو غير قابل للترحيل",IF(COUNTIF(Locations!$A:$A,$D21)=0,"الموقع غير معرف","")))))
I22: =IF($E22="","",IFERROR(INDEX(COA!$B:$B,MATCH($E22,COA!$A:$A,0)),"حساب غير موجود")) | J22: =IF($A22="","",IF(COUNTIF($A:$A,$A22)>1,"كود مكرر",IF(COUNTIF($E:$E,$E22)>1,"حساب الأستاذ مستخدم لخزينة أخرى",IF(COUNTIFS(COA!$A:$A,$E22,COA!$R:$R,1,COA!$H:$H,1)<>1,"الحساب غير موجود أو غير نقدي أو غير قابل للترحيل",IF(COUNTIF(Locations!$A:$A,$D22)=0,"الموقع غير معرف","")))))
I23: =IF($E23="","",IFERROR(INDEX(COA!$B:$B,MATCH($E23,COA!$A:$A,0)),"حساب غير موجود")) | J23: =IF($A23="","",IF(COUNTIF($A:$A,$A23)>1,"كود مكرر",IF(COUNTIF($E:$E,$E23)>1,"حساب الأستاذ مستخدم لخزينة أخرى",IF(COUNTIFS(COA!$A:$A,$E23,COA!$R:$R,1,COA!$H:$H,1)<>1,"الحساب غير موجود أو غير نقدي أو غير قابل للترحيل",IF(COUNTIF(Locations!$A:$A,$D23)=0,"الموقع غير معرف","")))))
I24: =IF($E24="","",IFERROR(INDEX(COA!$B:$B,MATCH($E24,COA!$A:$A,0)),"حساب غير موجود")) | J24: =IF($A24="","",IF(COUNTIF($A:$A,$A24)>1,"كود مكرر",IF(COUNTIF($E:$E,$E24)>1,"حساب الأستاذ مستخدم لخزينة أخرى",IF(COUNTIFS(COA!$A:$A,$E24,COA!$R:$R,1,COA!$H:$H,1)<>1,"الحساب غير موجود أو غير نقدي أو غير قابل للترحيل",IF(COUNTIF(Locations!$A:$A,$D24)=0,"الموقع غير معرف","")))))
... I34: =IF($E34="","",IFERROR(INDEX(COA!$B:$B,MATCH($E34,COA!$A:$A,0)),"حساب غير موجود")) | J34: =IF($A34="","",IF(COUNTIF($A:$A,$A34)>1,"كود مكرر",IF(COUNTIF($E:$E,$E34)>1,"حساب الأستاذ مستخدم لخزينة أخرى",IF(COUNTIFS(COA!$A:$A,$E34,COA!$R:$R,1,COA!$H:$H,1)<>1,"الحساب غير موجود أو غير نقدي أو غير قابل للترحيل",IF(COUNTIF(Locations!$A:$A,$D34)=0,"الموقع غير معرف","")))))

Sheet Users
A1: المستخدمون والصلاحيات (Users)
A2: تُستخدم أسماؤهم في خانات المُعِد والمعتمد. الصلاحيات الفعلية تُضبط في مشاركة Google Sheets وحماية الأوراق.
A3: خلايا الإدخال | B3: معادلات (لا تعدّل)
A4: كود المستخدم | B4: الاسم (يُستخدم في الخانات) | C4: بريد جوجل | D4: الدور | E4: نطاق الموقع | F4: نشط | G4: ملاحظات | H4: فحص
H5: =IF($A5="","",IF(COUNTIF($B:$B,$B5)>1,"اسم مكرر",IF($D5="","الدور ناقص","")))
H6: =IF($A6="","",IF(COUNTIF($B:$B,$B6)>1,"اسم مكرر",IF($D6="","الدور ناقص","")))
H7: =IF($A7="","",IF(COUNTIF($B:$B,$B7)>1,"اسم مكرر",IF($D7="","الدور ناقص","")))
H8: =IF($A8="","",IF(COUNTIF($B:$B,$B8)>1,"اسم مكرر",IF($D8="","الدور ناقص","")))
H9: =IF($A9="","",IF(COUNTIF($B:$B,$B9)>1,"اسم مكرر",IF($D9="","الدور ناقص","")))
H10: =IF($A10="","",IF(COUNTIF($B:$B,$B10)>1,"اسم مكرر",IF($D10="","الدور ناقص","")))
H11: =IF($A11="","",IF(COUNTIF($B:$B,$B11)>1,"اسم مكرر",IF($D11="","الدور ناقص","")))
H12: =IF($A12="","",IF(COUNTIF($B:$B,$B12)>1,"اسم مكرر",IF($D12="","الدور ناقص","")))
H13: =IF($A13="","",IF(COUNTIF($B:$B,$B13)>1,"اسم مكرر",IF($D13="","الدور ناقص","")))
H14: =IF($A14="","",IF(COUNTIF($B:$B,$B14)>1,"اسم مكرر",IF($D14="","الدور ناقص","")))
H15: =IF($A15="","",IF(COUNTIF($B:$B,$B15)>1,"اسم مكرر",IF($D15="","الدور ناقص","")))
H16: =IF($A16="","",IF(COUNTIF($B:$B,$B16)>1,"اسم مكرر",IF($D16="","الدور ناقص","")))
... H44: =IF($A44="","",IF(COUNTIF($B:$B,$B44)>1,"اسم مكرر",IF($D44="","الدور ناقص","")))

Sheet Permissions
A1: مصفوفة الصلاحيات والفصل بين المسؤوليات
A2: تطبيق فعلي: Google Sheets sharing + حماية الأوراق + مراجعة مستقلة. (✔ مسموح، ✖ غير مسموح)
A4: الدور | B4: إضافة مستند | C4: تعديل قبل الاعتماد | D4: اعتماد | E4: ترحيل | F4: إلغاء / عكس | G4: إقفال فترة | H4: مراجعة التقارير | I4: تعديل البيانات الأساسية
A5: الإدارة العليا | B5: ✖ | C5: ✖ | D5: ✔ (نهائي للمبالغ الكبيرة) | E5: ✖ | F5: ✖ | G5: ✔ (اعتماد نهائي) | H5: ✔ | I5: ✔ (اعتماد التغيير)
A6: المدير المالي | B6: ✔ | C6: ✔ | D6: ✔ | E6: ✖ (لا يرحّل ما اعتمده) | F6: ✔ (اعتماد) | G6: ✔ | H6: ✔ | I6: ✔
A7: المحاسب | B7: ✔ | C7: ✔ | D7: ✖ (لا يعتمد ما أعدّه) | E7: ✔ | F7: ✔ (بعد اعتماد المدير المالي) | G7: ✖ | H7: ✔ | I7: ✖ (اقتراح فقط)
A8: مراجع الحسابات | B8: ✖ | C8: ✖ | D8: ✖ | E8: ✖ | F8: ✖ | G8: ✔ (توقيع المراجعة) | H8: ✔ | I8: ✖
A9: مدير فرع | B9: ✔ (فرعه) | C9: ✔ (فرعه) | D9: ✔ (مبيعات ومصروفات فرعه) | E9: ✖ | F9: ✖ | G9: ✖ | H9: ✔ (فرعه) | I9: ✖
A10: أمين صندوق | B10: ✔ (خزينته) | C10: ✔ (خزينته) | D10: ✖ | E10: ✖ | F10: ✖ | G10: ✖ | H10: ✖ | I10: ✖
A11: أمين مخزن | B11: ✔ (مخزنه) | C11: ✔ (مخزنه) | D11: ✖ | E11: ✖ | F11: ✖ | G11: ✖ | H11: ✔ (مخزنه) | I11: ✖
A12: مشرف مشتريات | B12: ✔ (طلبات وأوامر) | C12: ✔ | D12: ✔ (حد صلاحية) | E12: ✖ | F12: ✖ | G12: ✖ | H12: ✔ (المشتريات) | I12: ✖
A13: مدير إنتاج | B13: ✔ (إنتاج) | C13: ✔ | D13: ✔ (إنتاج وهالك) | E13: ✖ | F13: ✖ | G13: ✖ | H13: ✔ (السنتر كيتشن) | I13: ✖
A14: مستخدم قراءة | B14: ✖ | C14: ✖ | D14: ✖ | E14: ✖ | F14: ✖ | G14: ✖ | H14: ✔ | I14: ✖
A17: قواعد الفصل بين المسؤوليات
A18: طالب الشراء ≠ معتمد الشراء ≠ مستلم البضاعة ≠ أمين المخزن ≠ معتمد الدفع | B18: لا يجتمع طلب البضاعة واستلامها واعتماد دفعها في شخص واحد.
A19: مُعِد المستند ≠ المعتمد ≠ المرحِّل | B19: النظام يفحص آليًا: المُعِد والمعتمد والمرحِّل أسماء مختلفة؛ وإلا يظهر خطأ ولا يُرحَّل المستند.
A20: أمين الصندوق ≠ مسجل الحسابات | B20: من يستلم النقدية لا يسجلها في دفاتر الحسابات.
A21: المحاسب ≠ مراجع الحسابات | B21: المراجعة مستقلة عن التسجيل.
A22: محاسب الأصول/المخزون ≠ أمين المخزن | B22: من يجرد ليس من يحفظ.
A24: ضوابط تعويضية عند محدودية الموظفين
A25: إذا كان فريق الفرع محدودًا: يوقّع مديرُ الفرع كمعتمد، ويكون الكاشير هو المُعِد، ويرحّل المحاسب المركزي (لا أحد من الفرع).
A26: مراجعة مستقلة شهرية من المدير المالي أو المراجع الخارجي للخزائن والمخزون والمستندات المرحلة (عينة 10% على الأقل + كل المستندات فوق حد الصلاحية).
A27: توقيع مزدوج (اثنان) على أي صرف نقدي أو تحويل أو عجز/زيادة فوق الحد المحدد في الإدارة.
A28: جرد مفاجئ للخزائن والمخزون مرة شهريًا على الأقل بواسطة شخص من خارج الموقع.
A29: حفظ نسخ احتياطية أسبوعية لملف Google Sheets، وتفعيل سجل الإصدارات (Version history)، وعدم مشاركة الملف مع صلاحية (محرر) لغير الأسماء الموجودة في Users.
A30: تنبيه: Google Sheets وحده ليس نظام صلاحيات مالي غير قابل للتلاعب. حماية الأوراق تمنع الأخطاء العارضة، لكن من لديه صلاحية (مالك/محرر كامل) يستطيع تجاوزها. اعتمد على صلاحيات حسابات جوجل، وسجل الإصدارات، والنسخ الاحتياطية، والمراجعة المستقلة.

Sheet Suppliers
A1: الموردون (Suppliers)
A2: كود المورد ثابت ولا يتكرر. شروط السداد (أيام) تحدد تاريخ الاستحقاق في فواتير الموردين.
A3: خلايا الإدخال | B3: معادلات (لا تعدّل)
A4: كود المورد | B4: اسم المورد | C4: التصنيف | D4: شروط السداد (أيام) | E4: الهاتف | F4: الرقم الضريبي | G4: حساب المدين الافتراضي | H4: نشط | I4: ملاحظات | J4: فحص
J5: =IF($A5="","",IF(COUNTIF($A:$A,$A5)>1,"كود مورد مكرر",IF($B5="","اسم المورد ناقص",IF($D5="","شروط السداد ناقصة",""))))
J6: =IF($A6="","",IF(COUNTIF($A:$A,$A6)>1,"كود مورد مكرر",IF($B6="","اسم المورد ناقص",IF($D6="","شروط السداد ناقصة",""))))
J7: =IF($A7="","",IF(COUNTIF($A:$A,$A7)>1,"كود مورد مكرر",IF($B7="","اسم المورد ناقص",IF($D7="","شروط السداد ناقصة",""))))
J8: =IF($A8="","",IF(COUNTIF($A:$A,$A8)>1,"كود مورد مكرر",IF($B8="","اسم المورد ناقص",IF($D8="","شروط السداد ناقصة",""))))
J9: =IF($A9="","",IF(COUNTIF($A:$A,$A9)>1,"كود مورد مكرر",IF($B9="","اسم المورد ناقص",IF($D9="","شروط السداد ناقصة",""))))
J10: =IF($A10="","",IF(COUNTIF($A:$A,$A10)>1,"كود مورد مكرر",IF($B10="","اسم المورد ناقص",IF($D10="","شروط السداد ناقصة",""))))
J11: =IF($A11="","",IF(COUNTIF($A:$A,$A11)>1,"كود مورد مكرر",IF($B11="","اسم المورد ناقص",IF($D11="","شروط السداد ناقصة",""))))
J12: =IF($A12="","",IF(COUNTIF($A:$A,$A12)>1,"كود مورد مكرر",IF($B12="","اسم المورد ناقص",IF($D12="","شروط السداد ناقصة",""))))
J13: =IF($A13="","",IF(COUNTIF($A:$A,$A13)>1,"كود مورد مكرر",IF($B13="","اسم المورد ناقص",IF($D13="","شروط السداد ناقصة",""))))
J14: =IF($A14="","",IF(COUNTIF($A:$A,$A14)>1,"كود مورد مكرر",IF($B14="","اسم المورد ناقص",IF($D14="","شروط السداد ناقصة",""))))
J15: =IF($A15="","",IF(COUNTIF($A:$A,$A15)>1,"كود مورد مكرر",IF($B15="","اسم المورد ناقص",IF($D15="","شروط السداد ناقصة",""))))
J16: =IF($A16="","",IF(COUNTIF($A:$A,$A16)>1,"كود مورد مكرر",IF($B16="","اسم المورد ناقص",IF($D16="","شروط السداد ناقصة",""))))
... J154: =IF($A154="","",IF(COUNTIF($A:$A,$A154)>1,"كود مورد مكرر",IF($B154="","اسم المورد ناقص",IF($D154="","شروط السداد ناقصة",""))))

Sheet Customers
A1: العملاء والمدينون (Customers)
A2: للعملاء الآجلين فقط (شركات/تموين). مبيعات الفروع والمنصات لا تحتاج عميلًا.
A3: خلايا الإدخال | B3: معادلات (لا تعدّل)
A4: كود العميل | B4: اسم العميل | C4: شروط السداد (أيام) | D4: حد الائتمان | E4: الهاتف | F4: نشط | G4: ملاحظات | H4: فحص
H5: =IF($A5="","",IF(COUNTIF($A:$A,$A5)>1,"كود مكرر",IF($B5="","الاسم ناقص","")))
H6: =IF($A6="","",IF(COUNTIF($A:$A,$A6)>1,"كود مكرر",IF($B6="","الاسم ناقص","")))
H7: =IF($A7="","",IF(COUNTIF($A:$A,$A7)>1,"كود مكرر",IF($B7="","الاسم ناقص","")))
H8: =IF($A8="","",IF(COUNTIF($A:$A,$A8)>1,"كود مكرر",IF($B8="","الاسم ناقص","")))
H9: =IF($A9="","",IF(COUNTIF($A:$A,$A9)>1,"كود مكرر",IF($B9="","الاسم ناقص","")))
H10: =IF($A10="","",IF(COUNTIF($A:$A,$A10)>1,"كود مكرر",IF($B10="","الاسم ناقص","")))
H11: =IF($A11="","",IF(COUNTIF($A:$A,$A11)>1,"كود مكرر",IF($B11="","الاسم ناقص","")))
H12: =IF($A12="","",IF(COUNTIF($A:$A,$A12)>1,"كود مكرر",IF($B12="","الاسم ناقص","")))
H13: =IF($A13="","",IF(COUNTIF($A:$A,$A13)>1,"كود مكرر",IF($B13="","الاسم ناقص","")))
H14: =IF($A14="","",IF(COUNTIF($A:$A,$A14)>1,"كود مكرر",IF($B14="","الاسم ناقص","")))
H15: =IF($A15="","",IF(COUNTIF($A:$A,$A15)>1,"كود مكرر",IF($B15="","الاسم ناقص","")))
H16: =IF($A16="","",IF(COUNTIF($A:$A,$A16)>1,"كود مكرر",IF($B16="","الاسم ناقص","")))
... H104: =IF($A104="","",IF(COUNTIF($A:$A,$A104)>1,"كود مكرر",IF($B104="","الاسم ناقص","")))

Sheet Employees
A1: الموظفون والسلف والعهد (Employees)
A2: أرصدة السلف والعهد تُحسب من الأستاذ العام (حسابا 1501 و1502) وفق كود الموظف.
A3: خلايا الإدخال | B3: معادلات (لا تعدّل)
A4: كود الموظف | B4: الاسم | C4: الموقع | D4: الوظيفة | E4: تاريخ التعيين | F4: الراتب الأساسي | G4: نشط | H4: ملاحظات | I4: رصيد السلف | J4: رصيد العهدة | K4: فحص
I5: =IF($A5="","",SUMIFS(GL_Journal!$S:$S,GL_Journal!$G:$G,1501,GL_Journal!$K:$K,$A5)-SUMIFS(GL_Journal!$T:$T,GL_Journal!$G:$G,1501,GL_Journal!$K:$K,$A5)) | J5: =IF($A5="","",SUMIFS(GL_Journal!$S:$S,GL_Journal!$G:$G,1502,GL_Journal!$K:$K,$A5)-SUMIFS(GL_Journal!$T:$T,GL_Journal!$G:$G,1502,GL_Journal!$K:$K,$A5)) | K5: =IF($A5="","",IF(COUNTIF($A:$A,$A5)>1,"كود مكرر",IF($B5="","الاسم ناقص","")))
I6: =IF($A6="","",SUMIFS(GL_Journal!$S:$S,GL_Journal!$G:$G,1501,GL_Journal!$K:$K,$A6)-SUMIFS(GL_Journal!$T:$T,GL_Journal!$G:$G,1501,GL_Journal!$K:$K,$A6)) | J6: =IF($A6="","",SUMIFS(GL_Journal!$S:$S,GL_Journal!$G:$G,1502,GL_Journal!$K:$K,$A6)-SUMIFS(GL_Journal!$T:$T,GL_Journal!$G:$G,1502,GL_Journal!$K:$K,$A6)) | K6: =IF($A6="","",IF(COUNTIF($A:$A,$A6)>1,"كود مكرر",IF($B6="","الاسم ناقص","")))
I7: =IF($A7="","",SUMIFS(GL_Journal!$S:$S,GL_Journal!$G:$G,1501,GL_Journal!$K:$K,$A7)-SUMIFS(GL_Journal!$T:$T,GL_Journal!$G:$G,1501,GL_Journal!$K:$K,$A7)) | J7: =IF($A7="","",SUMIFS(GL_Journal!$S:$S,GL_Journal!$G:$G,1502,GL_Journal!$K:$K,$A7)-SUMIFS(GL_Journal!$T:$T,GL_Journal!$G:$G,1502,GL_Journal!$K:$K,$A7)) | K7: =IF($A7="","",IF(COUNTIF($A:$A,$A7)>1,"كود مكرر",IF($B7="","الاسم ناقص","")))
I8: =IF($A8="","",SUMIFS(GL_Journal!$S:$S,GL_Journal!$G:$G,1501,GL_Journal!$K:$K,$A8)-SUMIFS(GL_Journal!$T:$T,GL_Journal!$G:$G,1501,GL_Journal!$K:$K,$A8)) | J8: =IF($A8="","",SUMIFS(GL_Journal!$S:$S,GL_Journal!$G:$G,1502,GL_Journal!$K:$K,$A8)-SUMIFS(GL_Journal!$T:$T,GL_Journal!$G:$G,1502,GL_Journal!$K:$K,$A8)) | K8: =IF($A8="","",IF(COUNTIF($A:$A,$A8)>1,"كود مكرر",IF($B8="","الاسم ناقص","")))
I9: =IF($A9="","",SUMIFS(GL_Journal!$S:$S,GL_Journal!$G:$G,1501,GL_Journal!$K:$K,$A9)-SUMIFS(GL_Journal!$T:$T,GL_Journal!$G:$G,1501,GL_Journal!$K:$K,$A9)) | J9: =IF($A9="","",SUMIFS(GL_Journal!$S:$S,GL_Journal!$G:$G,1502,GL_Journal!$K:$K,$A9)-SUMIFS(GL_Journal!$T:$T,GL_Journal!$G:$G,1502,GL_Journal!$K:$K,$A9)) | K9: =IF($A9="","",IF(COUNTIF($A:$A,$A9)>1,"كود مكرر",IF($B9="","الاسم ناقص","")))
I10: =IF($A10="","",SUMIFS(GL_Journal!$S:$S,GL_Journal!$G:$G,1501,GL_Journal!$K:$K,$A10)-SUMIFS(GL_Journal!$T:$T,GL_Journal!$G:$G,1501,GL_Journal!$K:$K,$A10)) | J10: =IF($A10="","",SUMIFS(GL_Journal!$S:$S,GL_Journal!$G:$G,1502,GL_Journal!$K:$K,$A10)-SUMIFS(GL_Journal!$T:$T,GL_Journal!$G:$G,1502,GL_Journal!$K:$K,$A10)) | K10: =IF($A10="","",IF(COUNTIF($A:$A,$A10)>1,"كود مكرر",IF($B10="","الاسم ناقص","")))
I11: =IF($A11="","",SUMIFS(GL_Journal!$S:$S,GL_Journal!$G:$G,1501,GL_Journal!$K:$K,$A11)-SUMIFS(GL_Journal!$T:$T,GL_Journal!$G:$G,1501,GL_Journal!$K:$K,$A11)) | J11: =IF($A11="","",SUMIFS(GL_Journal!$S:$S,GL_Journal!$G:$G,1502,GL_Journal!$K:$K,$A11)-SUMIFS(GL_Journal!$T:$T,GL_Journal!$G:$G,1502,GL_Journal!$K:$K,$A11)) | K11: =IF($A11="","",IF(COUNTIF($A:$A,$A11)>1,"كود مكرر",IF($B11="","الاسم ناقص","")))
I12: =IF($A12="","",SUMIFS(GL_Journal!$S:$S,GL_Journal!$G:$G,1501,GL_Journal!$K:$K,$A12)-SUMIFS(GL_Journal!$T:$T,GL_Journal!$G:$G,1501,GL_Journal!$K:$K,$A12)) | J12: =IF($A12="","",SUMIFS(GL_Journal!$S:$S,GL_Journal!$G:$G,1502,GL_Journal!$K:$K,$A12)-SUMIFS(GL_Journal!$T:$T,GL_Journal!$G:$G,1502,GL_Journal!$K:$K,$A12)) | K12: =IF($A12="","",IF(COUNTIF($A:$A,$A12)>1,"كود مكرر",IF($B12="","الاسم ناقص","")))
I13: =IF($A13="","",SUMIFS(GL_Journal!$S:$S,GL_Journal!$G:$G,1501,GL_Journal!$K:$K,$A13)-SUMIFS(GL_Journal!$T:$T,GL_Journal!$G:$G,1501,GL_Journal!$K:$K,$A13)) | J13: =IF($A13="","",SUMIFS(GL_Journal!$S:$S,GL_Journal!$G:$G,1502,GL_Journal!$K:$K,$A13)-SUMIFS(GL_Journal!$T:$T,GL_Journal!$G:$G,1502,GL_Journal!$K:$K,$A13)) | K13: =IF($A13="","",IF(COUNTIF($A:$A,$A13)>1,"كود مكرر",IF($B13="","الاسم ناقص","")))
I14: =IF($A14="","",SUMIFS(GL_Journal!$S:$S,GL_Journal!$G:$G,1501,GL_Journal!$K:$K,$A14)-SUMIFS(GL_Journal!$T:$T,GL_Journal!$G:$G,1501,GL_Journal!$K:$K,$A14)) | J14: =IF($A14="","",SUMIFS(GL_Journal!$S:$S,GL_Journal!$G:$G,1502,GL_Journal!$K:$K,$A14)-SUMIFS(GL_Journal!$T:$T,GL_Journal!$G:$G,1502,GL_Journal!$K:$K,$A14)) | K14: =IF($A14="","",IF(COUNTIF($A:$A,$A14)>1,"كود مكرر",IF($B14="","الاسم ناقص","")))
I15: =IF($A15="","",SUMIFS(GL_Journal!$S:$S,GL_Journal!$G:$G,1501,GL_Journal!$K:$K,$A15)-SUMIFS(GL_Journal!$T:$T,GL_Journal!$G:$G,1501,GL_Journal!$K:$K,$A15)) | J15: =IF($A15="","",SUMIFS(GL_Journal!$S:$S,GL_Journal!$G:$G,1502,GL_Journal!$K:$K,$A15)-SUMIFS(GL_Journal!$T:$T,GL_Journal!$G:$G,1502,GL_Journal!$K:$K,$A15)) | K15: =IF($A15="","",IF(COUNTIF($A:$A,$A15)>1,"كود مكرر",IF($B15="","الاسم ناقص","")))
I16: =IF($A16="","",SUMIFS(GL_Journal!$S:$S,GL_Journal!$G:$G,1501,GL_Journal!$K:$K,$A16)-SUMIFS(GL_Journal!$T:$T,GL_Journal!$G:$G,1501,GL_Journal!$K:$K,$A16)) | J16: =IF($A16="","",SUMIFS(GL_Journal!$S:$S,GL_Journal!$G:$G,1502,GL_Journal!$K:$K,$A16)-SUMIFS(GL_Journal!$T:$T,GL_Journal!$G:$G,1502,GL_Journal!$K:$K,$A16)) | K16: =IF($A16="","",IF(COUNTIF($A:$A,$A16)>1,"كود مكرر",IF($B16="","الاسم ناقص","")))
... I104: =IF($A104="","",SUMIFS(GL_Journal!$S:$S,GL_Journal!$G:$G,1501,GL_Journal!$K:$K,$A104)-SUMIFS(GL_Journal!$T:$T,GL_Journal!$G:$G,1501,GL_Journal!$K:$K,$A104)) | J104: =IF($A104="","",SUMIFS(GL_Journal!$S:$S,GL_Journal!$G:$G,1502,GL_Journal!$K:$K,$A104)-SUMIFS(GL_Journal!$T:$T,GL_Journal!$G:$G,1502,GL_Journal!$K:$K,$A104)) | K104: =IF($A104="","",IF(COUNTIF($A:$A,$A104)>1,"كود مكرر",IF($B104="","الاسم ناقص","")))

Sheet Items
A1: بطاقات الأصناف (Item Master)
A2: لكل صنف وحدة أساسية واحدة لا تتغير. الأرصدة تُحسب من حركات المخزون (المرحلة 2) وليس من هنا.
A3: خلايا الإدخال | B3: معادلات (لا تعدّل)
A4: كود الصنف | B4: اسم الصنف | C4: التصنيف | D4: الوحدة الأساسية | E4: النوع | F4: حد إعادة الطلب | G4: مدة الصلاحية (يوم) | H4: المورد الافتراضي | I4: تكلفة قياسية (اختياري) | J4: حساب المخزون | K4: نشط | L4: فحص
L5: =IF($A5="","",IF(COUNTIF($A:$A,$A5)>1,"كود صنف مكرر",IF($D5="","الوحدة الأساسية ناقصة",IF(COUNTIF(Units!$A:$A,$D5)=0,"وحدة غير معرفة",""))))
L6: =IF($A6="","",IF(COUNTIF($A:$A,$A6)>1,"كود صنف مكرر",IF($D6="","الوحدة الأساسية ناقصة",IF(COUNTIF(Units!$A:$A,$D6)=0,"وحدة غير معرفة",""))))
L7: =IF($A7="","",IF(COUNTIF($A:$A,$A7)>1,"كود صنف مكرر",IF($D7="","الوحدة الأساسية ناقصة",IF(COUNTIF(Units!$A:$A,$D7)=0,"وحدة غير معرفة",""))))
L8: =IF($A8="","",IF(COUNTIF($A:$A,$A8)>1,"كود صنف مكرر",IF($D8="","الوحدة الأساسية ناقصة",IF(COUNTIF(Units!$A:$A,$D8)=0,"وحدة غير معرفة",""))))
L9: =IF($A9="","",IF(COUNTIF($A:$A,$A9)>1,"كود صنف مكرر",IF($D9="","الوحدة الأساسية ناقصة",IF(COUNTIF(Units!$A:$A,$D9)=0,"وحدة غير معرفة",""))))
L10: =IF($A10="","",IF(COUNTIF($A:$A,$A10)>1,"كود صنف مكرر",IF($D10="","الوحدة الأساسية ناقصة",IF(COUNTIF(Units!$A:$A,$D10)=0,"وحدة غير معرفة",""))))
L11: =IF($A11="","",IF(COUNTIF($A:$A,$A11)>1,"كود صنف مكرر",IF($D11="","الوحدة الأساسية ناقصة",IF(COUNTIF(Units!$A:$A,$D11)=0,"وحدة غير معرفة",""))))
L12: =IF($A12="","",IF(COUNTIF($A:$A,$A12)>1,"كود صنف مكرر",IF($D12="","الوحدة الأساسية ناقصة",IF(COUNTIF(Units!$A:$A,$D12)=0,"وحدة غير معرفة",""))))
L13: =IF($A13="","",IF(COUNTIF($A:$A,$A13)>1,"كود صنف مكرر",IF($D13="","الوحدة الأساسية ناقصة",IF(COUNTIF(Units!$A:$A,$D13)=0,"وحدة غير معرفة",""))))
L14: =IF($A14="","",IF(COUNTIF($A:$A,$A14)>1,"كود صنف مكرر",IF($D14="","الوحدة الأساسية ناقصة",IF(COUNTIF(Units!$A:$A,$D14)=0,"وحدة غير معرفة",""))))
L15: =IF($A15="","",IF(COUNTIF($A:$A,$A15)>1,"كود صنف مكرر",IF($D15="","الوحدة الأساسية ناقصة",IF(COUNTIF(Units!$A:$A,$D15)=0,"وحدة غير معرفة",""))))
L16: =IF($A16="","",IF(COUNTIF($A:$A,$A16)>1,"كود صنف مكرر",IF($D16="","الوحدة الأساسية ناقصة",IF(COUNTIF(Units!$A:$A,$D16)=0,"وحدة غير معرفة",""))))
... L304: =IF($A304="","",IF(COUNTIF($A:$A,$A304)>1,"كود صنف مكرر",IF($D304="","الوحدة الأساسية ناقصة",IF(COUNTIF(Units!$A:$A,$D304)=0,"وحدة غير معرفة",""))))

Sheet Units
A1: وحدات القياس (Units of Measure)
A2: الوحدة الأساسية لكل صنف تُحدد في بطاقة الصنف. التحويل بين الوحدات يتم فقط عبر Unit_Conversions المعتمد.
A3: خلايا الإدخال | B3: معادلات (لا تعدّل)
A4: كود الوحدة | B4: الاسم | C4: النوع | D4: ملاحظات | E4: فحص
A5: KG | B5: كيلوجرام | C5: وزن | E5: =IF($A5="","",IF(COUNTIF($A:$A,$A5)>1,"كود مكرر",""))
A6: G | B6: جرام | C6: وزن | E6: =IF($A6="","",IF(COUNTIF($A:$A,$A6)>1,"كود مكرر",""))
A7: L | B7: لتر | C7: حجم | E7: =IF($A7="","",IF(COUNTIF($A:$A,$A7)>1,"كود مكرر",""))
A8: ML | B8: مللي لتر | C8: حجم | E8: =IF($A8="","",IF(COUNTIF($A:$A,$A8)>1,"كود مكرر",""))
A9: PC | B9: قطعة | C9: عدد | E9: =IF($A9="","",IF(COUNTIF($A:$A,$A9)>1,"كود مكرر",""))
A10: PACK | B10: عبوة | C10: عبوة | E10: =IF($A10="","",IF(COUNTIF($A:$A,$A10)>1,"كود مكرر",""))
A11: CTN | B11: كرتونة | C11: عبوة | E11: =IF($A11="","",IF(COUNTIF($A:$A,$A11)>1,"كود مكرر",""))
A12: BAG | B12: شكارة | C12: عبوة | E12: =IF($A12="","",IF(COUNTIF($A:$A,$A12)>1,"كود مكرر",""))
E13: =IF($A13="","",IF(COUNTIF($A:$A,$A13)>1,"كود مكرر",""))
E14: =IF($A14="","",IF(COUNTIF($A:$A,$A14)>1,"كود مكرر",""))
E15: =IF($A15="","",IF(COUNTIF($A:$A,$A15)>1,"كود مكرر",""))
E16: =IF($A16="","",IF(COUNTIF($A:$A,$A16)>1,"كود مكرر",""))
E17: =IF($A17="","",IF(COUNTIF($A:$A,$A17)>1,"كود مكرر",""))
E18: =IF($A18="","",IF(COUNTIF($A:$A,$A18)>1,"كود مكرر",""))
E19: =IF($A19="","",IF(COUNTIF($A:$A,$A19)>1,"كود مكرر",""))
E20: =IF($A20="","",IF(COUNTIF($A:$A,$A20)>1,"كود مكرر",""))
E21: =IF($A21="","",IF(COUNTIF($A:$A,$A21)>1,"كود مكرر",""))
E22: =IF($A22="","",IF(COUNTIF($A:$A,$A22)>1,"كود مكرر",""))
E23: =IF($A23="","",IF(COUNTIF($A:$A,$A23)>1,"كود مكرر",""))
E24: =IF($A24="","",IF(COUNTIF($A:$A,$A24)>1,"كود مكرر",""))
... E34: =IF($A34="","",IF(COUNTIF($A:$A,$A34)>1,"كود مكرر",""))

Sheet Unit_Conversions
A1: جدول تحويل الوحدات (Unit Conversions)
A2: التحويل لا يعمل آليًا إلا إذا كان المعامل معرّفًا ومعتمدًا (نعم). اكتب GENERAL في خانة الصنف للمعامل العام، أو كود الصنف للمعامل الخاص به (مثل: كرتونة البيض = 30 قطعة).
A3: خلايا الإدخال | B3: معادلات (لا تعدّل)
A4: من وحدة | B4: إلى وحدة | C4: المعامل (1 من = ؟ إلى) | D4: الصنف (GENERAL أو كود) | E4: معتمد؟ | F4: المعتمد | G4: ملاحظات | H4: فحص
A5: KG | B5: G | C5: 1000 | D5: GENERAL | E5: نعم | F5: المدير المالي (تجريبي) | H5: =IF($A5&$B5="","",IF(OR($A5="",$B5=""),"الوحدة ناقصة",IF($A5=$B5,"الوحدتان متطابقتان",IF(NOT(ISNUMBER($C5)),"المعامل غير معرف",IF($C5<=0,"المعامل يجب أن يكون موجبًا",IF($D5="","الصنف ناقص (GENERAL أو كود)",IF(COUNTIFS($A:$A,$A5,$B:$B,$B5,$D:$D,$D5)>1,"معامل مكرر لنفس الوحدتين والصنف",IF(AND($E5="نعم",$F5=""),"اسم المعتمد ناقص",""))))))))
A6: L | B6: ML | C6: 1000 | D6: GENERAL | E6: نعم | F6: المدير المالي (تجريبي) | H6: =IF($A6&$B6="","",IF(OR($A6="",$B6=""),"الوحدة ناقصة",IF($A6=$B6,"الوحدتان متطابقتان",IF(NOT(ISNUMBER($C6)),"المعامل غير معرف",IF($C6<=0,"المعامل يجب أن يكون موجبًا",IF($D6="","الصنف ناقص (GENERAL أو كود)",IF(COUNTIFS($A:$A,$A6,$B:$B,$B6,$D:$D,$D6)>1,"معامل مكرر لنفس الوحدتين والصنف",IF(AND($E6="نعم",$F6=""),"اسم المعتمد ناقص",""))))))))
A7: CTN | B7: PC | C7: 30 | D7: ITM010 | E7: نعم | F7: المدير المالي (تجريبي) | H7: =IF($A7&$B7="","",IF(OR($A7="",$B7=""),"الوحدة ناقصة",IF($A7=$B7,"الوحدتان متطابقتان",IF(NOT(ISNUMBER($C7)),"المعامل غير معرف",IF($C7<=0,"المعامل يجب أن يكون موجبًا",IF($D7="","الصنف ناقص (GENERAL أو كود)",IF(COUNTIFS($A:$A,$A7,$B:$B,$B7,$D:$D,$D7)>1,"معامل مكرر لنفس الوحدتين والصنف",IF(AND($E7="نعم",$F7=""),"اسم المعتمد ناقص",""))))))))
A8: BAG | B8: KG | C8: 25 | D8: ITM002 | E8: نعم | F8: المدير المالي (تجريبي) | H8: =IF($A8&$B8="","",IF(OR($A8="",$B8=""),"الوحدة ناقصة",IF($A8=$B8,"الوحدتان متطابقتان",IF(NOT(ISNUMBER($C8)),"المعامل غير معرف",IF($C8<=0,"المعامل يجب أن يكون موجبًا",IF($D8="","الصنف ناقص (GENERAL أو كود)",IF(COUNTIFS($A:$A,$A8,$B:$B,$B8,$D:$D,$D8)>1,"معامل مكرر لنفس الوحدتين والصنف",IF(AND($E8="نعم",$F8=""),"اسم المعتمد ناقص",""))))))))
A9: PACK | B9: KG | C9: 2.5 | D9: ITM001 | E9: لا | G9: غير معتمد: لن يعمل التحويل | H9: =IF($A9&$B9="","",IF(OR($A9="",$B9=""),"الوحدة ناقصة",IF($A9=$B9,"الوحدتان متطابقتان",IF(NOT(ISNUMBER($C9)),"المعامل غير معرف",IF($C9<=0,"المعامل يجب أن يكون موجبًا",IF($D9="","الصنف ناقص (GENERAL أو كود)",IF(COUNTIFS($A:$A,$A9,$B:$B,$B9,$D:$D,$D9)>1,"معامل مكرر لنفس الوحدتين والصنف",IF(AND($E9="نعم",$F9=""),"اسم المعتمد ناقص",""))))))))
H10: =IF($A10&$B10="","",IF(OR($A10="",$B10=""),"الوحدة ناقصة",IF($A10=$B10,"الوحدتان متطابقتان",IF(NOT(ISNUMBER($C10)),"المعامل غير معرف",IF($C10<=0,"المعامل يجب أن يكون موجبًا",IF($D10="","الصنف ناقص (GENERAL أو كود)",IF(COUNTIFS($A:$A,$A10,$B:$B,$B10,$D:$D,$D10)>1,"معامل مكرر لنفس الوحدتين والصنف",IF(AND($E10="نعم",$F10=""),"اسم المعتمد ناقص",""))))))))
H11: =IF($A11&$B11="","",IF(OR($A11="",$B11=""),"الوحدة ناقصة",IF($A11=$B11,"الوحدتان متطابقتان",IF(NOT(ISNUMBER($C11)),"المعامل غير معرف",IF($C11<=0,"المعامل يجب أن يكون موجبًا",IF($D11="","الصنف ناقص (GENERAL أو كود)",IF(COUNTIFS($A:$A,$A11,$B:$B,$B11,$D:$D,$D11)>1,"معامل مكرر لنفس الوحدتين والصنف",IF(AND($E11="نعم",$F11=""),"اسم المعتمد ناقص",""))))))))
H12: =IF($A12&$B12="","",IF(OR($A12="",$B12=""),"الوحدة ناقصة",IF($A12=$B12,"الوحدتان متطابقتان",IF(NOT(ISNUMBER($C12)),"المعامل غير معرف",IF($C12<=0,"المعامل يجب أن يكون موجبًا",IF($D12="","الصنف ناقص (GENERAL أو كود)",IF(COUNTIFS($A:$A,$A12,$B:$B,$B12,$D:$D,$D12)>1,"معامل مكرر لنفس الوحدتين والصنف",IF(AND($E12="نعم",$F12=""),"اسم المعتمد ناقص",""))))))))
H13: =IF($A13&$B13="","",IF(OR($A13="",$B13=""),"الوحدة ناقصة",IF($A13=$B13,"الوحدتان متطابقتان",IF(NOT(ISNUMBER($C13)),"المعامل غير معرف",IF($C13<=0,"المعامل يجب أن يكون موجبًا",IF($D13="","الصنف ناقص (GENERAL أو كود)",IF(COUNTIFS($A:$A,$A13,$B:$B,$B13,$D:$D,$D13)>1,"معامل مكرر لنفس الوحدتين والصنف",IF(AND($E13="نعم",$F13=""),"اسم المعتمد ناقص",""))))))))
H14: =IF($A14&$B14="","",IF(OR($A14="",$B14=""),"الوحدة ناقصة",IF($A14=$B14,"الوحدتان متطابقتان",IF(NOT(ISNUMBER($C14)),"المعامل غير معرف",IF($C14<=0,"المعامل يجب أن يكون موجبًا",IF($D14="","الصنف ناقص (GENERAL أو كود)",IF(COUNTIFS($A:$A,$A14,$B:$B,$B14,$D:$D,$D14)>1,"معامل مكرر لنفس الوحدتين والصنف",IF(AND($E14="نعم",$F14=""),"اسم المعتمد ناقص",""))))))))
H15: =IF($A15&$B15="","",IF(OR($A15="",$B15=""),"الوحدة ناقصة",IF($A15=$B15,"الوحدتان متطابقتان",IF(NOT(ISNUMBER($C15)),"المعامل غير معرف",IF($C15<=0,"المعامل يجب أن يكون موجبًا",IF($D15="","الصنف ناقص (GENERAL أو كود)",IF(COUNTIFS($A:$A,$A15,$B:$B,$B15,$D:$D,$D15)>1,"معامل مكرر لنفس الوحدتين والصنف",IF(AND($E15="نعم",$F15=""),"اسم المعتمد ناقص",""))))))))
H16: =IF($A16&$B16="","",IF(OR($A16="",$B16=""),"الوحدة ناقصة",IF($A16=$B16,"الوحدتان متطابقتان",IF(NOT(ISNUMBER($C16)),"المعامل غير معرف",IF($C16<=0,"المعامل يجب أن يكون موجبًا",IF($D16="","الصنف ناقص (GENERAL أو كود)",IF(COUNTIFS($A:$A,$A16,$B:$B,$B16,$D:$D,$D16)>1,"معامل مكرر لنفس الوحدتين والصنف",IF(AND($E16="نعم",$F16=""),"اسم المعتمد ناقص",""))))))))
H17: =IF($A17&$B17="","",IF(OR($A17="",$B17=""),"الوحدة ناقصة",IF($A17=$B17,"الوحدتان متطابقتان",IF(NOT(ISNUMBER($C17)),"المعامل غير معرف",IF($C17<=0,"المعامل يجب أن يكون موجبًا",IF($D17="","الصنف ناقص (GENERAL أو كود)",IF(COUNTIFS($A:$A,$A17,$B:$B,$B17,$D:$D,$D17)>1,"معامل مكرر لنفس الوحدتين والصنف",IF(AND($E17="نعم",$F17=""),"اسم المعتمد ناقص",""))))))))
H18: =IF($A18&$B18="","",IF(OR($A18="",$B18=""),"الوحدة ناقصة",IF($A18=$B18,"الوحدتان متطابقتان",IF(NOT(ISNUMBER($C18)),"المعامل غير معرف",IF($C18<=0,"المعامل يجب أن يكون موجبًا",IF($D18="","الصنف ناقص (GENERAL أو كود)",IF(COUNTIFS($A:$A,$A18,$B:$B,$B18,$D:$D,$D18)>1,"معامل مكرر لنفس الوحدتين والصنف",IF(AND($E18="نعم",$F18=""),"اسم المعتمد ناقص",""))))))))
H19: =IF($A19&$B19="","",IF(OR($A19="",$B19=""),"الوحدة ناقصة",IF($A19=$B19,"الوحدتان متطابقتان",IF(NOT(ISNUMBER($C19)),"المعامل غير معرف",IF($C19<=0,"المعامل يجب أن يكون موجبًا",IF($D19="","الصنف ناقص (GENERAL أو كود)",IF(COUNTIFS($A:$A,$A19,$B:$B,$B19,$D:$D,$D19)>1,"معامل مكرر لنفس الوحدتين والصنف",IF(AND($E19="نعم",$F19=""),"اسم المعتمد ناقص",""))))))))
H20: =IF($A20&$B20="","",IF(OR($A20="",$B20=""),"الوحدة ناقصة",IF($A20=$B20,"الوحدتان متطابقتان",IF(NOT(ISNUMBER($C20)),"المعامل غير معرف",IF($C20<=0,"المعامل يجب أن يكون موجبًا",IF($D20="","الصنف ناقص (GENERAL أو كود)",IF(COUNTIFS($A:$A,$A20,$B:$B,$B20,$D:$D,$D20)>1,"معامل مكرر لنفس الوحدتين والصنف",IF(AND($E20="نعم",$F20=""),"اسم المعتمد ناقص",""))))))))
H21: =IF($A21&$B21="","",IF(OR($A21="",$B21=""),"الوحدة ناقصة",IF($A21=$B21,"الوحدتان متطابقتان",IF(NOT(ISNUMBER($C21)),"المعامل غير معرف",IF($C21<=0,"المعامل يجب أن يكون موجبًا",IF($D21="","الصنف ناقص (GENERAL أو كود)",IF(COUNTIFS($A:$A,$A21,$B:$B,$B21,$D:$D,$D21)>1,"معامل مكرر لنفس الوحدتين والصنف",IF(AND($E21="نعم",$F21=""),"اسم المعتمد ناقص",""))))))))
... H64: =IF($A64&$B64="","",IF(OR($A64="",$B64=""),"الوحدة ناقصة",IF($A64=$B64,"الوحدتان متطابقتان",IF(NOT(ISNUMBER($C64)),"المعامل غير معرف",IF($C64<=0,"المعامل يجب أن يكون موجبًا",IF($D64="","الصنف ناقص (GENERAL أو كود)",IF(COUNTIFS($A:$A,$A64,$B:$B,$B64,$D:$D,$D64)>1,"معامل مكرر لنفس الوحدتين والصنف",IF(AND($E64="نعم",$F64=""),"اسم المعتمد ناقص",""))))))))

Sheet Unit_Converter
A1: محوّل الوحدات المضبوط (Unit Converter)
A2: يحوّل كمية من أي وحدة إلى الوحدة الأساسية للصنف فقط عبر معامل معرّف ومعتمد في Unit_Conversions؛ وإلا يظهر (التحويل غير مسموح) ولا يُنتج رقمًا. لا يُعكس معامل تلقائيًا.
A3: خلايا الإدخال | B3: معادلات (لا تعدّل)
A4: كود الصنف | B4: الكمية | C4: الوحدة المدخلة | D4: الوحدة الأساسية للصنف | E4: المعامل المعتمد | F4: الكمية بالوحدة الأساسية | G4: الحالة
D5: =IF($A5="","",IF(COUNTIF(Items!$A:$A,$A5)=0,"صنف غير معرف",INDEX(Items!$D:$D,MATCH($A5,Items!$A:$A,0)))) | E5: =IF(OR($A5="",$C5=""),"",IF($D5="صنف غير معرف","",IF($C5=$D5,1,IF(COUNTIFS(Unit_Conversions!$A:$A,$C5,Unit_Conversions!$B:$B,$D5,Unit_Conversions!$D:$D,$A5,Unit_Conversions!$E:$E,"نعم",Unit_Conversions!$C:$C,">0")=1,SUMIFS(Unit_Conversions!$C:$C,Unit_Conversions!$A:$A,$C5,Unit_Conversions!$B:$B,$D5,Unit_Conversions!$D:$D,$A5,Unit_Conversions!$E:$E,"نعم"),IF(COUNTIFS(Unit_Conversions!$A:$A,$C5,Unit_Conversions!$B:$B,$D5,Unit_Conversions!$D:$D,"GENERAL",Unit_Conversions!$E:$E,"نعم",Unit_Conversions!$C:$C,">0")=1,SUMIFS(Unit_Conversions!$C:$C,Unit_Conversions!$A:$A,$C5,Unit_Conversions!$B:$B,$D5,Unit_Conversions!$D:$D,"GENERAL",Unit_Conversions!$E:$E,"نعم"),""))))) | F5: =IF($E5="","",IF(ISNUMBER($B5),$B5*$E5,"")) | G5: =IF(OR($A5="",$C5=""),"",IF($D5="صنف غير معرف","صنف غير معرف",IF($E5="","التحويل غير مسموح: معامل غير معرّف أو غير معتمد","")))
D6: =IF($A6="","",IF(COUNTIF(Items!$A:$A,$A6)=0,"صنف غير معرف",INDEX(Items!$D:$D,MATCH($A6,Items!$A:$A,0)))) | E6: =IF(OR($A6="",$C6=""),"",IF($D6="صنف غير معرف","",IF($C6=$D6,1,IF(COUNTIFS(Unit_Conversions!$A:$A,$C6,Unit_Conversions!$B:$B,$D6,Unit_Conversions!$D:$D,$A6,Unit_Conversions!$E:$E,"نعم",Unit_Conversions!$C:$C,">0")=1,SUMIFS(Unit_Conversions!$C:$C,Unit_Conversions!$A:$A,$C6,Unit_Conversions!$B:$B,$D6,Unit_Conversions!$D:$D,$A6,Unit_Conversions!$E:$E,"نعم"),IF(COUNTIFS(Unit_Conversions!$A:$A,$C6,Unit_Conversions!$B:$B,$D6,Unit_Conversions!$D:$D,"GENERAL",Unit_Conversions!$E:$E,"نعم",Unit_Conversions!$C:$C,">0")=1,SUMIFS(Unit_Conversions!$C:$C,Unit_Conversions!$A:$A,$C6,Unit_Conversions!$B:$B,$D6,Unit_Conversions!$D:$D,"GENERAL",Unit_Conversions!$E:$E,"نعم"),""))))) | F6: =IF($E6="","",IF(ISNUMBER($B6),$B6*$E6,"")) | G6: =IF(OR($A6="",$C6=""),"",IF($D6="صنف غير معرف","صنف غير معرف",IF($E6="","التحويل غير مسموح: معامل غير معرّف أو غير معتمد","")))
D7: =IF($A7="","",IF(COUNTIF(Items!$A:$A,$A7)=0,"صنف غير معرف",INDEX(Items!$D:$D,MATCH($A7,Items!$A:$A,0)))) | E7: =IF(OR($A7="",$C7=""),"",IF($D7="صنف غير معرف","",IF($C7=$D7,1,IF(COUNTIFS(Unit_Conversions!$A:$A,$C7,Unit_Conversions!$B:$B,$D7,Unit_Conversions!$D:$D,$A7,Unit_Conversions!$E:$E,"نعم",Unit_Conversions!$C:$C,">0")=1,SUMIFS(Unit_Conversions!$C:$C,Unit_Conversions!$A:$A,$C7,Unit_Conversions!$B:$B,$D7,Unit_Conversions!$D:$D,$A7,Unit_Conversions!$E:$E,"نعم"),IF(COUNTIFS(Unit_Conversions!$A:$A,$C7,Unit_Conversions!$B:$B,$D7,Unit_Conversions!$D:$D,"GENERAL",Unit_Conversions!$E:$E,"نعم",Unit_Conversions!$C:$C,">0")=1,SUMIFS(Unit_Conversions!$C:$C,Unit_Conversions!$A:$A,$C7,Unit_Conversions!$B:$B,$D7,Unit_Conversions!$D:$D,"GENERAL",Unit_Conversions!$E:$E,"نعم"),""))))) | F7: =IF($E7="","",IF(ISNUMBER($B7),$B7*$E7,"")) | G7: =IF(OR($A7="",$C7=""),"",IF($D7="صنف غير معرف","صنف غير معرف",IF($E7="","التحويل غير مسموح: معامل غير معرّف أو غير معتمد","")))
D8: =IF($A8="","",IF(COUNTIF(Items!$A:$A,$A8)=0,"صنف غير معرف",INDEX(Items!$D:$D,MATCH($A8,Items!$A:$A,0)))) | E8: =IF(OR($A8="",$C8=""),"",IF($D8="صنف غير معرف","",IF($C8=$D8,1,IF(COUNTIFS(Unit_Conversions!$A:$A,$C8,Unit_Conversions!$B:$B,$D8,Unit_Conversions!$D:$D,$A8,Unit_Conversions!$E:$E,"نعم",Unit_Conversions!$C:$C,">0")=1,SUMIFS(Unit_Conversions!$C:$C,Unit_Conversions!$A:$A,$C8,Unit_Conversions!$B:$B,$D8,Unit_Conversions!$D:$D,$A8,Unit_Conversions!$E:$E,"نعم"),IF(COUNTIFS(Unit_Conversions!$A:$A,$C8,Unit_Conversions!$B:$B,$D8,Unit_Conversions!$D:$D,"GENERAL",Unit_Conversions!$E:$E,"نعم",Unit_Conversions!$C:$C,">0")=1,SUMIFS(Unit_Conversions!$C:$C,Unit_Conversions!$A:$A,$C8,Unit_Conversions!$B:$B,$D8,Unit_Conversions!$D:$D,"GENERAL",Unit_Conversions!$E:$E,"نعم"),""))))) | F8: =IF($E8="","",IF(ISNUMBER($B8),$B8*$E8,"")) | G8: =IF(OR($A8="",$C8=""),"",IF($D8="صنف غير معرف","صنف غير معرف",IF($E8="","التحويل غير مسموح: معامل غير معرّف أو غير معتمد","")))
D9: =IF($A9="","",IF(COUNTIF(Items!$A:$A,$A9)=0,"صنف غير معرف",INDEX(Items!$D:$D,MATCH($A9,Items!$A:$A,0)))) | E9: =IF(OR($A9="",$C9=""),"",IF($D9="صنف غير معرف","",IF($C9=$D9,1,IF(COUNTIFS(Unit_Conversions!$A:$A,$C9,Unit_Conversions!$B:$B,$D9,Unit_Conversions!$D:$D,$A9,Unit_Conversions!$E:$E,"نعم",Unit_Conversions!$C:$C,">0")=1,SUMIFS(Unit_Conversions!$C:$C,Unit_Conversions!$A:$A,$C9,Unit_Conversions!$B:$B,$D9,Unit_Conversions!$D:$D,$A9,Unit_Conversions!$E:$E,"نعم"),IF(COUNTIFS(Unit_Conversions!$A:$A,$C9,Unit_Conversions!$B:$B,$D9,Unit_Conversions!$D:$D,"GENERAL",Unit_Conversions!$E:$E,"نعم",Unit_Conversions!$C:$C,">0")=1,SUMIFS(Unit_Conversions!$C:$C,Unit_Conversions!$A:$A,$C9,Unit_Conversions!$B:$B,$D9,Unit_Conversions!$D:$D,"GENERAL",Unit_Conversions!$E:$E,"نعم"),""))))) | F9: =IF($E9="","",IF(ISNUMBER($B9),$B9*$E9,"")) | G9: =IF(OR($A9="",$C9=""),"",IF($D9="صنف غير معرف","صنف غير معرف",IF($E9="","التحويل غير مسموح: معامل غير معرّف أو غير معتمد","")))
D10: =IF($A10="","",IF(COUNTIF(Items!$A:$A,$A10)=0,"صنف غير معرف",INDEX(Items!$D:$D,MATCH($A10,Items!$A:$A,0)))) | E10: =IF(OR($A10="",$C10=""),"",IF($D10="صنف غير معرف","",IF($C10=$D10,1,IF(COUNTIFS(Unit_Conversions!$A:$A,$C10,Unit_Conversions!$B:$B,$D10,Unit_Conversions!$D:$D,$A10,Unit_Conversions!$E:$E,"نعم",Unit_Conversions!$C:$C,">0")=1,SUMIFS(Unit_Conversions!$C:$C,Unit_Conversions!$A:$A,$C10,Unit_Conversions!$B:$B,$D10,Unit_Conversions!$D:$D,$A10,Unit_Conversions!$E:$E,"نعم"),IF(COUNTIFS(Unit_Conversions!$A:$A,$C10,Unit_Conversions!$B:$B,$D10,Unit_Conversions!$D:$D,"GENERAL",Unit_Conversions!$E:$E,"نعم",Unit_Conversions!$C:$C,">0")=1,SUMIFS(Unit_Conversions!$C:$C,Unit_Conversions!$A:$A,$C10,Unit_Conversions!$B:$B,$D10,Unit_Conversions!$D:$D,"GENERAL",Unit_Conversions!$E:$E,"نعم"),""))))) | F10: =IF($E10="","",IF(ISNUMBER($B10),$B10*$E10,"")) | G10: =IF(OR($A10="",$C10=""),"",IF($D10="صنف غير معرف","صنف غير معرف",IF($E10="","التحويل غير مسموح: معامل غير معرّف أو غير معتمد","")))
D11: =IF($A11="","",IF(COUNTIF(Items!$A:$A,$A11)=0,"صنف غير معرف",INDEX(Items!$D:$D,MATCH($A11,Items!$A:$A,0)))) | E11: =IF(OR($A11="",$C11=""),"",IF($D11="صنف غير معرف","",IF($C11=$D11,1,IF(COUNTIFS(Unit_Conversions!$A:$A,$C11,Unit_Conversions!$B:$B,$D11,Unit_Conversions!$D:$D,$A11,Unit_Conversions!$E:$E,"نعم",Unit_Conversions!$C:$C,">0")=1,SUMIFS(Unit_Conversions!$C:$C,Unit_Conversions!$A:$A,$C11,Unit_Conversions!$B:$B,$D11,Unit_Conversions!$D:$D,$A11,Unit_Conversions!$E:$E,"نعم"),IF(COUNTIFS(Unit_Conversions!$A:$A,$C11,Unit_Conversions!$B:$B,$D11,Unit_Conversions!$D:$D,"GENERAL",Unit_Conversions!$E:$E,"نعم",Unit_Conversions!$C:$C,">0")=1,SUMIFS(Unit_Conversions!$C:$C,Unit_Conversions!$A:$A,$C11,Unit_Conversions!$B:$B,$D11,Unit_Conversions!$D:$D,"GENERAL",Unit_Conversions!$E:$E,"نعم"),""))))) | F11: =IF($E11="","",IF(ISNUMBER($B11),$B11*$E11,"")) | G11: =IF(OR($A11="",$C11=""),"",IF($D11="صنف غير معرف","صنف غير معرف",IF($E11="","التحويل غير مسموح: معامل غير معرّف أو غير معتمد","")))
D12: =IF($A12="","",IF(COUNTIF(Items!$A:$A,$A12)=0,"صنف غير معرف",INDEX(Items!$D:$D,MATCH($A12,Items!$A:$A,0)))) | E12: =IF(OR($A12="",$C12=""),"",IF($D12="صنف غير معرف","",IF($C12=$D12,1,IF(COUNTIFS(Unit_Conversions!$A:$A,$C12,Unit_Conversions!$B:$B,$D12,Unit_Conversions!$D:$D,$A12,Unit_Conversions!$E:$E,"نعم",Unit_Conversions!$C:$C,">0")=1,SUMIFS(Unit_Conversions!$C:$C,Unit_Conversions!$A:$A,$C12,Unit_Conversions!$B:$B,$D12,Unit_Conversions!$D:$D,$A12,Unit_Conversions!$E:$E,"نعم"),IF(COUNTIFS(Unit_Conversions!$A:$A,$C12,Unit_Conversions!$B:$B,$D12,Unit_Conversions!$D:$D,"GENERAL",Unit_Conversions!$E:$E,"نعم",Unit_Conversions!$C:$C,">0")=1,SUMIFS(Unit_Conversions!$C:$C,Unit_Conversions!$A:$A,$C12,Unit_Conversions!$B:$B,$D12,Unit_Conversions!$D:$D,"GENERAL",Unit_Conversions!$E:$E,"نعم"),""))))) | F12: =IF($E12="","",IF(ISNUMBER($B12),$B12*$E12,"")) | G12: =IF(OR($A12="",$C12=""),"",IF($D12="صنف غير معرف","صنف غير معرف",IF($E12="","التحويل غير مسموح: معامل غير معرّف أو غير معتمد","")))
D13: =IF($A13="","",IF(COUNTIF(Items!$A:$A,$A13)=0,"صنف غير معرف",INDEX(Items!$D:$D,MATCH($A13,Items!$A:$A,0)))) | E13: =IF(OR($A13="",$C13=""),"",IF($D13="صنف غير معرف","",IF($C13=$D13,1,IF(COUNTIFS(Unit_Conversions!$A:$A,$C13,Unit_Conversions!$B:$B,$D13,Unit_Conversions!$D:$D,$A13,Unit_Conversions!$E:$E,"نعم",Unit_Conversions!$C:$C,">0")=1,SUMIFS(Unit_Conversions!$C:$C,Unit_Conversions!$A:$A,$C13,Unit_Conversions!$B:$B,$D13,Unit_Conversions!$D:$D,$A13,Unit_Conversions!$E:$E,"نعم"),IF(COUNTIFS(Unit_Conversions!$A:$A,$C13,Unit_Conversions!$B:$B,$D13,Unit_Conversions!$D:$D,"GENERAL",Unit_Conversions!$E:$E,"نعم",Unit_Conversions!$C:$C,">0")=1,SUMIFS(Unit_Conversions!$C:$C,Unit_Conversions!$A:$A,$C13,Unit_Conversions!$B:$B,$D13,Unit_Conversions!$D:$D,"GENERAL",Unit_Conversions!$E:$E,"نعم"),""))))) | F13: =IF($E13="","",IF(ISNUMBER($B13),$B13*$E13,"")) | G13: =IF(OR($A13="",$C13=""),"",IF($D13="صنف غير معرف","صنف غير معرف",IF($E13="","التحويل غير مسموح: معامل غير معرّف أو غير معتمد","")))
D14: =IF($A14="","",IF(COUNTIF(Items!$A:$A,$A14)=0,"صنف غير معرف",INDEX(Items!$D:$D,MATCH($A14,Items!$A:$A,0)))) | E14: =IF(OR($A14="",$C14=""),"",IF($D14="صنف غير معرف","",IF($C14=$D14,1,IF(COUNTIFS(Unit_Conversions!$A:$A,$C14,Unit_Conversions!$B:$B,$D14,Unit_Conversions!$D:$D,$A14,Unit_Conversions!$E:$E,"نعم",Unit_Conversions!$C:$C,">0")=1,SUMIFS(Unit_Conversions!$C:$C,Unit_Conversions!$A:$A,$C14,Unit_Conversions!$B:$B,$D14,Unit_Conversions!$D:$D,$A14,Unit_Conversions!$E:$E,"نعم"),IF(COUNTIFS(Unit_Conversions!$A:$A,$C14,Unit_Conversions!$B:$B,$D14,Unit_Conversions!$D:$D,"GENERAL",Unit_Conversions!$E:$E,"نعم",Unit_Conversions!$C:$C,">0")=1,SUMIFS(Unit_Conversions!$C:$C,Unit_Conversions!$A:$A,$C14,Unit_Conversions!$B:$B,$D14,Unit_Conversions!$D:$D,"GENERAL",Unit_Conversions!$E:$E,"نعم"),""))))) | F14: =IF($E14="","",IF(ISNUMBER($B14),$B14*$E14,"")) | G14: =IF(OR($A14="",$C14=""),"",IF($D14="صنف غير معرف","صنف غير معرف",IF($E14="","التحويل غير مسموح: معامل غير معرّف أو غير معتمد","")))
D15: =IF($A15="","",IF(COUNTIF(Items!$A:$A,$A15)=0,"صنف غير معرف",INDEX(Items!$D:$D,MATCH($A15,Items!$A:$A,0)))) | E15: =IF(OR($A15="",$C15=""),"",IF($D15="صنف غير معرف","",IF($C15=$D15,1,IF(COUNTIFS(Unit_Conversions!$A:$A,$C15,Unit_Conversions!$B:$B,$D15,Unit_Conversions!$D:$D,$A15,Unit_Conversions!$E:$E,"نعم",Unit_Conversions!$C:$C,">0")=1,SUMIFS(Unit_Conversions!$C:$C,Unit_Conversions!$A:$A,$C15,Unit_Conversions!$B:$B,$D15,Unit_Conversions!$D:$D,$A15,Unit_Conversions!$E:$E,"نعم"),IF(COUNTIFS(Unit_Conversions!$A:$A,$C15,Unit_Conversions!$B:$B,$D15,Unit_Conversions!$D:$D,"GENERAL",Unit_Conversions!$E:$E,"نعم",Unit_Conversions!$C:$C,">0")=1,SUMIFS(Unit_Conversions!$C:$C,Unit_Conversions!$A:$A,$C15,Unit_Conversions!$B:$B,$D15,Unit_Conversions!$D:$D,"GENERAL",Unit_Conversions!$E:$E,"نعم"),""))))) | F15: =IF($E15="","",IF(ISNUMBER($B15),$B15*$E15,"")) | G15: =IF(OR($A15="",$C15=""),"",IF($D15="صنف غير معرف","صنف غير معرف",IF($E15="","التحويل غير مسموح: معامل غير معرّف أو غير معتمد","")))
D16: =IF($A16="","",IF(COUNTIF(Items!$A:$A,$A16)=0,"صنف غير معرف",INDEX(Items!$D:$D,MATCH($A16,Items!$A:$A,0)))) | E16: =IF(OR($A16="",$C16=""),"",IF($D16="صنف غير معرف","",IF($C16=$D16,1,IF(COUNTIFS(Unit_Conversions!$A:$A,$C16,Unit_Conversions!$B:$B,$D16,Unit_Conversions!$D:$D,$A16,Unit_Conversions!$E:$E,"نعم",Unit_Conversions!$C:$C,">0")=1,SUMIFS(Unit_Conversions!$C:$C,Unit_Conversions!$A:$A,$C16,Unit_Conversions!$B:$B,$D16,Unit_Conversions!$D:$D,$A16,Unit_Conversions!$E:$E,"نعم"),IF(COUNTIFS(Unit_Conversions!$A:$A,$C16,Unit_Conversions!$B:$B,$D16,Unit_Conversions!$D:$D,"GENERAL",Unit_Conversions!$E:$E,"نعم",Unit_Conversions!$C:$C,">0")=1,SUMIFS(Unit_Conversions!$C:$C,Unit_Conversions!$A:$A,$C16,Unit_Conversions!$B:$B,$D16,Unit_Conversions!$D:$D,"GENERAL",Unit_Conversions!$E:$E,"نعم"),""))))) | F16: =IF($E16="","",IF(ISNUMBER($B16),$B16*$E16,"")) | G16: =IF(OR($A16="",$C16=""),"",IF($D16="صنف غير معرف","صنف غير معرف",IF($E16="","التحويل غير مسموح: معامل غير معرّف أو غير معتمد","")))
... D44: =IF($A44="","",IF(COUNTIF(Items!$A:$A,$A44)=0,"صنف غير معرف",INDEX(Items!$D:$D,MATCH($A44,Items!$A:$A,0)))) | E44: =IF(OR($A44="",$C44=""),"",IF($D44="صنف غير معرف","",IF($C44=$D44,1,IF(COUNTIFS(Unit_Conversions!$A:$A,$C44,Unit_Conversions!$B:$B,$D44,Unit_Conversions!$D:$D,$A44,Unit_Conversions!$E:$E,"نعم",Unit_Conversions!$C:$C,">0")=1,SUMIFS(Unit_Conversions!$C:$C,Unit_Conversions!$A:$A,$C44,Unit_Conversions!$B:$B,$D44,Unit_Conversions!$D:$D,$A44,Unit_Conversions!$E:$E,"نعم"),IF(COUNTIFS(Unit_Conversions!$A:$A,$C44,Unit_Conversions!$B:$B,$D44,Unit_Conversions!$D:$D,"GENERAL",Unit_Conversions!$E:$E,"نعم",Unit_Conversions!$C:$C,">0")=1,SUMIFS(Unit_Conversions!$C:$C,Unit_Conversions!$A:$A,$C44,Unit_Conversions!$B:$B,$D44,Unit_Conversions!$D:$D,"GENERAL",Unit_Conversions!$E:$E,"نعم"),""))))) | F44: =IF($E44="","",IF(ISNUMBER($B44),$B44*$E44,"")) | G44: =IF(OR($A44="",$C44=""),"",IF($D44="صنف غير معرف","صنف غير معرف",IF($E44="","التحويل غير مسموح: معامل غير معرّف أو غير معتمد","")))

Sheet Payment_Methods
A1: وسائل الدفع (Payment Methods)
A2: وسيلة (نقدي) تُرحَّل على خزينة الفرع آليًا. الوسائل الأخرى تُرحَّل على حساب المستحقات المحدد هنا حتى يتم التحصيل الفعلي.
A3: خلايا الإدخال | B3: معادلات (لا تعدّل)
A4: كود الوسيلة | B4: الاسم | C4: النوع | D4: حساب المستحقات/التسوية | E4: حساب العمولة/الرسوم | F4: نسبة العمولة المقدّرة | G4: أيام التسوية المتوقعة | H4: نشط | I4: ملاحظات | J4: اسم حساب التسوية | K4: فحص | L4: رصيد المستحقات | M4: آخر تسوية | N4: تسوية متأخرة؟ | O4: موعد التسوية المتوقع
A5: CASH | B5: نقدي (كاش) | C5: نقدي | F5: 0 | G5: 0 | H5: نعم | J5: =IF($D5="","",IFERROR(INDEX(COA!$B:$B,MATCH($D5,COA!$A:$A,0)),"حساب غير موجود")) | K5: =IF($A5="","",IF(COUNTIF($A:$A,$A5)>1,"كود مكرر",IF(AND($C5<>"نقدي",COUNTIFS(COA!$A:$A,$D5,COA!$R:$R,1)<>1),"حساب التسوية غير صالح",IF(AND($C5="منصة",$E5=""),"المنصة تحتاج حساب عمولة","")))) | L5: =IF($A5="","",IF($C5="نقدي",0,(SUMIFS(GL_Journal!$S:$S,GL_Journal!$G:$G,$D5,GL_Journal!$D:$D,"<="&S_To)-SUMIFS(GL_Journal!$T:$T,GL_Journal!$G:$G,$D5,GL_Journal!$D:$D,"<="&S_To)))) | M5: =IF($A5="","",IF(COUNTIFS(Platform_Settlements!$C:$C,$A5,Platform_Settlements!$AA:$AA,1)=0,"",_xlfn.MAXIFS(Platform_Settlements!$B:$B,Platform_Settlements!$C:$C,$A5,Platform_Settlements!$AA:$AA,1))) | N5: =IF($A5="","",IF(AND(OR($C5="منصة",$C5="بطاقة"),$L5>S_Tol),IF(S_To-IF($M5="",_xlfn.MINIFS(GL_Journal!$D:$D,GL_Journal!$G:$G,$D5,GL_Journal!$R:$R,1),$M5)>S_PlatDays,1,0),0)) | O5: =IF($A5="","",IF(OR($M5="",NOT(ISNUMBER($G5))),"",$M5+$G5))
A6: CARD | B6: بطاقات ائتمان/خصم (POS) | C6: بطاقة | D6: 1302 | E6: 6702 | F6: 0.015 | G6: 2 | H6: نعم | J6: =IF($D6="","",IFERROR(INDEX(COA!$B:$B,MATCH($D6,COA!$A:$A,0)),"حساب غير موجود")) | K6: =IF($A6="","",IF(COUNTIF($A:$A,$A6)>1,"كود مكرر",IF(AND($C6<>"نقدي",COUNTIFS(COA!$A:$A,$D6,COA!$R:$R,1)<>1),"حساب التسوية غير صالح",IF(AND($C6="منصة",$E6=""),"المنصة تحتاج حساب عمولة","")))) | L6: =IF($A6="","",IF($C6="نقدي",0,(SUMIFS(GL_Journal!$S:$S,GL_Journal!$G:$G,$D6,GL_Journal!$D:$D,"<="&S_To)-SUMIFS(GL_Journal!$T:$T,GL_Journal!$G:$G,$D6,GL_Journal!$D:$D,"<="&S_To)))) | M6: =IF($A6="","",IF(COUNTIFS(Platform_Settlements!$C:$C,$A6,Platform_Settlements!$AA:$AA,1)=0,"",_xlfn.MAXIFS(Platform_Settlements!$B:$B,Platform_Settlements!$C:$C,$A6,Platform_Settlements!$AA:$AA,1))) | N6: =IF($A6="","",IF(AND(OR($C6="منصة",$C6="بطاقة"),$L6>S_Tol),IF(S_To-IF($M6="",_xlfn.MINIFS(GL_Journal!$D:$D,GL_Journal!$G:$G,$D6,GL_Journal!$R:$R,1),$M6)>S_PlatDays,1,0),0)) | O6: =IF($A6="","",IF(OR($M6="",NOT(ISNUMBER($G6))),"",$M6+$G6))
A7: TLB | B7: منصة طلبات | C7: منصة | D7: 1303 | E7: 6701 | F7: 0.18 | G7: 7 | H7: نعم | J7: =IF($D7="","",IFERROR(INDEX(COA!$B:$B,MATCH($D7,COA!$A:$A,0)),"حساب غير موجود")) | K7: =IF($A7="","",IF(COUNTIF($A:$A,$A7)>1,"كود مكرر",IF(AND($C7<>"نقدي",COUNTIFS(COA!$A:$A,$D7,COA!$R:$R,1)<>1),"حساب التسوية غير صالح",IF(AND($C7="منصة",$E7=""),"المنصة تحتاج حساب عمولة","")))) | L7: =IF($A7="","",IF($C7="نقدي",0,(SUMIFS(GL_Journal!$S:$S,GL_Journal!$G:$G,$D7,GL_Journal!$D:$D,"<="&S_To)-SUMIFS(GL_Journal!$T:$T,GL_Journal!$G:$G,$D7,GL_Journal!$D:$D,"<="&S_To)))) | M7: =IF($A7="","",IF(COUNTIFS(Platform_Settlements!$C:$C,$A7,Platform_Settlements!$AA:$AA,1)=0,"",_xlfn.MAXIFS(Platform_Settlements!$B:$B,Platform_Settlements!$C:$C,$A7,Platform_Settlements!$AA:$AA,1))) | N7: =IF($A7="","",IF(AND(OR($C7="منصة",$C7="بطاقة"),$L7>S_Tol),IF(S_To-IF($M7="",_xlfn.MINIFS(GL_Journal!$D:$D,GL_Journal!$G:$G,$D7,GL_Journal!$R:$R,1),$M7)>S_PlatDays,1,0),0)) | O7: =IF($A7="","",IF(OR($M7="",NOT(ISNUMBER($G7))),"",$M7+$G7))
A8: DLV2 | B8: منصة توصيل أخرى | C8: منصة | D8: 1304 | E8: 6701 | F8: 0.2 | G8: 7 | H8: نعم | J8: =IF($D8="","",IFERROR(INDEX(COA!$B:$B,MATCH($D8,COA!$A:$A,0)),"حساب غير موجود")) | K8: =IF($A8="","",IF(COUNTIF($A:$A,$A8)>1,"كود مكرر",IF(AND($C8<>"نقدي",COUNTIFS(COA!$A:$A,$D8,COA!$R:$R,1)<>1),"حساب التسوية غير صالح",IF(AND($C8="منصة",$E8=""),"المنصة تحتاج حساب عمولة","")))) | L8: =IF($A8="","",IF($C8="نقدي",0,(SUMIFS(GL_Journal!$S:$S,GL_Journal!$G:$G,$D8,GL_Journal!$D:$D,"<="&S_To)-SUMIFS(GL_Journal!$T:$T,GL_Journal!$G:$G,$D8,GL_Journal!$D:$D,"<="&S_To)))) | M8: =IF($A8="","",IF(COUNTIFS(Platform_Settlements!$C:$C,$A8,Platform_Settlements!$AA:$AA,1)=0,"",_xlfn.MAXIFS(Platform_Settlements!$B:$B,Platform_Settlements!$C:$C,$A8,Platform_Settlements!$AA:$AA,1))) | N8: =IF($A8="","",IF(AND(OR($C8="منصة",$C8="بطاقة"),$L8>S_Tol),IF(S_To-IF($M8="",_xlfn.MINIFS(GL_Journal!$D:$D,GL_Journal!$G:$G,$D8,GL_Journal!$R:$R,1),$M8)>S_PlatDays,1,0),0)) | O8: =IF($A8="","",IF(OR($M8="",NOT(ISNUMBER($G8))),"",$M8+$G8))
A9: INSTA | B9: تحويل إلكتروني / محفظة | C9: تحويل | D9: 1203 | E9: 6702 | F9: 0 | G9: 0 | H9: نعم | J9: =IF($D9="","",IFERROR(INDEX(COA!$B:$B,MATCH($D9,COA!$A:$A,0)),"حساب غير موجود")) | K9: =IF($A9="","",IF(COUNTIF($A:$A,$A9)>1,"كود مكرر",IF(AND($C9<>"نقدي",COUNTIFS(COA!$A:$A,$D9,COA!$R:$R,1)<>1),"حساب التسوية غير صالح",IF(AND($C9="منصة",$E9=""),"المنصة تحتاج حساب عمولة","")))) | L9: =IF($A9="","",IF($C9="نقدي",0,(SUMIFS(GL_Journal!$S:$S,GL_Journal!$G:$G,$D9,GL_Journal!$D:$D,"<="&S_To)-SUMIFS(GL_Journal!$T:$T,GL_Journal!$G:$G,$D9,GL_Journal!$D:$D,"<="&S_To)))) | M9: =IF($A9="","",IF(COUNTIFS(Platform_Settlements!$C:$C,$A9,Platform_Settlements!$AA:$AA,1)=0,"",_xlfn.MAXIFS(Platform_Settlements!$B:$B,Platform_Settlements!$C:$C,$A9,Platform_Settlements!$AA:$AA,1))) | N9: =IF($A9="","",IF(AND(OR($C9="منصة",$C9="بطاقة"),$L9>S_Tol),IF(S_To-IF($M9="",_xlfn.MINIFS(GL_Journal!$D:$D,GL_Journal!$G:$G,$D9,GL_Journal!$R:$R,1),$M9)>S_PlatDays,1,0),0)) | O9: =IF($A9="","",IF(OR($M9="",NOT(ISNUMBER($G9))),"",$M9+$G9))
J10: =IF($D10="","",IFERROR(INDEX(COA!$B:$B,MATCH($D10,COA!$A:$A,0)),"حساب غير موجود")) | K10: =IF($A10="","",IF(COUNTIF($A:$A,$A10)>1,"كود مكرر",IF(AND($C10<>"نقدي",COUNTIFS(COA!$A:$A,$D10,COA!$R:$R,1)<>1),"حساب التسوية غير صالح",IF(AND($C10="منصة",$E10=""),"المنصة تحتاج حساب عمولة","")))) | L10: =IF($A10="","",IF($C10="نقدي",0,(SUMIFS(GL_Journal!$S:$S,GL_Journal!$G:$G,$D10,GL_Journal!$D:$D,"<="&S_To)-SUMIFS(GL_Journal!$T:$T,GL_Journal!$G:$G,$D10,GL_Journal!$D:$D,"<="&S_To)))) | M10: =IF($A10="","",IF(COUNTIFS(Platform_Settlements!$C:$C,$A10,Platform_Settlements!$AA:$AA,1)=0,"",_xlfn.MAXIFS(Platform_Settlements!$B:$B,Platform_Settlements!$C:$C,$A10,Platform_Settlements!$AA:$AA,1))) | N10: =IF($A10="","",IF(AND(OR($C10="منصة",$C10="بطاقة"),$L10>S_Tol),IF(S_To-IF($M10="",_xlfn.MINIFS(GL_Journal!$D:$D,GL_Journal!$G:$G,$D10,GL_Journal!$R:$R,1),$M10)>S_PlatDays,1,0),0)) | O10: =IF($A10="","",IF(OR($M10="",NOT(ISNUMBER($G10))),"",$M10+$G10))
J11: =IF($D11="","",IFERROR(INDEX(COA!$B:$B,MATCH($D11,COA!$A:$A,0)),"حساب غير موجود")) | K11: =IF($A11="","",IF(COUNTIF($A:$A,$A11)>1,"كود مكرر",IF(AND($C11<>"نقدي",COUNTIFS(COA!$A:$A,$D11,COA!$R:$R,1)<>1),"حساب التسوية غير صالح",IF(AND($C11="منصة",$E11=""),"المنصة تحتاج حساب عمولة","")))) | L11: =IF($A11="","",IF($C11="نقدي",0,(SUMIFS(GL_Journal!$S:$S,GL_Journal!$G:$G,$D11,GL_Journal!$D:$D,"<="&S_To)-SUMIFS(GL_Journal!$T:$T,GL_Journal!$G:$G,$D11,GL_Journal!$D:$D,"<="&S_To)))) | M11: =IF($A11="","",IF(COUNTIFS(Platform_Settlements!$C:$C,$A11,Platform_Settlements!$AA:$AA,1)=0,"",_xlfn.MAXIFS(Platform_Settlements!$B:$B,Platform_Settlements!$C:$C,$A11,Platform_Settlements!$AA:$AA,1))) | N11: =IF($A11="","",IF(AND(OR($C11="منصة",$C11="بطاقة"),$L11>S_Tol),IF(S_To-IF($M11="",_xlfn.MINIFS(GL_Journal!$D:$D,GL_Journal!$G:$G,$D11,GL_Journal!$R:$R,1),$M11)>S_PlatDays,1,0),0)) | O11: =IF($A11="","",IF(OR($M11="",NOT(ISNUMBER($G11))),"",$M11+$G11))
J12: =IF($D12="","",IFERROR(INDEX(COA!$B:$B,MATCH($D12,COA!$A:$A,0)),"حساب غير موجود")) | K12: =IF($A12="","",IF(COUNTIF($A:$A,$A12)>1,"كود مكرر",IF(AND($C12<>"نقدي",COUNTIFS(COA!$A:$A,$D12,COA!$R:$R,1)<>1),"حساب التسوية غير صالح",IF(AND($C12="منصة",$E12=""),"المنصة تحتاج حساب عمولة","")))) | L12: =IF($A12="","",IF($C12="نقدي",0,(SUMIFS(GL_Journal!$S:$S,GL_Journal!$G:$G,$D12,GL_Journal!$D:$D,"<="&S_To)-SUMIFS(GL_Journal!$T:$T,GL_Journal!$G:$G,$D12,GL_Journal!$D:$D,"<="&S_To)))) | M12: =IF($A12="","",IF(COUNTIFS(Platform_Settlements!$C:$C,$A12,Platform_Settlements!$AA:$AA,1)=0,"",_xlfn.MAXIFS(Platform_Settlements!$B:$B,Platform_Settlements!$C:$C,$A12,Platform_Settlements!$AA:$AA,1))) | N12: =IF($A12="","",IF(AND(OR($C12="منصة",$C12="بطاقة"),$L12>S_Tol),IF(S_To-IF($M12="",_xlfn.MINIFS(GL_Journal!$D:$D,GL_Journal!$G:$G,$D12,GL_Journal!$R:$R,1),$M12)>S_PlatDays,1,0),0)) | O12: =IF($A12="","",IF(OR($M12="",NOT(ISNUMBER($G12))),"",$M12+$G12))
J13: =IF($D13="","",IFERROR(INDEX(COA!$B:$B,MATCH($D13,COA!$A:$A,0)),"حساب غير موجود")) | K13: =IF($A13="","",IF(COUNTIF($A:$A,$A13)>1,"كود مكرر",IF(AND($C13<>"نقدي",COUNTIFS(COA!$A:$A,$D13,COA!$R:$R,1)<>1),"حساب التسوية غير صالح",IF(AND($C13="منصة",$E13=""),"المنصة تحتاج حساب عمولة","")))) | L13: =IF($A13="","",IF($C13="نقدي",0,(SUMIFS(GL_Journal!$S:$S,GL_Journal!$G:$G,$D13,GL_Journal!$D:$D,"<="&S_To)-SUMIFS(GL_Journal!$T:$T,GL_Journal!$G:$G,$D13,GL_Journal!$D:$D,"<="&S_To)))) | M13: =IF($A13="","",IF(COUNTIFS(Platform_Settlements!$C:$C,$A13,Platform_Settlements!$AA:$AA,1)=0,"",_xlfn.MAXIFS(Platform_Settlements!$B:$B,Platform_Settlements!$C:$C,$A13,Platform_Settlements!$AA:$AA,1))) | N13: =IF($A13="","",IF(AND(OR($C13="منصة",$C13="بطاقة"),$L13>S_Tol),IF(S_To-IF($M13="",_xlfn.MINIFS(GL_Journal!$D:$D,GL_Journal!$G:$G,$D13,GL_Journal!$R:$R,1),$M13)>S_PlatDays,1,0),0)) | O13: =IF($A13="","",IF(OR($M13="",NOT(ISNUMBER($G13))),"",$M13+$G13))
J14: =IF($D14="","",IFERROR(INDEX(COA!$B:$B,MATCH($D14,COA!$A:$A,0)),"حساب غير موجود")) | K14: =IF($A14="","",IF(COUNTIF($A:$A,$A14)>1,"كود مكرر",IF(AND($C14<>"نقدي",COUNTIFS(COA!$A:$A,$D14,COA!$R:$R,1)<>1),"حساب التسوية غير صالح",IF(AND($C14="منصة",$E14=""),"المنصة تحتاج حساب عمولة","")))) | L14: =IF($A14="","",IF($C14="نقدي",0,(SUMIFS(GL_Journal!$S:$S,GL_Journal!$G:$G,$D14,GL_Journal!$D:$D,"<="&S_To)-SUMIFS(GL_Journal!$T:$T,GL_Journal!$G:$G,$D14,GL_Journal!$D:$D,"<="&S_To)))) | M14: =IF($A14="","",IF(COUNTIFS(Platform_Settlements!$C:$C,$A14,Platform_Settlements!$AA:$AA,1)=0,"",_xlfn.MAXIFS(Platform_Settlements!$B:$B,Platform_Settlements!$C:$C,$A14,Platform_Settlements!$AA:$AA,1))) | N14: =IF($A14="","",IF(AND(OR($C14="منصة",$C14="بطاقة"),$L14>S_Tol),IF(S_To-IF($M14="",_xlfn.MINIFS(GL_Journal!$D:$D,GL_Journal!$G:$G,$D14,GL_Journal!$R:$R,1),$M14)>S_PlatDays,1,0),0)) | O14: =IF($A14="","",IF(OR($M14="",NOT(ISNUMBER($G14))),"",$M14+$G14))
J15: =IF($D15="","",IFERROR(INDEX(COA!$B:$B,MATCH($D15,COA!$A:$A,0)),"حساب غير موجود")) | K15: =IF($A15="","",IF(COUNTIF($A:$A,$A15)>1,"كود مكرر",IF(AND($C15<>"نقدي",COUNTIFS(COA!$A:$A,$D15,COA!$R:$R,1)<>1),"حساب التسوية غير صالح",IF(AND($C15="منصة",$E15=""),"المنصة تحتاج حساب عمولة","")))) | L15: =IF($A15="","",IF($C15="نقدي",0,(SUMIFS(GL_Journal!$S:$S,GL_Journal!$G:$G,$D15,GL_Journal!$D:$D,"<="&S_To)-SUMIFS(GL_Journal!$T:$T,GL_Journal!$G:$G,$D15,GL_Journal!$D:$D,"<="&S_To)))) | M15: =IF($A15="","",IF(COUNTIFS(Platform_Settlements!$C:$C,$A15,Platform_Settlements!$AA:$AA,1)=0,"",_xlfn.MAXIFS(Platform_Settlements!$B:$B,Platform_Settlements!$C:$C,$A15,Platform_Settlements!$AA:$AA,1))) | N15: =IF($A15="","",IF(AND(OR($C15="منصة",$C15="بطاقة"),$L15>S_Tol),IF(S_To-IF($M15="",_xlfn.MINIFS(GL_Journal!$D:$D,GL_Journal!$G:$G,$D15,GL_Journal!$R:$R,1),$M15)>S_PlatDays,1,0),0)) | O15: =IF($A15="","",IF(OR($M15="",NOT(ISNUMBER($G15))),"",$M15+$G15))
J16: =IF($D16="","",IFERROR(INDEX(COA!$B:$B,MATCH($D16,COA!$A:$A,0)),"حساب غير موجود")) | K16: =IF($A16="","",IF(COUNTIF($A:$A,$A16)>1,"كود مكرر",IF(AND($C16<>"نقدي",COUNTIFS(COA!$A:$A,$D16,COA!$R:$R,1)<>1),"حساب التسوية غير صالح",IF(AND($C16="منصة",$E16=""),"المنصة تحتاج حساب عمولة","")))) | L16: =IF($A16="","",IF($C16="نقدي",0,(SUMIFS(GL_Journal!$S:$S,GL_Journal!$G:$G,$D16,GL_Journal!$D:$D,"<="&S_To)-SUMIFS(GL_Journal!$T:$T,GL_Journal!$G:$G,$D16,GL_Journal!$D:$D,"<="&S_To)))) | M16: =IF($A16="","",IF(COUNTIFS(Platform_Settlements!$C:$C,$A16,Platform_Settlements!$AA:$AA,1)=0,"",_xlfn.MAXIFS(Platform_Settlements!$B:$B,Platform_Settlements!$C:$C,$A16,Platform_Settlements!$AA:$AA,1))) | N16: =IF($A16="","",IF(AND(OR($C16="منصة",$C16="بطاقة"),$L16>S_Tol),IF(S_To-IF($M16="",_xlfn.MINIFS(GL_Journal!$D:$D,GL_Journal!$G:$G,$D16,GL_Journal!$R:$R,1),$M16)>S_PlatDays,1,0),0)) | O16: =IF($A16="","",IF(OR($M16="",NOT(ISNUMBER($G16))),"",$M16+$G16))
J17: =IF($D17="","",IFERROR(INDEX(COA!$B:$B,MATCH($D17,COA!$A:$A,0)),"حساب غير موجود")) | K17: =IF($A17="","",IF(COUNTIF($A:$A,$A17)>1,"كود مكرر",IF(AND($C17<>"نقدي",COUNTIFS(COA!$A:$A,$D17,COA!$R:$R,1)<>1),"حساب التسوية غير صالح",IF(AND($C17="منصة",$E17=""),"المنصة تحتاج حساب عمولة","")))) | L17: =IF($A17="","",IF($C17="نقدي",0,(SUMIFS(GL_Journal!$S:$S,GL_Journal!$G:$G,$D17,GL_Journal!$D:$D,"<="&S_To)-SUMIFS(GL_Journal!$T:$T,GL_Journal!$G:$G,$D17,GL_Journal!$D:$D,"<="&S_To)))) | M17: =IF($A17="","",IF(COUNTIFS(Platform_Settlements!$C:$C,$A17,Platform_Settlements!$AA:$AA,1)=0,"",_xlfn.MAXIFS(Platform_Settlements!$B:$B,Platform_Settlements!$C:$C,$A17,Platform_Settlements!$AA:$AA,1))) | N17: =IF($A17="","",IF(AND(OR($C17="منصة",$C17="بطاقة"),$L17>S_Tol),IF(S_To-IF($M17="",_xlfn.MINIFS(GL_Journal!$D:$D,GL_Journal!$G:$G,$D17,GL_Journal!$R:$R,1),$M17)>S_PlatDays,1,0),0)) | O17: =IF($A17="","",IF(OR($M17="",NOT(ISNUMBER($G17))),"",$M17+$G17))
J18: =IF($D18="","",IFERROR(INDEX(COA!$B:$B,MATCH($D18,COA!$A:$A,0)),"حساب غير موجود")) | K18: =IF($A18="","",IF(COUNTIF($A:$A,$A18)>1,"كود مكرر",IF(AND($C18<>"نقدي",COUNTIFS(COA!$A:$A,$D18,COA!$R:$R,1)<>1),"حساب التسوية غير صالح",IF(AND($C18="منصة",$E18=""),"المنصة تحتاج حساب عمولة","")))) | L18: =IF($A18="","",IF($C18="نقدي",0,(SUMIFS(GL_Journal!$S:$S,GL_Journal!$G:$G,$D18,GL_Journal!$D:$D,"<="&S_To)-SUMIFS(GL_Journal!$T:$T,GL_Journal!$G:$G,$D18,GL_Journal!$D:$D,"<="&S_To)))) | M18: =IF($A18="","",IF(COUNTIFS(Platform_Settlements!$C:$C,$A18,Platform_Settlements!$AA:$AA,1)=0,"",_xlfn.MAXIFS(Platform_Settlements!$B:$B,Platform_Settlements!$C:$C,$A18,Platform_Settlements!$AA:$AA,1))) | N18: =IF($A18="","",IF(AND(OR($C18="منصة",$C18="بطاقة"),$L18>S_Tol),IF(S_To-IF($M18="",_xlfn.MINIFS(GL_Journal!$D:$D,GL_Journal!$G:$G,$D18,GL_Journal!$R:$R,1),$M18)>S_PlatDays,1,0),0)) | O18: =IF($A18="","",IF(OR($M18="",NOT(ISNUMBER($G18))),"",$M18+$G18))
J19: =IF($D19="","",IFERROR(INDEX(COA!$B:$B,MATCH($D19,COA!$A:$A,0)),"حساب غير موجود")) | K19: =IF($A19="","",IF(COUNTIF($A:$A,$A19)>1,"كود مكرر",IF(AND($C19<>"نقدي",COUNTIFS(COA!$A:$A,$D19,COA!$R:$R,1)<>1),"حساب التسوية غير صالح",IF(AND($C19="منصة",$E19=""),"المنصة تحتاج حساب عمولة","")))) | L19: =IF($A19="","",IF($C19="نقدي",0,(SUMIFS(GL_Journal!$S:$S,GL_Journal!$G:$G,$D19,GL_Journal!$D:$D,"<="&S_To)-SUMIFS(GL_Journal!$T:$T,GL_Journal!$G:$G,$D19,GL_Journal!$D:$D,"<="&S_To)))) | M19: =IF($A19="","",IF(COUNTIFS(Platform_Settlements!$C:$C,$A19,Platform_Settlements!$AA:$AA,1)=0,"",_xlfn.MAXIFS(Platform_Settlements!$B:$B,Platform_Settlements!$C:$C,$A19,Platform_Settlements!$AA:$AA,1))) | N19: =IF($A19="","",IF(AND(OR($C19="منصة",$C19="بطاقة"),$L19>S_Tol),IF(S_To-IF($M19="",_xlfn.MINIFS(GL_Journal!$D:$D,GL_Journal!$G:$G,$D19,GL_Journal!$R:$R,1),$M19)>S_PlatDays,1,0),0)) | O19: =IF($A19="","",IF(OR($M19="",NOT(ISNUMBER($G19))),"",$M19+$G19))

Sheet Cost_Centers
A1: مراكز التكلفة (Cost Centers)
A2: مراكز التكلفة تتيح تحليل المصروفات حسب الوظيفة بعيدًا عن الفرع.
A3: خلايا الإدخال | B3: معادلات (لا تعدّل)
A4: كود المركز | B4: الاسم | C4: نشط | D4: ملاحظات | E4: فحص
A5: CC00 | B5: عام / غير موزع | C5: نعم | E5: =IF($A5="","",IF(COUNTIF($A:$A,$A5)>1,"كود مكرر",""))
A6: CC10 | B6: تشغيل الفروع | C6: نعم | E6: =IF($A6="","",IF(COUNTIF($A:$A,$A6)>1,"كود مكرر",""))
A7: CC20 | B7: الإنتاج - سنتر كيتشن | C7: نعم | E7: =IF($A7="","",IF(COUNTIF($A:$A,$A7)>1,"كود مكرر",""))
A8: CC30 | B8: التوصيل | C8: نعم | E8: =IF($A8="","",IF(COUNTIF($A:$A,$A8)>1,"كود مكرر",""))
A9: CC40 | B9: التسويق | C9: نعم | E9: =IF($A9="","",IF(COUNTIF($A:$A,$A9)>1,"كود مكرر",""))
A10: CC50 | B10: الإدارة والمحاسبة | C10: نعم | E10: =IF($A10="","",IF(COUNTIF($A:$A,$A10)>1,"كود مكرر",""))
A11: CC60 | B11: الصيانة | C11: نعم | E11: =IF($A11="","",IF(COUNTIF($A:$A,$A11)>1,"كود مكرر",""))
A12: CC70 | B12: المخازن | C12: نعم | E12: =IF($A12="","",IF(COUNTIF($A:$A,$A12)>1,"كود مكرر",""))
E13: =IF($A13="","",IF(COUNTIF($A:$A,$A13)>1,"كود مكرر",""))
E14: =IF($A14="","",IF(COUNTIF($A:$A,$A14)>1,"كود مكرر",""))
E15: =IF($A15="","",IF(COUNTIF($A:$A,$A15)>1,"كود مكرر",""))
E16: =IF($A16="","",IF(COUNTIF($A:$A,$A16)>1,"كود مكرر",""))
E17: =IF($A17="","",IF(COUNTIF($A:$A,$A17)>1,"كود مكرر",""))
E18: =IF($A18="","",IF(COUNTIF($A:$A,$A18)>1,"كود مكرر",""))
E19: =IF($A19="","",IF(COUNTIF($A:$A,$A19)>1,"كود مكرر",""))
E20: =IF($A20="","",IF(COUNTIF($A:$A,$A20)>1,"كود مكرر",""))
E21: =IF($A21="","",IF(COUNTIF($A:$A,$A21)>1,"كود مكرر",""))
E22: =IF($A22="","",IF(COUNTIF($A:$A,$A22)>1,"كود مكرر",""))
E23: =IF($A23="","",IF(COUNTIF($A:$A,$A23)>1,"كود مكرر",""))
E24: =IF($A24="","",IF(COUNTIF($A:$A,$A24)>1,"كود مكرر",""))
... E34: =IF($A34="","",IF(COUNTIF($A:$A,$A34)>1,"كود مكرر",""))

Sheet Tax_Settings
A1: إعدادات الضرائب (Tax Settings) - إن انطبقت
A2: تنبيه: لم تتم مراجعة المعالجة الضريبية مع محاسب قانوني مصري. الافتراضي في النسخة الأولى = ضريبة القيمة المضافة غير مفعّلة.
B4: البند | C4: القيمة | D4: ملاحظات
B5: تفعيل ضريبة القيمة المضافة؟ | C5: لا | D5: إذا (نعم): تعتبر مبالغ المبيعات والمشتريات شاملة للضريبة وتفصل المعادلات الضريبة تلقائيًا في قيد المبيعات.
B6: نسبة ضريبة القيمة المضافة | C6: 0.14 | D6: النسبة القياسية المفترضة 14% - تحقق منها مع المحاسب القانوني
B7: معامل الفصل (آلي) | C7: =IF(S_VATOn="نعم",1+S_VATRate,1) | D7: قيمة الإيراد بدون ضريبة = المبلغ الشامل ÷ هذا المعامل
B8: حساب ضريبة المخرجات | C8: =ACC_VAT_OUT | D8: من خريطة الحسابات (ورقة Posting_Rules)
B9: حساب ضريبة المدخلات | C9: =ACC_VAT_IN | D9: من خريطة الحسابات
B11: ملاحظات ضريبية (للمراجعة مع المحاسب القانوني):
B12: 1) تسجيل ضريبة المدخلات في المشتريات والمصروفات يتم فقط عند وجود فاتورة ضريبية صحيحة.
B13: 2) النظام لا يُعد إقرارات ضريبية ولا يُغني عن مراجعة قانونية؛ هو يفصل حسابات الضريبة فقط لتسهيل الإعداد.
B14: 3) الضرائب الأخرى (دمغة، جدول، دخل) غير مفعلة في النسخة الأولى؛ استخدم حساب 2302 يدويًا عبر قيد يدوي.

Sheet Doc_Numbering
A1: ترقيم المستندات (Document Numbering)
A2: صيغة الرقم: البادئة-كود الموقع-تسلسل 4 خانات (مثال SAL-BR01-0001). التسلسل مطبوع مسبقًا على النماذج الورقية. السجل المركزي Doc_Register يمنع التكرار.
A3: خلايا الإدخال | B3: معادلات (لا تعدّل)
A4: البادئة | B4: نوع المستند | C4: النموذج الورقي | D4: ورقة التسجيل | E4: المرحلة | F4: مثال | G4: عدد المستخدم في النظام | H4: الرقم التالي المقترح (للموقع في الخلية)
A5: SAL | B5: تقرير مبيعات يومي | C5: نموذج 15 | D5: Sales_Daily | E5: 1 | F5: SAL-BR01-0001 | G5: =IF($A5="","",COUNTIF(Doc_Register!$A:$A,$A5&"-*")) | H5: =IF($A5="","",$A5&"-[الموقع]-"&TEXT($G5+1,"0000"))
A6: PLT | B6: كشف تسوية منصة/بطاقات | C6: نموذج 16 | D6: Platform_Settlements | E6: 1 | F6: PLT-BR01-0001 | G6: =IF($A6="","",COUNTIF(Doc_Register!$A:$A,$A6&"-*")) | H6: =IF($A6="","",$A6&"-[الموقع]-"&TEXT($G6+1,"0000"))
A7: RCV | B7: سند قبض | C7: نموذج 11 | D7: Cash_Vouchers | E7: 1 | F7: RCV-BR01-0001 | G7: =IF($A7="","",COUNTIF(Doc_Register!$A:$A,$A7&"-*")) | H7: =IF($A7="","",$A7&"-[الموقع]-"&TEXT($G7+1,"0000"))
A8: PAY | B8: سند صرف | C8: نموذج 12 | D8: Cash_Vouchers | E8: 1 | F8: PAY-BR01-0001 | G8: =IF($A8="","",COUNTIF(Doc_Register!$A:$A,$A8&"-*")) | H8: =IF($A8="","",$A8&"-[الموقع]-"&TEXT($G8+1,"0000"))
A9: TRF | B9: إذن تحويل بين الخزائن/إيداع/سحب | C9: نموذج 13 | D9: Cash_Vouchers | E9: 1 | F9: TRF-BR01-0001 | G9: =IF($A9="","",COUNTIF(Doc_Register!$A:$A,$A9&"-*")) | H9: =IF($A9="","",$A9&"-[الموقع]-"&TEXT($G9+1,"0000"))
A10: ADJ | B10: تسوية عجز/زيادة خزينة | C10: نموذج 30 | D10: Cash_Vouchers | E10: 1 | F10: ADJ-BR01-0001 | G10: =IF($A10="","",COUNTIF(Doc_Register!$A:$A,$A10&"-*")) | H10: =IF($A10="","",$A10&"-[الموقع]-"&TEXT($G10+1,"0000"))
A11: EXP | B11: نموذج مصروفات | C11: نموذج 17 | D11: Expenses | E11: 1 | F11: EXP-BR01-0001 | G11: =IF($A11="","",COUNTIF(Doc_Register!$A:$A,$A11&"-*")) | H11: =IF($A11="","",$A11&"-[الموقع]-"&TEXT($G11+1,"0000"))
A12: SINV | B12: تسجيل فاتورة مورد/إشعار | C12: نموذج 20 (مرفق) | D12: Supplier_Invoices | E12: 1 | F12: SINV-BR01-0001 | G12: =IF($A12="","",COUNTIF(Doc_Register!$A:$A,$A12&"-*")) | H12: =IF($A12="","",$A12&"-[الموقع]-"&TEXT($G12+1,"0000"))
A13: SPAY | B13: دفعة مورد | C13: نموذج 12 | D13: Supplier_Payments | E13: 1 | F13: SPAY-BR01-0001 | G13: =IF($A13="","",COUNTIF(Doc_Register!$A:$A,$A13&"-*")) | H13: =IF($A13="","",$A13&"-[الموقع]-"&TEXT($G13+1,"0000"))
A14: MJE | B14: قيد يومية/تسوية | C14: نموذج 24-25 | D14: Manual_JE | E14: 1 | F14: MJE-BR01-0001 | G14: =IF($A14="","",COUNTIF(Doc_Register!$A:$A,$A14&"-*")) | H14: =IF($A14="","",$A14&"-[الموقع]-"&TEXT($G14+1,"0000"))
A15: PR | B15: طلب شراء | C15: نموذج 1 | D15: PR | E15: 2 | F15: PR-BR01-0001 | G15: =IF($A15="","",COUNTIF(Doc_Register!$A:$A,$A15&"-*")) | H15: =IF($A15="","",$A15&"-[الموقع]-"&TEXT($G15+1,"0000"))
A16: PO | B16: أمر شراء | C16: نموذج 2 | D16: PO | E16: 2 | F16: PO-BR01-0001 | G16: =IF($A16="","",COUNTIF(Doc_Register!$A:$A,$A16&"-*")) | H16: =IF($A16="","",$A16&"-[الموقع]-"&TEXT($G16+1,"0000"))
... A29: CLS | B29: محضر إقفال شهر | C29: نموذج 26 | D29: Period_Close | E29: 1 | F29: CLS-BR01-0001 | G29: =IF($A29="","",COUNTIF(Doc_Register!$A:$A,$A29&"-*")) | H29: =IF($A29="","",$A29&"-[الموقع]-"&TEXT($G29+1,"0000"))
G30: =IF($A30="","",COUNTIF(Doc_Register!$A:$A,$A30&"-*")) | H30: =IF($A30="","",$A30&"-[الموقع]-"&TEXT($G30+1,"0000"))
G31: =IF($A31="","",COUNTIF(Doc_Register!$A:$A,$A31&"-*")) | H31: =IF($A31="","",$A31&"-[الموقع]-"&TEXT($G31+1,"0000"))
G32: =IF($A32="","",COUNTIF(Doc_Register!$A:$A,$A32&"-*")) | H32: =IF($A32="","",$A32&"-[الموقع]-"&TEXT($G32+1,"0000"))
G33: =IF($A33="","",COUNTIF(Doc_Register!$A:$A,$A33&"-*")) | H33: =IF($A33="","",$A33&"-[الموقع]-"&TEXT($G33+1,"0000"))
G34: =IF($A34="","",COUNTIF(Doc_Register!$A:$A,$A34&"-*")) | H34: =IF($A34="","",$A34&"-[الموقع]-"&TEXT($G34+1,"0000"))
G35: =IF($A35="","",COUNTIF(Doc_Register!$A:$A,$A35&"-*")) | H35: =IF($A35="","",$A35&"-[الموقع]-"&TEXT($G35+1,"0000"))
G36: =IF($A36="","",COUNTIF(Doc_Register!$A:$A,$A36&"-*")) | H36: =IF($A36="","",$A36&"-[الموقع]-"&TEXT($G36+1,"0000"))
G37: =IF($A37="","",COUNTIF(Doc_Register!$A:$A,$A37&"-*")) | H37: =IF($A37="","",$A37&"-[الموقع]-"&TEXT($G37+1,"0000"))
G38: =IF($A38="","",COUNTIF(Doc_Register!$A:$A,$A38&"-*")) | H38: =IF($A38="","",$A38&"-[الموقع]-"&TEXT($G38+1,"0000"))
G39: =IF($A39="","",COUNTIF(Doc_Register!$A:$A,$A39&"-*")) | H39: =IF($A39="","",$A39&"-[الموقع]-"&TEXT($G39+1,"0000"))
G40: =IF($A40="","",COUNTIF(Doc_Register!$A:$A,$A40&"-*")) | H40: =IF($A40="","",$A40&"-[الموقع]-"&TEXT($G40+1,"0000"))
G41: =IF($A41="","",COUNTIF(Doc_Register!$A:$A,$A41&"-*")) | H41: =IF($A41="","",$A41&"-[الموقع]-"&TEXT($G41+1,"0000"))
... G44: =IF($A44="","",COUNTIF(Doc_Register!$A:$A,$A44&"-*")) | H44: =IF($A44="","",$A44&"-[الموقع]-"&TEXT($G44+1,"0000"))

Sheet Doc_Register
A1: السجل المركزي لأرقام المستندات (Document Register)
A2: سجل آلي بكل أرقام المستندات من كل الأوراق لمنع التكرار. لا تُدخل شيئًا هنا؛ أي رقم مكرر يظهر في عمود (تكرار) ويمنع ترحيل المستند.
A3: خلايا الإدخال | B3: معادلات (لا تعدّل)
A4: رقم المستند | B4: النوع | C4: التاريخ | D4: الموقع | E4: المبلغ | F4: الحالة | G4: ورقة المصدر | H4: تكرار؟ | I4: فحص
A5: =IF(Sales_Daily!$A5="","",Sales_Daily!$A5) | B5: =IF($A5="","","SAL") | C5: =IF($A5="","",Sales_Daily!$B5) | D5: =IF($A5="","",Sales_Daily!$C5) | E5: =IF($A5="","",Sales_Daily!$AA5) | F5: =IF($A5="","",Sales_Daily!$S5) | G5: =IF($A5="","","Sales_Daily") | H5: =IF($A5="","",IF(COUNTIF($A:$A,$A5)>1,"مكرر","")) | I5: =IF($H5="مكرر","مكرر","")
A6: =IF(Sales_Daily!$A6="","",Sales_Daily!$A6) | B6: =IF($A6="","","SAL") | C6: =IF($A6="","",Sales_Daily!$B6) | D6: =IF($A6="","",Sales_Daily!$C6) | E6: =IF($A6="","",Sales_Daily!$AA6) | F6: =IF($A6="","",Sales_Daily!$S6) | G6: =IF($A6="","","Sales_Daily") | H6: =IF($A6="","",IF(COUNTIF($A:$A,$A6)>1,"مكرر","")) | I6: =IF($H6="مكرر","مكرر","")
A7: =IF(Sales_Daily!$A7="","",Sales_Daily!$A7) | B7: =IF($A7="","","SAL") | C7: =IF($A7="","",Sales_Daily!$B7) | D7: =IF($A7="","",Sales_Daily!$C7) | E7: =IF($A7="","",Sales_Daily!$AA7) | F7: =IF($A7="","",Sales_Daily!$S7) | G7: =IF($A7="","","Sales_Daily") | H7: =IF($A7="","",IF(COUNTIF($A:$A,$A7)>1,"مكرر","")) | I7: =IF($H7="مكرر","مكرر","")
A8: =IF(Sales_Daily!$A8="","",Sales_Daily!$A8) | B8: =IF($A8="","","SAL") | C8: =IF($A8="","",Sales_Daily!$B8) | D8: =IF($A8="","",Sales_Daily!$C8) | E8: =IF($A8="","",Sales_Daily!$AA8) | F8: =IF($A8="","",Sales_Daily!$S8) | G8: =IF($A8="","","Sales_Daily") | H8: =IF($A8="","",IF(COUNTIF($A:$A,$A8)>1,"مكرر","")) | I8: =IF($H8="مكرر","مكرر","")
A9: =IF(Sales_Daily!$A9="","",Sales_Daily!$A9) | B9: =IF($A9="","","SAL") | C9: =IF($A9="","",Sales_Daily!$B9) | D9: =IF($A9="","",Sales_Daily!$C9) | E9: =IF($A9="","",Sales_Daily!$AA9) | F9: =IF($A9="","",Sales_Daily!$S9) | G9: =IF($A9="","","Sales_Daily") | H9: =IF($A9="","",IF(COUNTIF($A:$A,$A9)>1,"مكرر","")) | I9: =IF($H9="مكرر","مكرر","")
A10: =IF(Sales_Daily!$A10="","",Sales_Daily!$A10) | B10: =IF($A10="","","SAL") | C10: =IF($A10="","",Sales_Daily!$B10) | D10: =IF($A10="","",Sales_Daily!$C10) | E10: =IF($A10="","",Sales_Daily!$AA10) | F10: =IF($A10="","",Sales_Daily!$S10) | G10: =IF($A10="","","Sales_Daily") | H10: =IF($A10="","",IF(COUNTIF($A:$A,$A10)>1,"مكرر","")) | I10: =IF($H10="مكرر","مكرر","")
A11: =IF(Sales_Daily!$A11="","",Sales_Daily!$A11) | B11: =IF($A11="","","SAL") | C11: =IF($A11="","",Sales_Daily!$B11) | D11: =IF($A11="","",Sales_Daily!$C11) | E11: =IF($A11="","",Sales_Daily!$AA11) | F11: =IF($A11="","",Sales_Daily!$S11) | G11: =IF($A11="","","Sales_Daily") | H11: =IF($A11="","",IF(COUNTIF($A:$A,$A11)>1,"مكرر","")) | I11: =IF($H11="مكرر","مكرر","")
A12: =IF(Sales_Daily!$A12="","",Sales_Daily!$A12) | B12: =IF($A12="","","SAL") | C12: =IF($A12="","",Sales_Daily!$B12) | D12: =IF($A12="","",Sales_Daily!$C12) | E12: =IF($A12="","",Sales_Daily!$AA12) | F12: =IF($A12="","",Sales_Daily!$S12) | G12: =IF($A12="","","Sales_Daily") | H12: =IF($A12="","",IF(COUNTIF($A:$A,$A12)>1,"مكرر","")) | I12: =IF($H12="مكرر","مكرر","")
A13: =IF(Sales_Daily!$A13="","",Sales_Daily!$A13) | B13: =IF($A13="","","SAL") | C13: =IF($A13="","",Sales_Daily!$B13) | D13: =IF($A13="","",Sales_Daily!$C13) | E13: =IF($A13="","",Sales_Daily!$AA13) | F13: =IF($A13="","",Sales_Daily!$S13) | G13: =IF($A13="","","Sales_Daily") | H13: =IF($A13="","",IF(COUNTIF($A:$A,$A13)>1,"مكرر","")) | I13: =IF($H13="مكرر","مكرر","")
A14: =IF(Sales_Daily!$A14="","",Sales_Daily!$A14) | B14: =IF($A14="","","SAL") | C14: =IF($A14="","",Sales_Daily!$B14) | D14: =IF($A14="","",Sales_Daily!$C14) | E14: =IF($A14="","",Sales_Daily!$AA14) | F14: =IF($A14="","",Sales_Daily!$S14) | G14: =IF($A14="","","Sales_Daily") | H14: =IF($A14="","",IF(COUNTIF($A:$A,$A14)>1,"مكرر","")) | I14: =IF($H14="مكرر","مكرر","")
A15: =IF(Sales_Daily!$A15="","",Sales_Daily!$A15) | B15: =IF($A15="","","SAL") | C15: =IF($A15="","",Sales_Daily!$B15) | D15: =IF($A15="","",Sales_Daily!$C15) | E15: =IF($A15="","",Sales_Daily!$AA15) | F15: =IF($A15="","",Sales_Daily!$S15) | G15: =IF($A15="","","Sales_Daily") | H15: =IF($A15="","",IF(COUNTIF($A:$A,$A15)>1,"مكرر","")) | I15: =IF($H15="مكرر","مكرر","")
A16: =IF(Sales_Daily!$A16="","",Sales_Daily!$A16) | B16: =IF($A16="","","SAL") | C16: =IF($A16="","",Sales_Daily!$B16) | D16: =IF($A16="","",Sales_Daily!$C16) | E16: =IF($A16="","",Sales_Daily!$AA16) | F16: =IF($A16="","",Sales_Daily!$S16) | G16: =IF($A16="","","Sales_Daily") | H16: =IF($A16="","",IF(COUNTIF($A:$A,$A16)>1,"مكرر","")) | I16: =IF($H16="مكرر","مكرر","")
... A60: =IF(Sales_Daily!$A60="","",Sales_Daily!$A60) | B60: =IF($A60="","","SAL") | C60: =IF($A60="","",Sales_Daily!$B60) | D60: =IF($A60="","",Sales_Daily!$C60) | E60: =IF($A60="","",Sales_Daily!$AA60) | F60: =IF($A60="","",Sales_Daily!$S60) | G60: =IF($A60="","","Sales_Daily") | H60: =IF($A60="","",IF(COUNTIF($A:$A,$A60)>1,"مكرر","")) | I60: =IF($H60="مكرر","مكرر","")
A61: =IF(Platform_Settlements!$A5="","",Platform_Settlements!$A5) | B61: =IF($A61="","","PLT") | C61: =IF($A61="","",Platform_Settlements!$B5) | D61: =IF($A61="","",Platform_Settlements!$D5) | E61: =IF($A61="","",Platform_Settlements!$J5) | F61: =IF($A61="","",Platform_Settlements!$L5) | G61: =IF($A61="","","Platform_Settlements") | H61: =IF($A61="","",IF(COUNTIF($A:$A,$A61)>1,"مكرر","")) | I61: =IF($H61="مكرر","مكرر","")
A62: =IF(Platform_Settlements!$A6="","",Platform_Settlements!$A6) | B62: =IF($A62="","","PLT") | C62: =IF($A62="","",Platform_Settlements!$B6) | D62: =IF($A62="","",Platform_Settlements!$D6) | E62: =IF($A62="","",Platform_Settlements!$J6) | F62: =IF($A62="","",Platform_Settlements!$L6) | G62: =IF($A62="","","Platform_Settlements") | H62: =IF($A62="","",IF(COUNTIF($A:$A,$A62)>1,"مكرر","")) | I62: =IF($H62="مكرر","مكرر","")
A63: =IF(Platform_Settlements!$A7="","",Platform_Settlements!$A7) | B63: =IF($A63="","","PLT") | C63: =IF($A63="","",Platform_Settlements!$B7) | D63: =IF($A63="","",Platform_Settlements!$D7) | E63: =IF($A63="","",Platform_Settlements!$J7) | F63: =IF($A63="","",Platform_Settlements!$L7) | G63: =IF($A63="","","Platform_Settlements") | H63: =IF($A63="","",IF(COUNTIF($A:$A,$A63)>1,"مكرر","")) | I63: =IF($H63="مكرر","مكرر","")
A64: =IF(Platform_Settlements!$A8="","",Platform_Settlements!$A8) | B64: =IF($A64="","","PLT") | C64: =IF($A64="","",Platform_Settlements!$B8) | D64: =IF($A64="","",Platform_Settlements!$D8) | E64: =IF($A64="","",Platform_Settlements!$J8) | F64: =IF($A64="","",Platform_Settlements!$L8) | G64: =IF($A64="","","Platform_Settlements") | H64: =IF($A64="","",IF(COUNTIF($A:$A,$A64)>1,"مكرر","")) | I64: =IF($H64="مكرر","مكرر","")
A65: =IF(Platform_Settlements!$A9="","",Platform_Settlements!$A9) | B65: =IF($A65="","","PLT") | C65: =IF($A65="","",Platform_Settlements!$B9) | D65: =IF($A65="","",Platform_Settlements!$D9) | E65: =IF($A65="","",Platform_Settlements!$J9) | F65: =IF($A65="","",Platform_Settlements!$L9) | G65: =IF($A65="","","Platform_Settlements") | H65: =IF($A65="","",IF(COUNTIF($A:$A,$A65)>1,"مكرر","")) | I65: =IF($H65="مكرر","مكرر","")
A66: =IF(Platform_Settlements!$A10="","",Platform_Settlements!$A10) | B66: =IF($A66="","","PLT") | C66: =IF($A66="","",Platform_Settlements!$B10) | D66: =IF($A66="","",Platform_Settlements!$D10) | E66: =IF($A66="","",Platform_Settlements!$J10) | F66: =IF($A66="","",Platform_Settlements!$L10) | G66: =IF($A66="","","Platform_Settlements") | H66: =IF($A66="","",IF(COUNTIF($A:$A,$A66)>1,"مكرر","")) | I66: =IF($H66="مكرر","مكرر","")
A67: =IF(Platform_Settlements!$A11="","",Platform_Settlements!$A11) | B67: =IF($A67="","","PLT") | C67: =IF($A67="","",Platform_Settlements!$B11) | D67: =IF($A67="","",Platform_Settlements!$D11) | E67: =IF($A67="","",Platform_Settlements!$J11) | F67: =IF($A67="","",Platform_Settlements!$L11) | G67: =IF($A67="","","Platform_Settlements") | H67: =IF($A67="","",IF(COUNTIF($A:$A,$A67)>1,"مكرر","")) | I67: =IF($H67="مكرر","مكرر","")
A68: =IF(Platform_Settlements!$A12="","",Platform_Settlements!$A12) | B68: =IF($A68="","","PLT") | C68: =IF($A68="","",Platform_Settlements!$B12) | D68: =IF($A68="","",Platform_Settlements!$D12) | E68: =IF($A68="","",Platform_Settlements!$J12) | F68: =IF($A68="","",Platform_Settlements!$L12) | G68: =IF($A68="","","Platform_Settlements") | H68: =IF($A68="","",IF(COUNTIF($A:$A,$A68)>1,"مكرر","")) | I68: =IF($H68="مكرر","مكرر","")
A69: =IF(Platform_Settlements!$A13="","",Platform_Settlements!$A13) | B69: =IF($A69="","","PLT") | C69: =IF($A69="","",Platform_Settlements!$B13) | D69: =IF($A69="","",Platform_Settlements!$D13) | E69: =IF($A69="","",Platform_Settlements!$J13) | F69: =IF($A69="","",Platform_Settlements!$L13) | G69: =IF($A69="","","Platform_Settlements") | H69: =IF($A69="","",IF(COUNTIF($A:$A,$A69)>1,"مكرر","")) | I69: =IF($H69="مكرر","مكرر","")
A70: =IF(Platform_Settlements!$A14="","",Platform_Settlements!$A14) | B70: =IF($A70="","","PLT") | C70: =IF($A70="","",Platform_Settlements!$B14) | D70: =IF($A70="","",Platform_Settlements!$D14) | E70: =IF($A70="","",Platform_Settlements!$J14) | F70: =IF($A70="","",Platform_Settlements!$L14) | G70: =IF($A70="","","Platform_Settlements") | H70: =IF($A70="","",IF(COUNTIF($A:$A,$A70)>1,"مكرر","")) | I70: =IF($H70="مكرر","مكرر","")
A71: =IF(Platform_Settlements!$A15="","",Platform_Settlements!$A15) | B71: =IF($A71="","","PLT") | C71: =IF($A71="","",Platform_Settlements!$B15) | D71: =IF($A71="","",Platform_Settlements!$D15) | E71: =IF($A71="","",Platform_Settlements!$J15) | F71: =IF($A71="","",Platform_Settlements!$L15) | G71: =IF($A71="","","Platform_Settlements") | H71: =IF($A71="","",IF(COUNTIF($A:$A,$A71)>1,"مكرر","")) | I71: =IF($H71="مكرر","مكرر","")
A72: =IF(Platform_Settlements!$A16="","",Platform_Settlements!$A16) | B72: =IF($A72="","","PLT") | C72: =IF($A72="","",Platform_Settlements!$B16) | D72: =IF($A72="","",Platform_Settlements!$D16) | E72: =IF($A72="","",Platform_Settlements!$J16) | F72: =IF($A72="","",Platform_Settlements!$L16) | G72: =IF($A72="","","Platform_Settlements") | H72: =IF($A72="","",IF(COUNTIF($A:$A,$A72)>1,"مكرر","")) | I72: =IF($H72="مكرر","مكرر","")
... A76: =IF(Platform_Settlements!$A20="","",Platform_Settlements!$A20) | B76: =IF($A76="","","PLT") | C76: =IF($A76="","",Platform_Settlements!$B20) | D76: =IF($A76="","",Platform_Settlements!$D20) | E76: =IF($A76="","",Platform_Settlements!$J20) | F76: =IF($A76="","",Platform_Settlements!$L20) | G76: =IF($A76="","","Platform_Settlements") | H76: =IF($A76="","",IF(COUNTIF($A:$A,$A76)>1,"مكرر","")) | I76: =IF($H76="مكرر","مكرر","")
A77: =IF(Cash_Vouchers!$A5="","",Cash_Vouchers!$A5) | B77: =IF($A77="","","CV") | C77: =IF($A77="","",Cash_Vouchers!$B5) | D77: =IF($A77="","",Cash_Vouchers!$Y5) | E77: =IF($A77="","",Cash_Vouchers!$I5) | F77: =IF($A77="","",Cash_Vouchers!$N5) | G77: =IF($A77="","","Cash_Vouchers") | H77: =IF($A77="","",IF(COUNTIF($A:$A,$A77)>1,"مكرر","")) | I77: =IF($H77="مكرر","مكرر","")
A78: =IF(Cash_Vouchers!$A6="","",Cash_Vouchers!$A6) | B78: =IF($A78="","","CV") | C78: =IF($A78="","",Cash_Vouchers!$B6) | D78: =IF($A78="","",Cash_Vouchers!$Y6) | E78: =IF($A78="","",Cash_Vouchers!$I6) | F78: =IF($A78="","",Cash_Vouchers!$N6) | G78: =IF($A78="","","Cash_Vouchers") | H78: =IF($A78="","",IF(COUNTIF($A:$A,$A78)>1,"مكرر","")) | I78: =IF($H78="مكرر","مكرر","")
A79: =IF(Cash_Vouchers!$A7="","",Cash_Vouchers!$A7) | B79: =IF($A79="","","CV") | C79: =IF($A79="","",Cash_Vouchers!$B7) | D79: =IF($A79="","",Cash_Vouchers!$Y7) | E79: =IF($A79="","",Cash_Vouchers!$I7) | F79: =IF($A79="","",Cash_Vouchers!$N7) | G79: =IF($A79="","","Cash_Vouchers") | H79: =IF($A79="","",IF(COUNTIF($A:$A,$A79)>1,"مكرر","")) | I79: =IF($H79="مكرر","مكرر","")
A80: =IF(Cash_Vouchers!$A8="","",Cash_Vouchers!$A8) | B80: =IF($A80="","","CV") | C80: =IF($A80="","",Cash_Vouchers!$B8) | D80: =IF($A80="","",Cash_Vouchers!$Y8) | E80: =IF($A80="","",Cash_Vouchers!$I8) | F80: =IF($A80="","",Cash_Vouchers!$N8) | G80: =IF($A80="","","Cash_Vouchers") | H80: =IF($A80="","",IF(COUNTIF($A:$A,$A80)>1,"مكرر","")) | I80: =IF($H80="مكرر","مكرر","")
A81: =IF(Cash_Vouchers!$A9="","",Cash_Vouchers!$A9) | B81: =IF($A81="","","CV") | C81: =IF($A81="","",Cash_Vouchers!$B9) | D81: =IF($A81="","",Cash_Vouchers!$Y9) | E81: =IF($A81="","",Cash_Vouchers!$I9) | F81: =IF($A81="","",Cash_Vouchers!$N9) | G81: =IF($A81="","","Cash_Vouchers") | H81: =IF($A81="","",IF(COUNTIF($A:$A,$A81)>1,"مكرر","")) | I81: =IF($H81="مكرر","مكرر","")
A82: =IF(Cash_Vouchers!$A10="","",Cash_Vouchers!$A10) | B82: =IF($A82="","","CV") | C82: =IF($A82="","",Cash_Vouchers!$B10) | D82: =IF($A82="","",Cash_Vouchers!$Y10) | E82: =IF($A82="","",Cash_Vouchers!$I10) | F82: =IF($A82="","",Cash_Vouchers!$N10) | G82: =IF($A82="","","Cash_Vouchers") | H82: =IF($A82="","",IF(COUNTIF($A:$A,$A82)>1,"مكرر","")) | I82: =IF($H82="مكرر","مكرر","")
A83: =IF(Cash_Vouchers!$A11="","",Cash_Vouchers!$A11) | B83: =IF($A83="","","CV") | C83: =IF($A83="","",Cash_Vouchers!$B11) | D83: =IF($A83="","",Cash_Vouchers!$Y11) | E83: =IF($A83="","",Cash_Vouchers!$I11) | F83: =IF($A83="","",Cash_Vouchers!$N11) | G83: =IF($A83="","","Cash_Vouchers") | H83: =IF($A83="","",IF(COUNTIF($A:$A,$A83)>1,"مكرر","")) | I83: =IF($H83="مكرر","مكرر","")
A84: =IF(Cash_Vouchers!$A12="","",Cash_Vouchers!$A12) | B84: =IF($A84="","","CV") | C84: =IF($A84="","",Cash_Vouchers!$B12) | D84: =IF($A84="","",Cash_Vouchers!$Y12) | E84: =IF($A84="","",Cash_Vouchers!$I12) | F84: =IF($A84="","",Cash_Vouchers!$N12) | G84: =IF($A84="","","Cash_Vouchers") | H84: =IF($A84="","",IF(COUNTIF($A:$A,$A84)>1,"مكرر","")) | I84: =IF($H84="مكرر","مكرر","")
A85: =IF(Cash_Vouchers!$A13="","",Cash_Vouchers!$A13) | B85: =IF($A85="","","CV") | C85: =IF($A85="","",Cash_Vouchers!$B13) | D85: =IF($A85="","",Cash_Vouchers!$Y13) | E85: =IF($A85="","",Cash_Vouchers!$I13) | F85: =IF($A85="","",Cash_Vouchers!$N13) | G85: =IF($A85="","","Cash_Vouchers") | H85: =IF($A85="","",IF(COUNTIF($A:$A,$A85)>1,"مكرر","")) | I85: =IF($H85="مكرر","مكرر","")
A86: =IF(Cash_Vouchers!$A14="","",Cash_Vouchers!$A14) | B86: =IF($A86="","","CV") | C86: =IF($A86="","",Cash_Vouchers!$B14) | D86: =IF($A86="","",Cash_Vouchers!$Y14) | E86: =IF($A86="","",Cash_Vouchers!$I14) | F86: =IF($A86="","",Cash_Vouchers!$N14) | G86: =IF($A86="","","Cash_Vouchers") | H86: =IF($A86="","",IF(COUNTIF($A:$A,$A86)>1,"مكرر","")) | I86: =IF($H86="مكرر","مكرر","")
A87: =IF(Cash_Vouchers!$A15="","",Cash_Vouchers!$A15) | B87: =IF($A87="","","CV") | C87: =IF($A87="","",Cash_Vouchers!$B15) | D87: =IF($A87="","",Cash_Vouchers!$Y15) | E87: =IF($A87="","",Cash_Vouchers!$I15) | F87: =IF($A87="","",Cash_Vouchers!$N15) | G87: =IF($A87="","","Cash_Vouchers") | H87: =IF($A87="","",IF(COUNTIF($A:$A,$A87)>1,"مكرر","")) | I87: =IF($H87="مكرر","مكرر","")
A88: =IF(Cash_Vouchers!$A16="","",Cash_Vouchers!$A16) | B88: =IF($A88="","","CV") | C88: =IF($A88="","",Cash_Vouchers!$B16) | D88: =IF($A88="","",Cash_Vouchers!$Y16) | E88: =IF($A88="","",Cash_Vouchers!$I16) | F88: =IF($A88="","",Cash_Vouchers!$N16) | G88: =IF($A88="","","Cash_Vouchers") | H88: =IF($A88="","",IF(COUNTIF($A:$A,$A88)>1,"مكرر","")) | I88: =IF($H88="مكرر","مكرر","")
... A156: =IF(Cash_Vouchers!$A84="","",Cash_Vouchers!$A84) | B156: =IF($A156="","","CV") | C156: =IF($A156="","",Cash_Vouchers!$B84) | D156: =IF($A156="","",Cash_Vouchers!$Y84) | E156: =IF($A156="","",Cash_Vouchers!$I84) | F156: =IF($A156="","",Cash_Vouchers!$N84) | G156: =IF($A156="","","Cash_Vouchers") | H156: =IF($A156="","",IF(COUNTIF($A:$A,$A156)>1,"مكرر","")) | I156: =IF($H156="مكرر","مكرر","")
